Workbook

Sheet 1_Data Entry
A1: Sale Tracker — Structured Workbook (App Revision v34)
A2: Manual entry tab. One row per buy lot. For partial sales, split into multiple rows. Column L is optional for manual replacement-lot override. Asset Description auto-fills from the reference table.
A5: Entry # | B5: Status | C5: Sleeve | D5: Asset Type | E5: Ticker | F5: Asset Description | G5: Buy Date | H5: Shares Bought | I5: Cost / Share | J5: Sell Date | K5: Shares Sold | L5: Sale Price / Share | M5: Shares Remaining | N5: Notes
A6: =IF($E6="","",IF(COUNTA(C6:N6)=0,"",ROW()-5)) -> 1 | B6: =IF(E6="","",IF(DataEntryTable[[#This Row],[Sell Date]]="","Open","Closed")) -> Closed | C6: =IF(E6="","",IFERROR(VLOOKUP(UPPER(TRIM(E6)),'6_Reference Lists'!$A$4:$D$64,2,FALSE()),"")) -> US | D6: =IF(E6="","",IFERROR(VLOOKUP(UPPER(TRIM(E6)),'6_Reference Lists'!$A$4:$D$64,3,FALSE()),"")) -> MLP | E6: EPD | F6: =IF(E6="","",IFERROR(VLOOKUP(UPPER(TRIM(E6)),'6_Reference Lists'!$A$4:$D$64,4,FALSE()),"")) -> Enterprise Products Partners L.P. | G6: 45338 | H6: 580 | I6: 27.25 | J6: 46090 | K6: 580 | L6: 38.15 | M6: =IF(E6="","",DataEntryTable[[#This Row],[Shares Bought]]-DataEntryTable[[#This Row],[Shares Sold]]) -> 0
A7: =IF($E7="","",IF(COUNTA(C7:N7)=0,"",ROW()-5)) -> 2 | B7: =IF(E7="","",IF(DataEntryTable[[#This Row],[Sell Date]]="","Open","Closed")) -> Closed | C7: =IF(E7="","",IFERROR(VLOOKUP(UPPER(TRIM(E7)),'6_Reference Lists'!$A$4:$D$64,2,FALSE()),"")) -> US | D7: =IF(E7="","",IFERROR(VLOOKUP(UPPER(TRIM(E7)),'6_Reference Lists'!$A$4:$D$64,3,FALSE()),"")) -> MLP | E7: EPD | F7: =IF(E7="","",IFERROR(VLOOKUP(UPPER(TRIM(E7)),'6_Reference Lists'!$A$4:$D$64,4,FALSE()),"")) -> Enterprise Products Partners L.P. | G7: 45338 | H7: 615 | I7: 27.25 | J7: 46090 | K7: 615 | L7: 38.15 | M7: =IF(E7="","",DataEntryTable[[#This Row],[Shares Bought]]-DataEntryTable[[#This Row],[Shares Sold]]) -> 0
A8: =IF($E8="","",IF(COUNTA(C8:N8)=0,"",ROW()-5)) -> 3 | B8: =IF(E8="","",IF(DataEntryTable[[#This Row],[Sell Date]]="","Open","Closed")) -> Closed | C8: =IF(E8="","",IFERROR(VLOOKUP(UPPER(TRIM(E8)),'6_Reference Lists'!$A$4:$D$64,2,FALSE()),"")) -> US | D8: =IF(E8="","",IFERROR(VLOOKUP(UPPER(TRIM(E8)),'6_Reference Lists'!$A$4:$D$64,3,FALSE()),"")) -> MLP | E8: EPD | F8: =IF(E8="","",IFERROR(VLOOKUP(UPPER(TRIM(E8)),'6_Reference Lists'!$A$4:$D$64,4,FALSE()),"")) -> Enterprise Products Partners L.P. | G8: 45706 | H8: 580 | I8: 33.72 | J8: 46090 | K8: 580 | L8: 38.15 | M8: =IF(E8="","",DataEntryTable[[#This Row],[Shares Bought]]-DataEntryTable[[#This Row],[Shares Sold]]) -> 0
A9: =IF($E9="","",IF(COUNTA(C9:N9)=0,"",ROW()-5)) -> 4 | B9: =IF(E9="","",IF(DataEntryTable[[#This Row],[Sell Date]]="","Open","Closed")) -> Closed | C9: =IF(E9="","",IFERROR(VLOOKUP(UPPER(TRIM(E9)),'6_Reference Lists'!$A$4:$D$64,2,FALSE()),"")) -> US | D9: =IF(E9="","",IFERROR(VLOOKUP(UPPER(TRIM(E9)),'6_Reference Lists'!$A$4:$D$64,3,FALSE()),"")) -> MLP | E9: EPD | F9: =IF(E9="","",IFERROR(VLOOKUP(UPPER(TRIM(E9)),'6_Reference Lists'!$A$4:$D$64,4,FALSE()),"")) -> Enterprise Products Partners L.P. | G9: 45706 | H9: 30 | I9: 33.72 | J9: 46090 | K9: 30 | L9: 38 | M9: =IF(E9="","",DataEntryTable[[#This Row],[Shares Bought]]-DataEntryTable[[#This Row],[Shares Sold]]) -> 0
A10: =IF($E10="","",IF(COUNTA(C10:N10)=0,"",ROW()-5)) -> 5 | B10: =IF(E10="","",IF(DataEntryTable[[#This Row],[Sell Date]]="","Open","Closed")) -> Closed | C10: =IF(E10="","",IFERROR(VLOOKUP(UPPER(TRIM(E10)),'6_Reference Lists'!$A$4:$D$64,2,FALSE()),"")) -> US | D10: =IF(E10="","",IFERROR(VLOOKUP(UPPER(TRIM(E10)),'6_Reference Lists'!$A$4:$D$64,3,FALSE()),"")) -> MLP | E10: EPD | F10: =IF(E10="","",IFERROR(VLOOKUP(UPPER(TRIM(E10)),'6_Reference Lists'!$A$4:$D$64,4,FALSE()),"")) -> Enterprise Products Partners L.P. | G10: 45706 | H10: 585 | I10: 33.72 | J10: 46090 | K10: 585 | L10: 38 | M10: =IF(E10="","",DataEntryTable[[#This Row],[Shares Bought]]-DataEntryTable[[#This Row],[Shares Sold]]) -> 0
A11: =IF($E11="","",IF(COUNTA(C11:N11)=0,"",ROW()-5)) -> 6 | B11: =IF(E11="","",IF(DataEntryTable[[#This Row],[Sell Date]]="","Open","Closed")) -> Closed | C11: =IF(E11="","",IFERROR(VLOOKUP(UPPER(TRIM(E11)),'6_Reference Lists'!$A$4:$D$64,2,FALSE()),"")) -> US | D11: =IF(E11="","",IFERROR(VLOOKUP(UPPER(TRIM(E11)),'6_Reference Lists'!$A$4:$D$64,3,FALSE()),"")) -> MLP | E11: EPD | F11: =IF(E11="","",IFERROR(VLOOKUP(UPPER(TRIM(E11)),'6_Reference Lists'!$A$4:$D$64,4,FALSE()),"")) -> Enterprise Products Partners L.P. | G11: 45706 | H11: 562 | I11: 33.72 | J11: 46090 | K11: 562 | L11: 38 | M11: =IF(E11="","",DataEntryTable[[#This Row],[Shares Bought]]-DataEntryTable[[#This Row],[Shares Sold]]) -> 0
A12: =IF($E12="","",IF(COUNTA(C12:N12)=0,"",ROW()-5)) -> 7 | B12: =IF(E12="","",IF(DataEntryTable[[#This Row],[Sell Date]]="","Open","Closed")) -> Closed | C12: =IF(E12="","",IFERROR(VLOOKUP(UPPER(TRIM(E12)),'6_Reference Lists'!$A$4:$D$64,2,FALSE()),"")) -> US | D12: =IF(E12="","",IFERROR(VLOOKUP(UPPER(TRIM(E12)),'6_Reference Lists'!$A$4:$D$64,3,FALSE()),"")) -> MLP | E12: EPD | F12: =IF(E12="","",IFERROR(VLOOKUP(UPPER(TRIM(E12)),'6_Reference Lists'!$A$4:$D$64,4,FALSE()),"")) -> Enterprise Products Partners L.P. | G12: 45706 | H12: 580 | I12: 33.72 | J12: 46090 | K12: 580 | L12: 38 | M12: =IF(E12="","",DataEntryTable[[#This Row],[Shares Bought]]-DataEntryTable[[#This Row],[Shares Sold]]) -> 0
A13: =IF($E13="","",IF(COUNTA(C13:N13)=0,"",ROW()-5)) -> 8 | B13: =IF(E13="","",IF(DataEntryTable[[#This Row],[Sell Date]]="","Open","Closed")) -> Closed | C13: =IF(E13="","",IFERROR(VLOOKUP(UPPER(TRIM(E13)),'6_Reference Lists'!$A$4:$D$64,2,FALSE()),"")) -> US | D13: =IF(E13="","",IFERROR(VLOOKUP(UPPER(TRIM(E13)),'6_Reference Lists'!$A$4:$D$64,3,FALSE()),"")) -> MLP | E13: EPD | F13: =IF(E13="","",IFERROR(VLOOKUP(UPPER(TRIM(E13)),'6_Reference Lists'!$A$4:$D$64,4,FALSE()),"")) -> Enterprise Products Partners L.P. | G13: 45338 | H13: 580 | I13: 27.25 | J13: 46098 | K13: 580 | L13: 37.79 | M13: =IF(E13="","",DataEntryTable[[#This Row],[Shares Bought]]-DataEntryTable[[#This Row],[Shares Sold]]) -> 0
A14: =IF($E14="","",IF(COUNTA(C14:N14)=0,"",ROW()-5)) -> 9 | B14: =IF(E14="","",IF(DataEntryTable[[#This Row],[Sell Date]]="","Open","Closed")) -> Closed | C14: =IF(E14="","",IFERROR(VLOOKUP(UPPER(TRIM(E14)),'6_Reference Lists'!$A$4:$D$64,2,FALSE()),"")) -> US | D14: =IF(E14="","",IFERROR(VLOOKUP(UPPER(TRIM(E14)),'6_Reference Lists'!$A$4:$D$64,3,FALSE()),"")) -> MLP | E14: EPD | F14: =IF(E14="","",IFERROR(VLOOKUP(UPPER(TRIM(E14)),'6_Reference Lists'!$A$4:$D$64,4,FALSE()),"")) -> Enterprise Products Partners L.P. | G14: 45338 | H14: 351 | I14: 27.25 | J14: 46098 | K14: 351 | L14: 37.79 | M14: =IF(E14="","",DataEntryTable[[#This Row],[Shares Bought]]-DataEntryTable[[#This Row],[Shares Sold]]) -> 0
A15: =IF($E15="","",IF(COUNTA(C15:N15)=0,"",ROW()-5)) -> 10 | B15: =IF(E15="","",IF(DataEntryTable[[#This Row],[Sell Date]]="","Open","Closed")) -> Closed | C15: =IF(E15="","",IFERROR(VLOOKUP(UPPER(TRIM(E15)),'6_Reference Lists'!$A$4:$D$64,2,FALSE()),"")) -> US | D15: =IF(E15="","",IFERROR(VLOOKUP(UPPER(TRIM(E15)),'6_Reference Lists'!$A$4:$D$64,3,FALSE()),"")) -> ETF | E15: ITOT | F15: =IF(E15="","",IFERROR(VLOOKUP(UPPER(TRIM(E15)),'6_Reference Lists'!$A$4:$D$64,4,FALSE()),"")) -> iShares Core S&P Total U.S. Stock Market ETF | G15: 46098 | H15: 0.883 | I15: 150.63 | J15: 46101 | K15: 0.883 | L15: 142.93 | M15: =IF(E15="","",DataEntryTable[[#This Row],[Shares Bought]]-DataEntryTable[[#This Row],[Shares Sold]]) -> 0
A16: =IF($E16="","",IF(COUNTA(C16:N16)=0,"",ROW()-5)) -> 11 | B16: =IF(E16="","",IF(DataEntryTable[[#This Row],[Sell Date]]="","Open","Closed")) -> Closed | C16: =IF(E16="","",IFERROR(VLOOKUP(UPPER(TRIM(E16)),'6_Reference Lists'!$A$4:$D$64,2,FALSE()),"")) -> US | D16: =IF(E16="","",IFERROR(VLOOKUP(UPPER(TRIM(E16)),'6_Reference Lists'!$A$4:$D$64,3,FALSE()),"")) -> ETF | E16: ITOT | F16: =IF(E16="","",IFERROR(VLOOKUP(UPPER(TRIM(E16)),'6_Reference Lists'!$A$4:$D$64,4,FALSE()),"")) -> iShares Core S&P Total U.S. Stock Market ETF | G16: 46098 | H16: 143 | I16: 146.76 | J16: 46101 | K16: 143 | L16: 142.93 | M16: =IF(E16="","",DataEntryTable[[#This Row],[Shares Bought]]-DataEntryTable[[#This Row],[Shares Sold]]) -> 0
A17: =IF($E17="","",IF(COUNTA(C17:N17)=0,"",ROW()-5)) -> 12 | B17: =IF(E17="","",IF(DataEntryTable[[#This Row],[Sell Date]]="","Open","Closed")) -> Closed | C17: =IF(E17="","",IFERROR(VLOOKUP(UPPER(TRIM(E17)),'6_Reference Lists'!$A$4:$D$64,2,FALSE()),"")) -> US | D17: =IF(E17="","",IFERROR(VLOOKUP(UPPER(TRIM(E17)),'6_Reference Lists'!$A$4:$D$64,3,FALSE()),"")) -> ETF | E17: SCHB | F17: =IF(E17="","",IFERROR(VLOOKUP(UPPER(TRIM(E17)),'6_Reference Lists'!$A$4:$D$64,4,FALSE()),"")) -> Schwab U.S. Broad Market ETF | G17: 46098 | H17: 0.872 | I17: 25.951835 | J17: 46108 | K17: 0.872 | L17: 24.610092 | M17: =IF(E17="","",DataEntryTable[[#This Row],[Shares Bought]]-DataEntryTable[[#This Row],[Shares Sold]]) -> 0
A18: =IF($E18="","",IF(COUNTA(C18:N18)=0,"",ROW()-5)) -> 13 | B18: =IF(E18="","",IF(DataEntryTable[[#This Row],[Sell Date]]="","Open","Closed")) -> Closed | C18: =IF(E18="","",IFERROR(VLOOKUP(UPPER(TRIM(E18)),'6_Reference Lists'!$A$4:$D$64,2,FALSE()),"")) -> US | D18: =IF(E18="","",IFERROR(VLOOKUP(UPPER(TRIM(E18)),'6_Reference Lists'!$A$4:$D$64,3,FALSE()),"")) -> ETF | E18: SCHB | F18: =IF(E18="","",IFERROR(VLOOKUP(UPPER(TRIM(E18)),'6_Reference Lists'!$A$4:$D$64,4,FALSE()),"")) -> Schwab U.S. Broad Market ETF | G18: 46098 | H18: 813 | I18: 25.95 | J18: 46108 | K18: 813 | L18: 24.600295 | M18: =IF(E18="","",DataEntryTable[[#This Row],[Shares Bought]]-DataEntryTable[[#This Row],[Shares Sold]]) -> 0
A19: =IF($E19="","",IF(COUNTA(C19:N19)=0,"",ROW()-5)) -> 14 | B19: =IF(E19="","",IF(DataEntryTable[[#This Row],[Sell Date]]="","Open","Closed")) -> Closed | C19: =IF(E19="","",IFERROR(VLOOKUP(UPPER(TRIM(E19)),'6_Reference Lists'!$A$4:$D$64,2,FALSE()),"")) -> US | D19: =IF(E19="","",IFERROR(VLOOKUP(UPPER(TRIM(E19)),'6_Reference Lists'!$A$4:$D$64,3,FALSE()),"")) -> MLP | E19: EPD | F19: =IF(E19="","",IFERROR(VLOOKUP(UPPER(TRIM(E19)),'6_Reference Lists'!$A$4:$D$64,4,FALSE()),"")) -> Enterprise Products Partners L.P. | G19: 45960 | H19: 800 | I19: 30.53 | J19: 46111 | K19: 800 | L19: 39.05 | M19: =IF(E19="","",DataEntryTable[[#This Row],[Shares Bought]]-DataEntryTable[[#This Row],[Shares Sold]]) -> 0 | N19: Sold 800 shares @ 39.05; combined two same-day fills of 400 shares each.
A20: =IF($E20="","",IF(COUNTA(C20:N20)=0,"",ROW()-5)) -> 15 | B20: =IF(E20="","",IF(DataEntryTable[[#This Row],[Sell Date]]="","Open","Closed")) -> Open | C20: =IF(E20="","",IFERROR(VLOOKUP(UPPER(TRIM(E20)),'6_Reference Lists'!$A$4:$D$64,2,FALSE()),"")) -> US | D20: =IF(E20="","",IFERROR(VLOOKUP(UPPER(TRIM(E20)),'6_Reference Lists'!$A$4:$D$64,3,FALSE()),"")) -> ETF | E20: VTI | F20: =IF(E20="","",IFERROR(VLOOKUP(UPPER(TRIM(E20)),'6_Reference Lists'!$A$4:$D$64,4,FALSE()),"")) -> Vanguard Total Stock Market ETF | G20: 46098 | H20: 0.251 | I20: 331.83267 | K20: 0 | M20: =IF(E20="","",DataEntryTable[[#This Row],[Shares Bought]]-DataEntryTable[[#This Row],[Shares Sold]]) -> 0.251
A21: =IF($E21="","",IF(COUNTA(C21:N21)=0,"",ROW()-5)) -> 16 | B21: =IF(E21="","",IF(DataEntryTable[[#This Row],[Sell Date]]="","Open","Closed")) -> Open | C21: =IF(E21="","",IFERROR(VLOOKUP(UPPER(TRIM(E21)),'6_Reference Lists'!$A$4:$D$64,2,FALSE()),"")) -> US | D21: =IF(E21="","",IFERROR(VLOOKUP(UPPER(TRIM(E21)),'6_Reference Lists'!$A$4:$D$64,3,FALSE()),"")) -> ETF | E21: VTI | F21: =IF(E21="","",IFERROR(VLOOKUP(UPPER(TRIM(E21)),'6_Reference Lists'!$A$4:$D$64,4,FALSE()),"")) -> Vanguard Total Stock Market ETF | G21: 46098 | H21: 212 | I21: 331.8 | K21: 0 | M21: =IF(E21="","",DataEntryTable[[#This Row],[Shares Bought]]-DataEntryTable[[#This Row],[Shares Sold]]) -> 212
A22: =IF($E22="","",IF(COUNTA(C22:N22)=0,"",ROW()-5)) -> 17 | B22: =IF(E22="","",IF(DataEntryTable[[#This Row],[Sell Date]]="","Open","Closed")) -> Open | C22: =IF(E22="","",IFERROR(VLOOKUP(UPPER(TRIM(E22)),'6_Reference Lists'!$A$4:$D$64,2,FALSE()),"")) -> US | D22: =IF(E22="","",IFERROR(VLOOKUP(UPPER(TRIM(E22)),'6_Reference Lists'!$A$4:$D$64,3,FALSE()),"")) -> ETF | E22: VOO | F22: =IF(E22="","",IFERROR(VLOOKUP(UPPER(TRIM(E22)),'6_Reference Lists'!$A$4:$D$64,4,FALSE()),"")) -> Vanguard S&P 500 ETF | G22: 46099 | H22: 0.993 | I22: 614.73313 | K22: 0 | M22: =IF(E22="","",DataEntryTable[[#This Row],[Shares Bought]]-DataEntryTable[[#This Row],[Shares Sold]]) -> 0.993
A23: =IF($E23="","",IF(COUNTA(C23:N23)=0,"",ROW()-5)) -> 18 | B23: =IF(E23="","",IF(DataEntryTable[[#This Row],[Sell Date]]="","Open","Closed")) -> Open | C23: =IF(E23="","",IFERROR(VLOOKUP(UPPER(TRIM(E23)),'6_Reference Lists'!$A$4:$D$64,2,FALSE()),"")) -> US | D23: =IF(E23="","",IFERROR(VLOOKUP(UPPER(TRIM(E23)),'6_Reference Lists'!$A$4:$D$64,3,FALSE()),"")) -> ETF | E23: VOO | F23: =IF(E23="","",IFERROR(VLOOKUP(UPPER(TRIM(E23)),'6_Reference Lists'!$A$4:$D$64,4,FALSE()),"")) -> Vanguard S&P 500 ETF | G23: 46099 | H23: 40 | I23: 614.735 | K23: 0 | M23: =IF(E23="","",DataEntryTable[[#This Row],[Shares Bought]]-DataEntryTable[[#This Row],[Shares Sold]]) -> 40
A24: =IF($E24="","",IF(COUNTA(C24:N24)=0,"",ROW()-5)) -> 19 | B24: =IF(E24="","",IF(DataEntryTable[[#This Row],[Sell Date]]="","Open","Closed")) -> Open | C24: =IF(E24="","",IFERROR(VLOOKUP(UPPER(TRIM(E24)),'6_Reference Lists'!$A$4:$D$64,2,FALSE()),"")) -> US | D24: =IF(E24="","",IFERROR(VLOOKUP(UPPER(TRIM(E24)),'6_Reference Lists'!$A$4:$D$64,3,FALSE()),"")) -> ETF | E24: VOO | F24: =IF(E24="","",IFERROR(VLOOKUP(UPPER(TRIM(E24)),'6_Reference Lists'!$A$4:$D$64,4,FALSE()),"")) -> Vanguard S&P 500 ETF | G24: 46101 | H24: 34 | I24: 602.785 | K24: 0 | M24: =IF(E24="","",DataEntryTable[[#This Row],[Shares Bought]]-DataEntryTable[[#This Row],[Shares Sold]]) -> 34
A25: =IF($E25="","",IF(COUNTA(C25:N25)=0,"",ROW()-5)) -> 20 | B25: =IF(E25="","",IF(DataEntryTable[[#This Row],[Sell Date]]="","Open","Closed")) -> Open | C25: =IF(E25="","",IFERROR(VLOOKUP(UPPER(TRIM(E25)),'6_Reference Lists'!$A$4:$D$64,2,FALSE()),"")) -> US | D25: =IF(E25="","",IFERROR(VLOOKUP(UPPER(TRIM(E25)),'6_Reference Lists'!$A$4:$D$64,3,FALSE()),"")) -> ETF | E25: VOO | F25: =IF(E25="","",IFERROR(VLOOKUP(UPPER(TRIM(E25)),'6_Reference Lists'!$A$4:$D$64,4,FALSE()),"")) -> Vanguard S&P 500 ETF | G25: 46101 | H25: 0.135 | I25: 602.81481 | K25: 0 | M25: =IF(E25="","",DataEntryTable[[#This Row],[Shares Bought]]-DataEntryTable[[#This Row],[Shares Sold]]) -> 0.135
A26: =IF($E26="","",IF(COUNTA(C26:N26)=0,"",ROW()-5)) -> 21 | B26: =IF(E26="","",IF(DataEntryTable[[#This Row],[Sell Date]]="","Open","Closed")) -> Open | C26: =IF(E26="","",IFERROR(VLOOKUP(UPPER(TRIM(E26)),'6_Reference Lists'!$A$4:$D$64,2,FALSE()),"")) -> US | D26: =IF(E26="","",IFERROR(VLOOKUP(UPPER(TRIM(E26)),'6_Reference Lists'!$A$4:$D$64,3,FALSE()),"")) -> ETF | E26: VTI | F26: =IF(E26="","",IFERROR(VLOOKUP(UPPER(TRIM(E26)),'6_Reference Lists'!$A$4:$D$64,4,FALSE()),"")) -> Vanguard Total Stock Market ETF | G26: 46108 | H26: 0.736 | I26: 314.34783 | K26: 0 | M26: =IF(E26="","",DataEntryTable[[#This Row],[Shares Bought]]-DataEntryTable[[#This Row],[Shares Sold]]) -> 0.736
A27: =IF($E27="","",IF(COUNTA(C27:N27)=0,"",ROW()-5)) -> 22 | B27: =IF(E27="","",IF(DataEntryTable[[#This Row],[Sell Date]]="","Open","Closed")) -> Open | C27: =IF(E27="","",IFERROR(VLOOKUP(UPPER(TRIM(E27)),'6_Reference Lists'!$A$4:$D$64,2,FALSE()),"")) -> US | D27: =IF(E27="","",IFERROR(VLOOKUP(UPPER(TRIM(E27)),'6_Reference Lists'!$A$4:$D$64,3,FALSE()),"")) -> ETF | E27: VTI | F27: =IF(E27="","",IFERROR(VLOOKUP(UPPER(TRIM(E27)),'6_Reference Lists'!$A$4:$D$64,4,FALSE()),"")) -> Vanguard Total Stock Market ETF | G27: 46108 | H27: 63 | I27: 314.35 | K27: 0 | M27: =IF(E27="","",DataEntryTable[[#This Row],[Shares Bought]]-DataEntryTable[[#This Row],[Shares Sold]]) -> 63
A28: =IF($E28="","",IF(COUNTA(C28:N28)=0,"",ROW()-5)) -> 23 | B28: =IF(E28="","",IF(DataEntryTable[[#This Row],[Sell Date]]="","Open","Closed")) -> Closed | C28: =IF(E28="","",IFERROR(VLOOKUP(UPPER(TRIM(E28)),'6_Reference Lists'!$A$4:$D$64,2,FALSE()),"")) -> International | D28: =IF(E28="","",IFERROR(VLOOKUP(UPPER(TRIM(E28)),'6_Reference Lists'!$A$4:$D$64,3,FALSE()),"")) -> ETF | E28: IXUS | F28: =IF(E28="","",IFERROR(VLOOKUP(UPPER(TRIM(E28)),'6_Reference Lists'!$A$4:$D$64,4,FALSE()),"")) -> iShares Core MSCI Total International Stock ETF | G28: 46098 | H28: 157.003 | I28: 88.55 | J28: 46101 | K28: 157.003 | L28: 83.55 | M28: =IF(E28="","",DataEntryTable[[#This Row],[Shares Bought]]-DataEntryTable[[#This Row],[Shares Sold]]) -> 0
A29: =IF($E29="","",IF(COUNTA(C29:N29)=0,"",ROW()-5)) -> 24 | B29: =IF(E29="","",IF(DataEntryTable[[#This Row],[Sell Date]]="","Open","Closed")) -> Closed | C29: =IF(E29="","",IFERROR(VLOOKUP(UPPER(TRIM(E29)),'6_Reference Lists'!$A$4:$D$64,2,FALSE()),"")) -> International | D29: =IF(E29="","",IFERROR(VLOOKUP(UPPER(TRIM(E29)),'6_Reference Lists'!$A$4:$D$64,3,FALSE()),"")) -> ETF | E29: IXUS | F29: =IF(E29="","",IFERROR(VLOOKUP(UPPER(TRIM(E29)),'6_Reference Lists'!$A$4:$D$64,4,FALSE()),"")) -> iShares Core MSCI Total International Stock ETF | G29: 46098 | H29: 0.997 | I29: 93.56 | J29: 46101 | K29: 0.997 | L29: 83.55 | M29: =IF(E29="","",DataEntryTable[[#This Row],[Shares Bought]]-DataEntryTable[[#This Row],[Shares Sold]]) -> 0
A30: =IF($E30="","",IF(COUNTA(C30:N30)=0,"",ROW()-5)) -> 25 | B30: =IF(E30="","",IF(DataEntryTable[[#This Row],[Sell Date]]="","Open","Closed")) -> Open | C30: =IF(E30="","",IFERROR(VLOOKUP(UPPER(TRIM(E30)),'6_Reference Lists'!$A$4:$D$64,2,FALSE()),"")) -> International | D30: =IF(E30="","",IFERROR(VLOOKUP(UPPER(TRIM(E30)),'6_Reference Lists'!$A$4:$D$64,3,FALSE()),"")) -> ETF | E30: VXUS | F30: =IF(E30="","",IFERROR(VLOOKUP(UPPER(TRIM(E30)),'6_Reference Lists'!$A$4:$D$64,4,FALSE()),"")) -> Vanguard Total International Stock ETF | G30: 46098 | H30: 178 | I30: 79.019888 | K30: 0 | M30: =IF(E30="","",DataEntryTable[[#This Row],[Shares Bought]]-DataEntryTable[[#This Row],[Shares Sold]]) -> 178
A31: =IF($E31="","",IF(COUNTA(C31:N31)=0,"",ROW()-5)) -> 26 | B31: =IF(E31="","",IF(DataEntryTable[[#This Row],[Sell Date]]="","Open","Closed")) -> Open | C31: =IF(E31="","",IFERROR(VLOOKUP(UPPER(TRIM(E31)),'6_Reference Lists'!$A$4:$D$64,2,FALSE()),"")) -> International | D31: =IF(E31="","",IFERROR(VLOOKUP(UPPER(TRIM(E31)),'6_Reference Lists'!$A$4:$D$64,3,FALSE()),"")) -> ETF | E31: VXUS | F31: =IF(E31="","",IFERROR(VLOOKUP(UPPER(TRIM(E31)),'6_Reference Lists'!$A$4:$D$64,4,FALSE()),"")) -> Vanguard Total International Stock ETF | G31: 46098 | H31: 0.182 | I31: 79.010989 | K31: 0 | M31: =IF(E31="","",DataEntryTable[[#This Row],[Shares Bought]]-DataEntryTable[[#This Row],[Shares Sold]]) -> 0.182
A32: =IF($E32="","",IF(COUNTA(C32:N32)=0,"",ROW()-5)) -> 27 | B32: =IF(E32="","",IF(DataEntryTable[[#This Row],[Sell Date]]="","Open","Closed")) -> Open | C32: =IF(E32="","",IFERROR(VLOOKUP(UPPER(TRIM(E32)),'6_Reference Lists'!$A$4:$D$64,2,FALSE()),"")) -> International | D32: =IF(E32="","",IFERROR(VLOOKUP(UPPER(TRIM(E32)),'6_Reference Lists'!$A$4:$D$64,3,FALSE()),"")) -> ETF | E32: VXUS | F32: =IF(E32="","",IFERROR(VLOOKUP(UPPER(TRIM(E32)),'6_Reference Lists'!$A$4:$D$64,4,FALSE()),"")) -> Vanguard Total International Stock ETF | G32: 46101 | H32: 177 | I32: 74.639887 | K32: 0 | M32: =IF(E32="","",DataEntryTable[[#This Row],[Shares Bought]]-DataEntryTable[[#This Row],[Shares Sold]]) -> 177
A33: =IF($E33="","",IF(COUNTA(C33:N33)=0,"",ROW()-5)) -> 28 | B33: =IF(E33="","",IF(DataEntryTable[[#This Row],[Sell Date]]="","Open","Closed")) -> Open | C33: =IF(E33="","",IFERROR(VLOOKUP(UPPER(TRIM(E33)),'6_Reference Lists'!$A$4:$D$64,2,FALSE()),"")) -> International | D33: =IF(E33="","",IFERROR(VLOOKUP(UPPER(TRIM(E33)),'6_Reference Lists'!$A$4:$D$64,3,FALSE()),"")) -> ETF | E33: VXUS | F33: =IF(E33="","",IFERROR(VLOOKUP(UPPER(TRIM(E33)),'6_Reference Lists'!$A$4:$D$64,4,FALSE()),"")) -> Vanguard Total International Stock ETF | G33: 46101 | H33: 0.98 | I33: 74.632653 | K33: 0 | M33: =IF(E33="","",DataEntryTable[[#This Row],[Shares Bought]]-DataEntryTable[[#This Row],[Shares Sold]]) -> 0.98
A34: =IF($E34="","",IF(COUNTA(C34:N34)=0,"",ROW()-5)) -> 29 | B34: =IF(E34="","",IF(DataEntryTable[[#This Row],[Sell Date]]="","Open","Closed")) -> Closed | C34: =IF(E34="","",IFERROR(VLOOKUP(UPPER(TRIM(E34)),'6_Reference Lists'!$A$4:$D$64,2,FALSE()),"")) -> US | D34: =IF(E34="","",IFERROR(VLOOKUP(UPPER(TRIM(E34)),'6_Reference Lists'!$A$4:$D$64,3,FALSE()),"")) -> MLP | E34: EPD | F34: =IF(E34="","",IFERROR(VLOOKUP(UPPER(TRIM(E34)),'6_Reference Lists'!$A$4:$D$64,4,FALSE()),"")) -> Enterprise Products Partners L.P. | G34: 45960 | H34: 310 | I34: 30.53 | J34: 46111 | K34: 310 | L34: 39.0514 | M34: =IF(E34="","",DataEntryTable[[#This Row],[Shares Bought]]-DataEntryTable[[#This Row],[Shares Sold]]) -> 0 | N34: Sold 310 shares @ 39.0514; separate same-day execution.
A35: =IF($E35="","",IF(COUNTA(C35:N35)=0,"",ROW()-5)) -> 30 | B35: =IF(E35="","",IF(DataEntryTable[[#This Row],[Sell Date]]="","Open","Closed")) -> Open | C35: =IF(E35="","",IFERROR(VLOOKUP(UPPER(TRIM(E35)),'6_Reference Lists'!$A$4:$D$64,2,FALSE()),"")) -> US | D35: =IF(E35="","",IFERROR(VLOOKUP(UPPER(TRIM(E35)),'6_Reference Lists'!$A$4:$D$64,3,FALSE()),"")) -> ETF | E35: schb | F35: =IF(E35="","",IFERROR(VLOOKUP(UPPER(TRIM(E35)),'6_Reference Lists'!$A$4:$D$64,4,FALSE()),"")) -> Schwab U.S. Broad Market ETF | G35: 46111 | H35: 50 | I35: 20 | M35: =IF(E35="","",DataEntryTable[[#This Row],[Shares Bought]]-DataEntryTable[[#This Row],[Shares Sold]]) -> 50
A36: =IF($E36="","",IF(COUNTA(C36:N36)=0,"",ROW()-5)) -> 31 | B36: =IF(E36="","",IF(DataEntryTable[[#This Row],[Sell Date]]="","Open","Closed")) -> Open | C36: =IF(E36="","",IFERROR(VLOOKUP(UPPER(TRIM(E36)),'6_Reference Lists'!$A$4:$D$64,2,FALSE()),"")) -> US | D36: =IF(E36="","",IFERROR(VLOOKUP(UPPER(TRIM(E36)),'6_Reference Lists'!$A$4:$D$64,3,FALSE()),"")) -> ETF | E36: schb | F36: =IF(E36="","",IFERROR(VLOOKUP(UPPER(TRIM(E36)),'6_Reference Lists'!$A$4:$D$64,4,FALSE()),"")) -> Schwab U.S. Broad Market ETF | G36: 46112 | H36: 60 | I36: 22 | M36: =IF(E36="","",DataEntryTable[[#This Row],[Shares Bought]]-DataEntryTable[[#This Row],[Shares Sold]]) -> 60
A37: =IF($E37="","",IF(COUNTA(C37:N37)=0,"",ROW()-5)) -> 32 | B37: =IF(E37="","",IF(DataEntryTable[[#This Row],[Sell Date]]="","Open","Closed")) -> Open | C37: =IF(E37="","",IFERROR(VLOOKUP(UPPER(TRIM(E37)),'6_Reference Lists'!$A$4:$D$64,2,FALSE()),"")) -> US | D37: =IF(E37="","",IFERROR(VLOOKUP(UPPER(TRIM(E37)),'6_Reference Lists'!$A$4:$D$64,3,FALSE()),"")) -> ETF | E37: schb | F37: =IF(E37="","",IFERROR(VLOOKUP(UPPER(TRIM(E37)),'6_Reference Lists'!$A$4:$D$64,4,FALSE()),"")) -> Schwab U.S. Broad Market ETF | G37: 46133 | H37: 70 | I37: 24 | M37: =IF(E37="","",DataEntryTable[[#This Row],[Shares Bought]]-DataEntryTable[[#This Row],[Shares Sold]]) -> 70
A38: =IF($E38="","",IF(COUNTA(C38:N38)=0,"",ROW()-5)) | B38: =IF(E38="","",IF(DataEntryTable[[#This Row],[Sell Date]]="","Open","Closed")) | C38: =IF(E38="","",IFERROR(VLOOKUP(UPPER(TRIM(E38)),'6_Reference Lists'!$A$4:$D$64,2,FALSE()),"")) | D38: =IF(E38="","",IFERROR(VLOOKUP(UPPER(TRIM(E38)),'6_Reference Lists'!$A$4:$D$64,3,FALSE()),"")) | F38: =IF(E38="","",IFERROR(VLOOKUP(UPPER(TRIM(E38)),'6_Reference Lists'!$A$4:$D$64,4,FALSE()),"")) | M38: =IF(E38="","",DataEntryTable[[#This Row],[Shares Bought]]-DataEntryTable[[#This Row],[Shares Sold]])
A39: =IF($E39="","",IF(COUNTA(C39:N39)=0,"",ROW()-5)) | B39: =IF(E39="","",IF(DataEntryTable[[#This Row],[Sell Date]]="","Open","Closed")) | C39: =IF(E39="","",IFERROR(VLOOKUP(UPPER(TRIM(E39)),'6_Reference Lists'!$A$4:$D$64,2,FALSE()),"")) | D39: =IF(E39="","",IFERROR(VLOOKUP(UPPER(TRIM(E39)),'6_Reference Lists'!$A$4:$D$64,3,FALSE()),"")) | F39: =IF(E39="","",IFERROR(VLOOKUP(UPPER(TRIM(E39)),'6_Reference Lists'!$A$4:$D$64,4,FALSE()),"")) | M39: =IF(E39="","",DataEntryTable[[#This Row],[Shares Bought]]-DataEntryTable[[#This Row],[Shares Sold]])
A40: =IF($E40="","",IF(COUNTA(C40:N40)=0,"",ROW()-5)) | B40: =IF(E40="","",IF(DataEntryTable[[#This Row],[Sell Date]]="","Open","Closed")) | C40: =IF(E40="","",IFERROR(VLOOKUP(UPPER(TRIM(E40)),'6_Reference Lists'!$A$4:$D$64,2,FALSE()),"")) | D40: =IF(E40="","",IFERROR(VLOOKUP(UPPER(TRIM(E40)),'6_Reference Lists'!$A$4:$D$64,3,FALSE()),"")) | F40: =IF(E40="","",IFERROR(VLOOKUP(UPPER(TRIM(E40)),'6_Reference Lists'!$A$4:$D$64,4,FALSE()),"")) | M40: =IF(E40="","",DataEntryTable[[#This Row],[Shares Bought]]-DataEntryTable[[#This Row],[Shares Sold]])
A41: =IF($E41="","",IF(COUNTA(C41:N41)=0,"",ROW()-5)) | B41: =IF(E41="","",IF(DataEntryTable[[#This Row],[Sell Date]]="","Open","Closed")) | C41: =IF(E41="","",IFERROR(VLOOKUP(UPPER(TRIM(E41)),'6_Reference Lists'!$A$4:$D$64,2,FALSE()),"")) | D41: =IF(E41="","",IFERROR(VLOOKUP(UPPER(TRIM(E41)),'6_Reference Lists'!$A$4:$D$64,3,FALSE()),"")) | F41: =IF(E41="","",IFERROR(VLOOKUP(UPPER(TRIM(E41)),'6_Reference Lists'!$A$4:$D$64,4,FALSE()),"")) | M41: =IF(E41="","",DataEntryTable[[#This Row],[Shares Bought]]-DataEntryTable[[#This Row],[Shares Sold]])
A42: =IF($E42="","",IF(COUNTA(C42:N42)=0,"",ROW()-5)) | B42: =IF(E42="","",IF(DataEntryTable[[#This Row],[Sell Date]]="","Open","Closed")) | C42: =IF(E42="","",IFERROR(VLOOKUP(UPPER(TRIM(E42)),'6_Reference Lists'!$A$4:$D$64,2,FALSE()),"")) | D42: =IF(E42="","",IFERROR(VLOOKUP(UPPER(TRIM(E42)),'6_Reference Lists'!$A$4:$D$64,3,FALSE()),"")) | F42: =IF(E42="","",IFERROR(VLOOKUP(UPPER(TRIM(E42)),'6_Reference Lists'!$A$4:$D$64,4,FALSE()),"")) | M42: =IF(E42="","",DataEntryTable[[#This Row],[Shares Bought]]-DataEntryTable[[#This Row],[Shares Sold]])
A43: =IF($E43="","",IF(COUNTA(C43:N43)=0,"",ROW()-5)) | B43: =IF(E43="","",IF(DataEntryTable[[#This Row],[Sell Date]]="","Open","Closed")) | C43: =IF(E43="","",IFERROR(VLOOKUP(UPPER(TRIM(E43)),'6_Reference Lists'!$A$4:$D$64,2,FALSE()),"")) | D43: =IF(E43="","",IFERROR(VLOOKUP(UPPER(TRIM(E43)),'6_Reference Lists'!$A$4:$D$64,3,FALSE()),"")) | F43: =IF(E43="","",IFERROR(VLOOKUP(UPPER(TRIM(E43)),'6_Reference Lists'!$A$4:$D$64,4,FALSE()),"")) | M43: =IF(E43="","",DataEntryTable[[#This Row],[Shares Bought]]-DataEntryTable[[#This Row],[Shares Sold]])
A44: =IF($E44="","",IF(COUNTA(C44:N44)=0,"",ROW()-5)) | B44: =IF(E44="","",IF(DataEntryTable[[#This Row],[Sell Date]]="","Open","Closed")) | C44: =IF(E44="","",IFERROR(VLOOKUP(UPPER(TRIM(E44)),'6_Reference Lists'!$A$4:$D$64,2,FALSE()),"")) | D44: =IF(E44="","",IFERROR(VLOOKUP(UPPER(TRIM(E44)),'6_Reference Lists'!$A$4:$D$64,3,FALSE()),"")) | F44: =IF(E44="","",IFERROR(VLOOKUP(UPPER(TRIM(E44)),'6_Reference Lists'!$A$4:$D$64,4,FALSE()),"")) | M44: =IF(E44="","",DataEntryTable[[#This Row],[Shares Bought]]-DataEntryTable[[#This Row],[Shares Sold]])
A45: =IF($E45="","",IF(COUNTA(C45:N45)=0,"",ROW()-5)) | B45: =IF(E45="","",IF(DataEntryTable[[#This Row],[Sell Date]]="","Open","Closed")) | C45: =IF(E45="","",IFERROR(VLOOKUP(UPPER(TRIM(E45)),'6_Reference Lists'!$A$4:$D$64,2,FALSE()),"")) | D45: =IF(E45="","",IFERROR(VLOOKUP(UPPER(TRIM(E45)),'6_Reference Lists'!$A$4:$D$64,3,FALSE()),"")) | F45: =IF(E45="","",IFERROR(VLOOKUP(UPPER(TRIM(E45)),'6_Reference Lists'!$A$4:$D$64,4,FALSE()),"")) | M45: =IF(E45="","",DataEntryTable[[#This Row],[Shares Bought]]-DataEntryTable[[#This Row],[Shares Sold]])
A46: =IF($E46="","",IF(COUNTA(C46:N46)=0,"",ROW()-5)) | B46: =IF(E46="","",IF(DataEntryTable[[#This Row],[Sell Date]]="","Open","Closed")) | C46: =IF(E46="","",IFERROR(VLOOKUP(UPPER(TRIM(E46)),'6_Reference Lists'!$A$4:$D$64,2,FALSE()),"")) | D46: =IF(E46="","",IFERROR(VLOOKUP(UPPER(TRIM(E46)),'6_Reference Lists'!$A$4:$D$64,3,FALSE()),"")) | F46: =IF(E46="","",IFERROR(VLOOKUP(UPPER(TRIM(E46)),'6_Reference Lists'!$A$4:$D$64,4,FALSE()),"")) | M46: =IF(E46="","",DataEntryTable[[#This Row],[Shares Bought]]-DataEntryTable[[#This Row],[Shares Sold]])
A47: =IF($E47="","",IF(COUNTA(C47:N47)=0,"",ROW()-5)) | B47: =IF(E47="","",IF(DataEntryTable[[#This Row],[Sell Date]]="","Open","Closed")) | C47: =IF(E47="","",IFERROR(VLOOKUP(UPPER(TRIM(E47)),'6_Reference Lists'!$A$4:$D$64,2,FALSE()),"")) | D47: =IF(E47="","",IFERROR(VLOOKUP(UPPER(TRIM(E47)),'6_Reference Lists'!$A$4:$D$64,3,FALSE()),"")) | F47: =IF(E47="","",IFERROR(VLOOKUP(UPPER(TRIM(E47)),'6_Reference Lists'!$A$4:$D$64,4,FALSE()),"")) | M47: =IF(E47="","",DataEntryTable[[#This Row],[Shares Bought]]-DataEntryTable[[#This Row],[Shares Sold]])
A48: =IF($E48="","",IF(COUNTA(C48:N48)=0,"",ROW()-5)) | B48: =IF(E48="","",IF(DataEntryTable[[#This Row],[Sell Date]]="","Open","Closed")) | C48: =IF(E48="","",IFERROR(VLOOKUP(UPPER(TRIM(E48)),'6_Reference Lists'!$A$4:$D$64,2,FALSE()),"")) | D48: =IF(E48="","",IFERROR(VLOOKUP(UPPER(TRIM(E48)),'6_Reference Lists'!$A$4:$D$64,3,FALSE()),"")) | F48: =IF(E48="","",IFERROR(VLOOKUP(UPPER(TRIM(E48)),'6_Reference Lists'!$A$4:$D$64,4,FALSE()),"")) | M48: =IF(E48="","",DataEntryTable[[#This Row],[Shares Bought]]-DataEntryTable[[#This Row],[Shares Sold]])
A49: =IF($E49="","",IF(COUNTA(C49:N49)=0,"",ROW()-5)) | B49: =IF(E49="","",IF(DataEntryTable[[#This Row],[Sell Date]]="","Open","Closed")) | C49: =IF(E49="","",IFERROR(VLOOKUP(UPPER(TRIM(E49)),'6_Reference Lists'!$A$4:$D$64,2,FALSE()),"")) | D49: =IF(E49="","",IFERROR(VLOOKUP(UPPER(TRIM(E49)),'6_Reference Lists'!$A$4:$D$64,3,FALSE()),"")) | F49: =IF(E49="","",IFERROR(VLOOKUP(UPPER(TRIM(E49)),'6_Reference Lists'!$A$4:$D$64,4,FALSE()),"")) | M49: =IF(E49="","",DataEntryTable[[#This Row],[Shares Bought]]-DataEntryTable[[#This Row],[Shares Sold]])
... A505: =IF($E505="","",IF(COUNTA(C505:N505)=0,"",ROW()-5)) | B505: =IF(E505="","",IF(DataEntryTable[[#This Row],[Sell Date]]="","Open","Closed")) | C505: =IF(E505="","",IFERROR(VLOOKUP(UPPER(TRIM(E505)),'6_Reference Lists'!$A$4:$D$64,2,FALSE()),"")) | D505: =IF(E505="","",IFERROR(VLOOKUP(UPPER(TRIM(E505)),'6_Reference Lists'!$A$4:$D$64,3,FALSE()),"")) | F505: =IF(E505="","",IFERROR(VLOOKUP(UPPER(TRIM(E505)),'6_Reference Lists'!$A$4:$D$64,4,FALSE()),"")) | M505: =IF(E505="","",DataEntryTable[[#This Row],[Shares Bought]]-DataEntryTable[[#This Row],[Shares Sold]])

Sheet 2_Review & Audit
A1: 2_Review & Audit
A2: Cleaned helper layer for imported rows. Gray area = review outputs and current-state calculations.
A5: Entry # | B5: Data Entry Status | C5: Sleeve | D5: Asset Type | E5: Raw Ticker | F5: Clean Ticker | G5: Asset Description | H5: Generated Lot ID | I5: Buy Date | J5: Shares Bought | K5: Cost / Share | L5: Purchase Cost | M5: Sell Date | N5: Shares Sold | O5: Sale Price / Share | P5: Sale Proceeds | Q5: Realized Gain / (Loss) | R5: Shares Remaining | S5: Validation Flag | T5: Wash Candidate? | U5: Recent Rebuy? | V5: Wash Sale Window End Date | W5: Review Notes | X5: Holding Period (Days) | Y5: Tax Term | Z5: Wash Basis Adjustment | AA5: Adjusted Total Cost | AB5: Adjusted Cost / Share | AC5: Loss Seq | AD5: Review Row #
A6: =IF('1_Data Entry'!$E6="","",IF(COUNTA('1_Data Entry'!C6:N6)=0,"",'1_Data Entry'!A6)) -> 1 | B6: =IF('1_Data Entry'!$E6="","",IF(A6="","",IF(S6<>"OK","Check row",IF(M6="","Open lot",IF(R6=0,"Closed lot","Partially sold"))))) -> Closed lot | C6: =IF(A6="","",'1_Data Entry'!C6) -> US | D6: =IF(A6="","",'1_Data Entry'!D6) -> MLP | E6: =IF(A6="","",'1_Data Entry'!E6) -> EPD | F6: =IF(E6="","",UPPER(TRIM(E6))) -> EPD | G6: =IF(F6="","",IFERROR(VLOOKUP(F6,'6_Reference Lists'!$A$4:$D$64,4,FALSE()),'1_Data Entry'!F6)) -> Enterprise Products Partners L.P. | H6: =IF('1_Data Entry'!$E6="","",IF(OR(F6="",I6="",J6="",K6=""),"",F6&"-"&TEXT(I6,"yyyymmdd")&"-"&SUBSTITUTE(TEXT(ROUND(J6,3),"0.###"),".","D")&"-"&SUBSTITUTE(TEXT(ROUND(K6,3),"0.###"),".","D"))) -> EPD-20240216-580D-27D25 | I6: =IF('1_Data Entry'!$E6="","",IF(A6="","",'1_Data Entry'!G6)) -> 45338 | J6: =IF('1_Data Entry'!$E6="","",IF(A6="","",'1_Data Entry'!H6)) -> 580 | K6: =IF('1_Data Entry'!$E6="","",IF(A6="","",'1_Data Entry'!I6)) -> 27.25 | L6: =IF('1_Data Entry'!$E6="","",IF(OR(J6="",K6=""),"",J6*K6)) -> 15805 | M6: =IF(A6="","",IF(OR('1_Data Entry'!L6="",'1_Data Entry'!L6<=0),"",'1_Data Entry'!J6)) -> 46090 | N6: =IF('1_Data Entry'!$E6="","",IF(OR(J6="",R6=""),"",MAX(J6-R6,0))) -> 580 | O6: =IF('1_Data Entry'!$E6="","",IF(A6="","",'1_Data Entry'!L6)) -> 38.15 | P6: =IF(OR(M6="",O6="",O6<=0,N6="",N6<=0),"",O6*N6) -> 22127 | Q6: =IF('1_Data Entry'!$E6="","",IF(OR(M6="",P6="",L6=""),"",P6-L6)) -> 6322 | R6: =IF(A6="","",IF('1_Data Entry'!M6<>"",'1_Data Entry'!M6,IF('1_Data Entry'!J6="",J6,""))) -> 0 | S6: =IF('1_Data Entry'!$E6="","",IF(A6="","",IF(OR(F6="",I6="",J6="",K6=""),"Check row",IF(AND(M6<>"",M6<I6),"Sell before buy",IF(AND(R6<>"",J6<R6),"Shares remaining exceeds buy",IF(AND(M6<>"",OR(O6="",O6<=0),N6>0),"Missing sale price","OK")))))) -> OK | T6: =IF('1_Data Entry'!$E6="","",IF(A6="","",IF(AND(Q6<0,M6<>""),"Yes","No"))) -> No | U6: =IF('1_Data Entry'!$E6="","",IF(OR(A6="",T6<>"Yes",M6=""),"No",IF(COUNTIFS($F$6:$F$505,F6,$I$6:$I$505,">="&M6-30,$I$6:$I$505,"<="&M6+30,$A$6:$A$505,"<>"&A6)>0,"Yes","No"))) -> No | V6: =IF('1_Data Entry'!$E6="","",IF(OR(A6="",U6<>"Yes",M6=""),"",M6+30)) | W6: =IF('1_Data Entry'!$E6="","",IF(A6="","",IF(S6="OK","Ready","Review row"))) -> Ready | X6: =IF(OR(I6="",M6=""),"",M6-I6) -> 752 | Y6: =IF(X6="","",IF(X6<=365,"Short-Term","Long-Term")) -> Long-Term | Z6: =IF('1_Data Entry'!$E6="","",SUM(SUMIFS('4_Wash Match Table'!R$7:R$500,'4_Wash Match Table'!L$7:L$500,H6),(SUMIFS('4_Wash Match Table'!AA$7:AA$500,'4_Wash Match Table'!U$7:U$500,H6)),(SUMIFS('4_Wash Match Table'!AJ$7:AJ$500,'4_Wash Match Table'!AD$7:AD$500,H6)),(SUMIFS('4_Wash Match Table'!AS$7:AS$500,'4_Wash Match Table'!AM$7:AM$500,H6)))) -> 0 | AA6: =IF('1_Data Entry'!$E6="","",IF(OR(L6="",Z6=""),"",L6+Z6)) -> 15805 | AB6: =IFERROR(IF(OR(J6="",AA6=""),"",AA6/J6),"") -> 27.25 | AC6: =IF(AND($M6<>"",$Q6<0),COUNTIFS($M$6:M6,"<>",$Q$6:Q6,"<0"),"") | AD6: =IF(A6="","",ROW()) -> 6
A7: =IF('1_Data Entry'!$E7="","",IF(COUNTA('1_Data Entry'!C7:N7)=0,"",'1_Data Entry'!A7)) -> 2 | B7: =IF('1_Data Entry'!$E7="","",IF(A7="","",IF(S7<>"OK","Check row",IF(M7="","Open lot",IF(R7=0,"Closed lot","Partially sold"))))) -> Closed lot | C7: =IF(A7="","",'1_Data Entry'!C7) -> US | D7: =IF(A7="","",'1_Data Entry'!D7) -> MLP | E7: =IF(A7="","",'1_Data Entry'!E7) -> EPD | F7: =IF(E7="","",UPPER(TRIM(E7))) -> EPD | G7: =IF(F7="","",IFERROR(VLOOKUP(F7,'6_Reference Lists'!$A$4:$D$64,4,FALSE()),'1_Data Entry'!F7)) -> Enterprise Products Partners L.P. | H7: =IF('1_Data Entry'!$E7="","",IF(OR(F7="",I7="",J7="",K7=""),"",F7&"-"&TEXT(I7,"yyyymmdd")&"-"&SUBSTITUTE(TEXT(ROUND(J7,3),"0.###"),".","D")&"-"&SUBSTITUTE(TEXT(ROUND(K7,3),"0.###"),".","D"))) -> EPD-20240216-615D-27D25 | I7: =IF('1_Data Entry'!$E7="","",IF(A7="","",'1_Data Entry'!G7)) -> 45338 | J7: =IF('1_Data Entry'!$E7="","",IF(A7="","",'1_Data Entry'!H7)) -> 615 | K7: =IF('1_Data Entry'!$E7="","",IF(A7="","",'1_Data Entry'!I7)) -> 27.25 | L7: =IF('1_Data Entry'!$E7="","",IF(OR(J7="",K7=""),"",J7*K7)) -> 16758.75 | M7: =IF(A7="","",IF(OR('1_Data Entry'!L7="",'1_Data Entry'!L7<=0),"",'1_Data Entry'!J7)) -> 46090 | N7: =IF('1_Data Entry'!$E7="","",IF(OR(J7="",R7=""),"",MAX(J7-R7,0))) -> 615 | O7: =IF('1_Data Entry'!$E7="","",IF(A7="","",'1_Data Entry'!L7)) -> 38.15 | P7: =IF(OR(M7="",O7="",O7<=0,N7="",N7<=0),"",O7*N7) -> 23462.25 | Q7: =IF('1_Data Entry'!$E7="","",IF(OR(M7="",P7="",L7=""),"",P7-L7)) -> 6703.5 | R7: =IF(A7="","",IF('1_Data Entry'!M7<>"",'1_Data Entry'!M7,IF('1_Data Entry'!J7="",J7,""))) -> 0 | S7: =IF('1_Data Entry'!$E7="","",IF(A7="","",IF(OR(F7="",I7="",J7="",K7=""),"Check row",IF(AND(M7<>"",M7<I7),"Sell before buy",IF(AND(R7<>"",J7<R7),"Shares remaining exceeds buy",IF(AND(M7<>"",OR(O7="",O7<=0),N7>0),"Missing sale price","OK")))))) -> OK | T7: =IF('1_Data Entry'!$E7="","",IF(A7="","",IF(AND(Q7<0,M7<>""),"Yes","No"))) -> No | U7: =IF('1_Data Entry'!$E7="","",IF(OR(A7="",T7<>"Yes",M7=""),"No",IF(COUNTIFS($F$6:$F$505,F7,$I$6:$I$505,">="&M7-30,$I$6:$I$505,"<="&M7+30,$A$6:$A$505,"<>"&A7)>0,"Yes","No"))) -> No | V7: =IF('1_Data Entry'!$E7="","",IF(OR(A7="",U7<>"Yes",M7=""),"",M7+30)) | W7: =IF('1_Data Entry'!$E7="","",IF(A7="","",IF(S7="OK","Ready","Review row"))) -> Ready | X7: =IF(OR(I7="",M7=""),"",M7-I7) -> 752 | Y7: =IF(X7="","",IF(X7<=365,"Short-Term","Long-Term")) -> Long-Term | Z7: =IF('1_Data Entry'!$E7="","",SUM(SUMIFS('4_Wash Match Table'!R$7:R$500,'4_Wash Match Table'!L$7:L$500,H7),(SUMIFS('4_Wash Match Table'!AA$7:AA$500,'4_Wash Match Table'!U$7:U$500,H7)),(SUMIFS('4_Wash Match Table'!AJ$7:AJ$500,'4_Wash Match Table'!AD$7:AD$500,H7)),(SUMIFS('4_Wash Match Table'!AS$7:AS$500,'4_Wash Match Table'!AM$7:AM$500,H7)))) -> 0 | AA7: =IF('1_Data Entry'!$E7="","",IF(OR(L7="",Z7=""),"",L7+Z7)) -> 16758.75 | AB7: =IFERROR(IF(OR(J7="",AA7=""),"",AA7/J7),"") -> 27.25 | AC7: =IF(AND($M7<>"",$Q7<0),COUNTIFS($M$6:M7,"<>",$Q$6:Q7,"<0"),"") | AD7: =IF(A7="","",ROW()) -> 7
A8: =IF('1_Data Entry'!$E8="","",IF(COUNTA('1_Data Entry'!C8:N8)=0,"",'1_Data Entry'!A8)) -> 3 | B8: =IF('1_Data Entry'!$E8="","",IF(A8="","",IF(S8<>"OK","Check row",IF(M8="","Open lot",IF(R8=0,"Closed lot","Partially sold"))))) -> Closed lot | C8: =IF(A8="","",'1_Data Entry'!C8) -> US | D8: =IF(A8="","",'1_Data Entry'!D8) -> MLP | E8: =IF(A8="","",'1_Data Entry'!E8) -> EPD | F8: =IF(E8="","",UPPER(TRIM(E8))) -> EPD | G8: =IF(F8="","",IFERROR(VLOOKUP(F8,'6_Reference Lists'!$A$4:$D$64,4,FALSE()),'1_Data Entry'!F8)) -> Enterprise Products Partners L.P. | H8: =IF('1_Data Entry'!$E8="","",IF(OR(F8="",I8="",J8="",K8=""),"",F8&"-"&TEXT(I8,"yyyymmdd")&"-"&SUBSTITUTE(TEXT(ROUND(J8,3),"0.###"),".","D")&"-"&SUBSTITUTE(TEXT(ROUND(K8,3),"0.###"),".","D"))) -> EPD-20250218-580D-33D72 | I8: =IF('1_Data Entry'!$E8="","",IF(A8="","",'1_Data Entry'!G8)) -> 45706 | J8: =IF('1_Data Entry'!$E8="","",IF(A8="","",'1_Data Entry'!H8)) -> 580 | K8: =IF('1_Data Entry'!$E8="","",IF(A8="","",'1_Data Entry'!I8)) -> 33.72 | L8: =IF('1_Data Entry'!$E8="","",IF(OR(J8="",K8=""),"",J8*K8)) -> 19557.6 | M8: =IF(A8="","",IF(OR('1_Data Entry'!L8="",'1_Data Entry'!L8<=0),"",'1_Data Entry'!J8)) -> 46090 | N8: =IF('1_Data Entry'!$E8="","",IF(OR(J8="",R8=""),"",MAX(J8-R8,0))) -> 580 | O8: =IF('1_Data Entry'!$E8="","",IF(A8="","",'1_Data Entry'!L8)) -> 38.15 | P8: =IF(OR(M8="",O8="",O8<=0,N8="",N8<=0),"",O8*N8) -> 22127 | Q8: =IF('1_Data Entry'!$E8="","",IF(OR(M8="",P8="",L8=""),"",P8-L8)) -> 2569.4 | R8: =IF(A8="","",IF('1_Data Entry'!M8<>"",'1_Data Entry'!M8,IF('1_Data Entry'!J8="",J8,""))) -> 0 | S8: =IF('1_Data Entry'!$E8="","",IF(A8="","",IF(OR(F8="",I8="",J8="",K8=""),"Check row",IF(AND(M8<>"",M8<I8),"Sell before buy",IF(AND(R8<>"",J8<R8),"Shares remaining exceeds buy",IF(AND(M8<>"",OR(O8="",O8<=0),N8>0),"Missing sale price","OK")))))) -> OK | T8: =IF('1_Data Entry'!$E8="","",IF(A8="","",IF(AND(Q8<0,M8<>""),"Yes","No"))) -> No | U8: =IF('1_Data Entry'!$E8="","",IF(OR(A8="",T8<>"Yes",M8=""),"No",IF(COUNTIFS($F$6:$F$505,F8,$I$6:$I$505,">="&M8-30,$I$6:$I$505,"<="&M8+30,$A$6:$A$505,"<>"&A8)>0,"Yes","No"))) -> No | V8: =IF('1_Data Entry'!$E8="","",IF(OR(A8="",U8<>"Yes",M8=""),"",M8+30)) | W8: =IF('1_Data Entry'!$E8="","",IF(A8="","",IF(S8="OK","Ready","Review row"))) -> Ready | X8: =IF(OR(I8="",M8=""),"",M8-I8) -> 384 | Y8: =IF(X8="","",IF(X8<=365,"Short-Term","Long-Term")) -> Long-Term | Z8: =IF('1_Data Entry'!$E8="","",SUM(SUMIFS('4_Wash Match Table'!R$7:R$500,'4_Wash Match Table'!L$7:L$500,H8),(SUMIFS('4_Wash Match Table'!AA$7:AA$500,'4_Wash Match Table'!U$7:U$500,H8)),(SUMIFS('4_Wash Match Table'!AJ$7:AJ$500,'4_Wash Match Table'!AD$7:AD$500,H8)),(SUMIFS('4_Wash Match Table'!AS$7:AS$500,'4_Wash Match Table'!AM$7:AM$500,H8)))) -> 0 | AA8: =IF('1_Data Entry'!$E8="","",IF(OR(L8="",Z8=""),"",L8+Z8)) -> 19557.6 | AB8: =IFERROR(IF(OR(J8="",AA8=""),"",AA8/J8),"") -> 33.72 | AC8: =IF(AND($M8<>"",$Q8<0),COUNTIFS($M$6:M8,"<>",$Q$6:Q8,"<0"),"") | AD8: =IF(A8="","",ROW()) -> 8
A9: =IF('1_Data Entry'!$E9="","",IF(COUNTA('1_Data Entry'!C9:N9)=0,"",'1_Data Entry'!A9)) -> 4 | B9: =IF('1_Data Entry'!$E9="","",IF(A9="","",IF(S9<>"OK","Check row",IF(M9="","Open lot",IF(R9=0,"Closed lot","Partially sold"))))) -> Closed lot | C9: =IF(A9="","",'1_Data Entry'!C9) -> US | D9: =IF(A9="","",'1_Data Entry'!D9) -> MLP | E9: =IF(A9="","",'1_Data Entry'!E9) -> EPD | F9: =IF(E9="","",UPPER(TRIM(E9))) -> EPD | G9: =IF(F9="","",IFERROR(VLOOKUP(F9,'6_Reference Lists'!$A$4:$D$64,4,FALSE()),'1_Data Entry'!F9)) -> Enterprise Products Partners L.P. | H9: =IF('1_Data Entry'!$E9="","",IF(OR(F9="",I9="",J9="",K9=""),"",F9&"-"&TEXT(I9,"yyyymmdd")&"-"&SUBSTITUTE(TEXT(ROUND(J9,3),"0.###"),".","D")&"-"&SUBSTITUTE(TEXT(ROUND(K9,3),"0.###"),".","D"))) -> EPD-20250218-30D-33D72 | I9: =IF('1_Data Entry'!$E9="","",IF(A9="","",'1_Data Entry'!G9)) -> 45706 | J9: =IF('1_Data Entry'!$E9="","",IF(A9="","",'1_Data Entry'!H9)) -> 30 | K9: =IF('1_Data Entry'!$E9="","",IF(A9="","",'1_Data Entry'!I9)) -> 33.72 | L9: =IF('1_Data Entry'!$E9="","",IF(OR(J9="",K9=""),"",J9*K9)) -> 1011.6 | M9: =IF(A9="","",IF(OR('1_Data Entry'!L9="",'1_Data Entry'!L9<=0),"",'1_Data Entry'!J9)) -> 46090 | N9: =IF('1_Data Entry'!$E9="","",IF(OR(J9="",R9=""),"",MAX(J9-R9,0))) -> 30 | O9: =IF('1_Data Entry'!$E9="","",IF(A9="","",'1_Data Entry'!L9)) -> 38 | P9: =IF(OR(M9="",O9="",O9<=0,N9="",N9<=0),"",O9*N9) -> 1140 | Q9: =IF('1_Data Entry'!$E9="","",IF(OR(M9="",P9="",L9=""),"",P9-L9)) -> 128.4 | R9: =IF(A9="","",IF('1_Data Entry'!M9<>"",'1_Data Entry'!M9,IF('1_Data Entry'!J9="",J9,""))) -> 0 | S9: =IF('1_Data Entry'!$E9="","",IF(A9="","",IF(OR(F9="",I9="",J9="",K9=""),"Check row",IF(AND(M9<>"",M9<I9),"Sell before buy",IF(AND(R9<>"",J9<R9),"Shares remaining exceeds buy",IF(AND(M9<>"",OR(O9="",O9<=0),N9>0),"Missing sale price","OK")))))) -> OK | T9: =IF('1_Data Entry'!$E9="","",IF(A9="","",IF(AND(Q9<0,M9<>""),"Yes","No"))) -> No | U9: =IF('1_Data Entry'!$E9="","",IF(OR(A9="",T9<>"Yes",M9=""),"No",IF(COUNTIFS($F$6:$F$505,F9,$I$6:$I$505,">="&M9-30,$I$6:$I$505,"<="&M9+30,$A$6:$A$505,"<>"&A9)>0,"Yes","No"))) -> No | V9: =IF('1_Data Entry'!$E9="","",IF(OR(A9="",U9<>"Yes",M9=""),"",M9+30)) | W9: =IF('1_Data Entry'!$E9="","",IF(A9="","",IF(S9="OK","Ready","Review row"))) -> Ready | X9: =IF(OR(I9="",M9=""),"",M9-I9) -> 384 | Y9: =IF(X9="","",IF(X9<=365,"Short-Term","Long-Term")) -> Long-Term | Z9: =IF('1_Data Entry'!$E9="","",SUM(SUMIFS('4_Wash Match Table'!R$7:R$500,'4_Wash Match Table'!L$7:L$500,H9),(SUMIFS('4_Wash Match Table'!AA$7:AA$500,'4_Wash Match Table'!U$7:U$500,H9)),(SUMIFS('4_Wash Match Table'!AJ$7:AJ$500,'4_Wash Match Table'!AD$7:AD$500,H9)),(SUMIFS('4_Wash Match Table'!AS$7:AS$500,'4_Wash Match Table'!AM$7:AM$500,H9)))) -> 0 | AA9: =IF('1_Data Entry'!$E9="","",IF(OR(L9="",Z9=""),"",L9+Z9)) -> 1011.6 | AB9: =IFERROR(IF(OR(J9="",AA9=""),"",AA9/J9),"") -> 33.72 | AC9: =IF(AND($M9<>"",$Q9<0),COUNTIFS($M$6:M9,"<>",$Q$6:Q9,"<0"),"") | AD9: =IF(A9="","",ROW()) -> 9
A10: =IF('1_Data Entry'!$E10="","",IF(COUNTA('1_Data Entry'!C10:N10)=0,"",'1_Data Entry'!A10)) -> 5 | B10: =IF('1_Data Entry'!$E10="","",IF(A10="","",IF(S10<>"OK","Check row",IF(M10="","Open lot",IF(R10=0,"Closed lot","Partially sold"))))) -> Closed lot | C10: =IF(A10="","",'1_Data Entry'!C10) -> US | D10: =IF(A10="","",'1_Data Entry'!D10) -> MLP | E10: =IF(A10="","",'1_Data Entry'!E10) -> EPD | F10: =IF(E10="","",UPPER(TRIM(E10))) -> EPD | G10: =IF(F10="","",IFERROR(VLOOKUP(F10,'6_Reference Lists'!$A$4:$D$64,4,FALSE()),'1_Data Entry'!F10)) -> Enterprise Products Partners L.P. | H10: =IF('1_Data Entry'!$E10="","",IF(OR(F10="",I10="",J10="",K10=""),"",F10&"-"&TEXT(I10,"yyyymmdd")&"-"&SUBSTITUTE(TEXT(ROUND(J10,3),"0.###"),".","D")&"-"&SUBSTITUTE(TEXT(ROUND(K10,3),"0.###"),".","D"))) -> EPD-20250218-585D-33D72 | I10: =IF('1_Data Entry'!$E10="","",IF(A10="","",'1_Data Entry'!G10)) -> 45706 | J10: =IF('1_Data Entry'!$E10="","",IF(A10="","",'1_Data Entry'!H10)) -> 585 | K10: =IF('1_Data Entry'!$E10="","",IF(A10="","",'1_Data Entry'!I10)) -> 33.72 | L10: =IF('1_Data Entry'!$E10="","",IF(OR(J10="",K10=""),"",J10*K10)) -> 19726.2 | M10: =IF(A10="","",IF(OR('1_Data Entry'!L10="",'1_Data Entry'!L10<=0),"",'1_Data Entry'!J10)) -> 46090 | N10: =IF('1_Data Entry'!$E10="","",IF(OR(J10="",R10=""),"",MAX(J10-R10,0))) -> 585 | O10: =IF('1_Data Entry'!$E10="","",IF(A10="","",'1_Data Entry'!L10)) -> 38 | P10: =IF(OR(M10="",O10="",O10<=0,N10="",N10<=0),"",O10*N10) -> 22230 | Q10: =IF('1_Data Entry'!$E10="","",IF(OR(M10="",P10="",L10=""),"",P10-L10)) -> 2503.8 | R10: =IF(A10="","",IF('1_Data Entry'!M10<>"",'1_Data Entry'!M10,IF('1_Data Entry'!J10="",J10,""))) -> 0 | S10: =IF('1_Data Entry'!$E10="","",IF(A10="","",IF(OR(F10="",I10="",J10="",K10=""),"Check row",IF(AND(M10<>"",M10<I10),"Sell before buy",IF(AND(R10<>"",J10<R10),"Shares remaining exceeds buy",IF(AND(M10<>"",OR(O10="",O10<=0),N10>0),"Missing sale price","OK")))))) -> OK | T10: =IF('1_Data Entry'!$E10="","",IF(A10="","",IF(AND(Q10<0,M10<>""),"Yes","No"))) -> No | U10: =IF('1_Data Entry'!$E10="","",IF(OR(A10="",T10<>"Yes",M10=""),"No",IF(COUNTIFS($F$6:$F$505,F10,$I$6:$I$505,">="&M10-30,$I$6:$I$505,"<="&M10+30,$A$6:$A$505,"<>"&A10)>0,"Yes","No"))) -> No | V10: =IF('1_Data Entry'!$E10="","",IF(OR(A10="",U10<>"Yes",M10=""),"",M10+30)) | W10: =IF('1_Data Entry'!$E10="","",IF(A10="","",IF(S10="OK","Ready","Review row"))) -> Ready | X10: =IF(OR(I10="",M10=""),"",M10-I10) -> 384 | Y10: =IF(X10="","",IF(X10<=365,"Short-Term","Long-Term")) -> Long-Term | Z10: =IF('1_Data Entry'!$E10="","",SUM(SUMIFS('4_Wash Match Table'!R$7:R$500,'4_Wash Match Table'!L$7:L$500,H10),(SUMIFS('4_Wash Match Table'!AA$7:AA$500,'4_Wash Match Table'!U$7:U$500,H10)),(SUMIFS('4_Wash Match Table'!AJ$7:AJ$500,'4_Wash Match Table'!AD$7:AD$500,H10)),(SUMIFS('4_Wash Match Table'!AS$7:AS$500,'4_Wash Match Table'!AM$7:AM$500,H10)))) -> 0 | AA10: =IF('1_Data Entry'!$E10="","",IF(OR(L10="",Z10=""),"",L10+Z10)) -> 19726.2 | AB10: =IFERROR(IF(OR(J10="",AA10=""),"",AA10/J10),"") -> 33.72 | AC10: =IF(AND($M10<>"",$Q10<0),COUNTIFS($M$6:M10,"<>",$Q$6:Q10,"<0"),"") | AD10: =IF(A10="","",ROW()) -> 10
A11: =IF('1_Data Entry'!$E11="","",IF(COUNTA('1_Data Entry'!C11:N11)=0,"",'1_Data Entry'!A11)) -> 6 | B11: =IF('1_Data Entry'!$E11="","",IF(A11="","",IF(S11<>"OK","Check row",IF(M11="","Open lot",IF(R11=0,"Closed lot","Partially sold"))))) -> Closed lot | C11: =IF(A11="","",'1_Data Entry'!C11) -> US | D11: =IF(A11="","",'1_Data Entry'!D11) -> MLP | E11: =IF(A11="","",'1_Data Entry'!E11) -> EPD | F11: =IF(E11="","",UPPER(TRIM(E11))) -> EPD | G11: =IF(F11="","",IFERROR(VLOOKUP(F11,'6_Reference Lists'!$A$4:$D$64,4,FALSE()),'1_Data Entry'!F11)) -> Enterprise Products Partners L.P. | H11: =IF('1_Data Entry'!$E11="","",IF(OR(F11="",I11="",J11="",K11=""),"",F11&"-"&TEXT(I11,"yyyymmdd")&"-"&SUBSTITUTE(TEXT(ROUND(J11,3),"0.###"),".","D")&"-"&SUBSTITUTE(TEXT(ROUND(K11,3),"0.###"),".","D"))) -> EPD-20250218-562D-33D72 | I11: =IF('1_Data Entry'!$E11="","",IF(A11="","",'1_Data Entry'!G11)) -> 45706 | J11: =IF('1_Data Entry'!$E11="","",IF(A11="","",'1_Data Entry'!H11)) -> 562 | K11: =IF('1_Data Entry'!$E11="","",IF(A11="","",'1_Data Entry'!I11)) -> 33.72 | L11: =IF('1_Data Entry'!$E11="","",IF(OR(J11="",K11=""),"",J11*K11)) -> 18950.64 | M11: =IF(A11="","",IF(OR('1_Data Entry'!L11="",'1_Data Entry'!L11<=0),"",'1_Data Entry'!J11)) -> 46090 | N11: =IF('1_Data Entry'!$E11="","",IF(OR(J11="",R11=""),"",MAX(J11-R11,0))) -> 562 | O11: =IF('1_Data Entry'!$E11="","",IF(A11="","",'1_Data Entry'!L11)) -> 38 | P11: =IF(OR(M11="",O11="",O11<=0,N11="",N11<=0),"",O11*N11) -> 21356 | Q11: =IF('1_Data Entry'!$E11="","",IF(OR(M11="",P11="",L11=""),"",P11-L11)) -> 2405.36 | R11: =IF(A11="","",IF('1_Data Entry'!M11<>"",'1_Data Entry'!M11,IF('1_Data Entry'!J11="",J11,""))) -> 0 | S11: =IF('1_Data Entry'!$E11="","",IF(A11="","",IF(OR(F11="",I11="",J11="",K11=""),"Check row",IF(AND(M11<>"",M11<I11),"Sell before buy",IF(AND(R11<>"",J11<R11),"Shares remaining exceeds buy",IF(AND(M11<>"",OR(O11="",O11<=0),N11>0),"Missing sale price","OK")))))) -> OK | T11: =IF('1_Data Entry'!$E11="","",IF(A11="","",IF(AND(Q11<0,M11<>""),"Yes","No"))) -> No | U11: =IF('1_Data Entry'!$E11="","",IF(OR(A11="",T11<>"Yes",M11=""),"No",IF(COUNTIFS($F$6:$F$505,F11,$I$6:$I$505,">="&M11-30,$I$6:$I$505,"<="&M11+30,$A$6:$A$505,"<>"&A11)>0,"Yes","No"))) -> No | V11: =IF('1_Data Entry'!$E11="","",IF(OR(A11="",U11<>"Yes",M11=""),"",M11+30)) | W11: =IF('1_Data Entry'!$E11="","",IF(A11="","",IF(S11="OK","Ready","Review row"))) -> Ready | X11: =IF(OR(I11="",M11=""),"",M11-I11) -> 384 | Y11: =IF(X11="","",IF(X11<=365,"Short-Term","Long-Term")) -> Long-Term | Z11: =IF('1_Data Entry'!$E11="","",SUM(SUMIFS('4_Wash Match Table'!R$7:R$500,'4_Wash Match Table'!L$7:L$500,H11),(SUMIFS('4_Wash Match Table'!AA$7:AA$500,'4_Wash Match Table'!U$7:U$500,H11)),(SUMIFS('4_Wash Match Table'!AJ$7:AJ$500,'4_Wash Match Table'!AD$7:AD$500,H11)),(SUMIFS('4_Wash Match Table'!AS$7:AS$500,'4_Wash Match Table'!AM$7:AM$500,H11)))) -> 0 | AA11: =IF('1_Data Entry'!$E11="","",IF(OR(L11="",Z11=""),"",L11+Z11)) -> 18950.64 | AB11: =IFERROR(IF(OR(J11="",AA11=""),"",AA11/J11),"") -> 33.72 | AC11: =IF(AND($M11<>"",$Q11<0),COUNTIFS($M$6:M11,"<>",$Q$6:Q11,"<0"),"") | AD11: =IF(A11="","",ROW()) -> 11
A12: =IF('1_Data Entry'!$E12="","",IF(COUNTA('1_Data Entry'!C12:N12)=0,"",'1_Data Entry'!A12)) -> 7 | B12: =IF('1_Data Entry'!$E12="","",IF(A12="","",IF(S12<>"OK","Check row",IF(M12="","Open lot",IF(R12=0,"Closed lot","Partially sold"))))) -> Closed lot | C12: =IF(A12="","",'1_Data Entry'!C12) -> US | D12: =IF(A12="","",'1_Data Entry'!D12) -> MLP | E12: =IF(A12="","",'1_Data Entry'!E12) -> EPD | F12: =IF(E12="","",UPPER(TRIM(E12))) -> EPD | G12: =IF(F12="","",IFERROR(VLOOKUP(F12,'6_Reference Lists'!$A$4:$D$64,4,FALSE()),'1_Data Entry'!F12)) -> Enterprise Products Partners L.P. | H12: =IF('1_Data Entry'!$E12="","",IF(OR(F12="",I12="",J12="",K12=""),"",F12&"-"&TEXT(I12,"yyyymmdd")&"-"&SUBSTITUTE(TEXT(ROUND(J12,3),"0.###"),".","D")&"-"&SUBSTITUTE(TEXT(ROUND(K12,3),"0.###"),".","D"))) -> EPD-20250218-580D-33D72 | I12: =IF('1_Data Entry'!$E12="","",IF(A12="","",'1_Data Entry'!G12)) -> 45706 | J12: =IF('1_Data Entry'!$E12="","",IF(A12="","",'1_Data Entry'!H12)) -> 580 | K12: =IF('1_Data Entry'!$E12="","",IF(A12="","",'1_Data Entry'!I12)) -> 33.72 | L12: =IF('1_Data Entry'!$E12="","",IF(OR(J12="",K12=""),"",J12*K12)) -> 19557.6 | M12: =IF(A12="","",IF(OR('1_Data Entry'!L12="",'1_Data Entry'!L12<=0),"",'1_Data Entry'!J12)) -> 46090 | N12: =IF('1_Data Entry'!$E12="","",IF(OR(J12="",R12=""),"",MAX(J12-R12,0))) -> 580 | O12: =IF('1_Data Entry'!$E12="","",IF(A12="","",'1_Data Entry'!L12)) -> 38 | P12: =IF(OR(M12="",O12="",O12<=0,N12="",N12<=0),"",O12*N12) -> 22040 | Q12: =IF('1_Data Entry'!$E12="","",IF(OR(M12="",P12="",L12=""),"",P12-L12)) -> 2482.4 | R12: =IF(A12="","",IF('1_Data Entry'!M12<>"",'1_Data Entry'!M12,IF('1_Data Entry'!J12="",J12,""))) -> 0 | S12: =IF('1_Data Entry'!$E12="","",IF(A12="","",IF(OR(F12="",I12="",J12="",K12=""),"Check row",IF(AND(M12<>"",M12<I12),"Sell before buy",IF(AND(R12<>"",J12<R12),"Shares remaining exceeds buy",IF(AND(M12<>"",OR(O12="",O12<=0),N12>0),"Missing sale price","OK")))))) -> OK | T12: =IF('1_Data Entry'!$E12="","",IF(A12="","",IF(AND(Q12<0,M12<>""),"Yes","No"))) -> No | U12: =IF('1_Data Entry'!$E12="","",IF(OR(A12="",T12<>"Yes",M12=""),"No",IF(COUNTIFS($F$6:$F$505,F12,$I$6:$I$505,">="&M12-30,$I$6:$I$505,"<="&M12+30,$A$6:$A$505,"<>"&A12)>0,"Yes","No"))) -> No | V12: =IF('1_Data Entry'!$E12="","",IF(OR(A12="",U12<>"Yes",M12=""),"",M12+30)) | W12: =IF('1_Data Entry'!$E12="","",IF(A12="","",IF(S12="OK","Ready","Review row"))) -> Ready | X12: =IF(OR(I12="",M12=""),"",M12-I12) -> 384 | Y12: =IF(X12="","",IF(X12<=365,"Short-Term","Long-Term")) -> Long-Term | Z12: =IF('1_Data Entry'!$E12="","",SUM(SUMIFS('4_Wash Match Table'!R$7:R$500,'4_Wash Match Table'!L$7:L$500,H12),(SUMIFS('4_Wash Match Table'!AA$7:AA$500,'4_Wash Match Table'!U$7:U$500,H12)),(SUMIFS('4_Wash Match Table'!AJ$7:AJ$500,'4_Wash Match Table'!AD$7:AD$500,H12)),(SUMIFS('4_Wash Match Table'!AS$7:AS$500,'4_Wash Match Table'!AM$7:AM$500,H12)))) -> 0 | AA12: =IF('1_Data Entry'!$E12="","",IF(OR(L12="",Z12=""),"",L12+Z12)) -> 19557.6 | AB12: =IFERROR(IF(OR(J12="",AA12=""),"",AA12/J12),"") -> 33.72 | AC12: =IF(AND($M12<>"",$Q12<0),COUNTIFS($M$6:M12,"<>",$Q$6:Q12,"<0"),"") | AD12: =IF(A12="","",ROW()) -> 12
A13: =IF('1_Data Entry'!$E13="","",IF(COUNTA('1_Data Entry'!C13:N13)=0,"",'1_Data Entry'!A13)) -> 8 | B13: =IF('1_Data Entry'!$E13="","",IF(A13="","",IF(S13<>"OK","Check row",IF(M13="","Open lot",IF(R13=0,"Closed lot","Partially sold"))))) -> Closed lot | C13: =IF(A13="","",'1_Data Entry'!C13) -> US | D13: =IF(A13="","",'1_Data Entry'!D13) -> MLP | E13: =IF(A13="","",'1_Data Entry'!E13) -> EPD | F13: =IF(E13="","",UPPER(TRIM(E13))) -> EPD | G13: =IF(F13="","",IFERROR(VLOOKUP(F13,'6_Reference Lists'!$A$4:$D$64,4,FALSE()),'1_Data Entry'!F13)) -> Enterprise Products Partners L.P. | H13: =IF('1_Data Entry'!$E13="","",IF(OR(F13="",I13="",J13="",K13=""),"",F13&"-"&TEXT(I13,"yyyymmdd")&"-"&SUBSTITUTE(TEXT(ROUND(J13,3),"0.###"),".","D")&"-"&SUBSTITUTE(TEXT(ROUND(K13,3),"0.###"),".","D"))) -> EPD-20240216-580D-27D25 | I13: =IF('1_Data Entry'!$E13="","",IF(A13="","",'1_Data Entry'!G13)) -> 45338 | J13: =IF('1_Data Entry'!$E13="","",IF(A13="","",'1_Data Entry'!H13)) -> 580 | K13: =IF('1_Data Entry'!$E13="","",IF(A13="","",'1_Data Entry'!I13)) -> 27.25 | L13: =IF('1_Data Entry'!$E13="","",IF(OR(J13="",K13=""),"",J13*K13)) -> 15805 | M13: =IF(A13="","",IF(OR('1_Data Entry'!L13="",'1_Data Entry'!L13<=0),"",'1_Data Entry'!J13)) -> 46098 | N13: =IF('1_Data Entry'!$E13="","",IF(OR(J13="",R13=""),"",MAX(J13-R13,0))) -> 580 | O13: =IF('1_Data Entry'!$E13="","",IF(A13="","",'1_Data Entry'!L13)) -> 37.79 | P13: =IF(OR(M13="",O13="",O13<=0,N13="",N13<=0),"",O13*N13) -> 21918.2 | Q13: =IF('1_Data Entry'!$E13="","",IF(OR(M13="",P13="",L13=""),"",P13-L13)) -> 6113.2 | R13: =IF(A13="","",IF('1_Data Entry'!M13<>"",'1_Data Entry'!M13,IF('1_Data Entry'!J13="",J13,""))) -> 0 | S13: =IF('1_Data Entry'!$E13="","",IF(A13="","",IF(OR(F13="",I13="",J13="",K13=""),"Check row",IF(AND(M13<>"",M13<I13),"Sell before buy",IF(AND(R13<>"",J13<R13),"Shares remaining exceeds buy",IF(AND(M13<>"",OR(O13="",O13<=0),N13>0),"Missing sale price","OK")))))) -> OK | T13: =IF('1_Data Entry'!$E13="","",IF(A13="","",IF(AND(Q13<0,M13<>""),"Yes","No"))) -> No | U13: =IF('1_Data Entry'!$E13="","",IF(OR(A13="",T13<>"Yes",M13=""),"No",IF(COUNTIFS($F$6:$F$505,F13,$I$6:$I$505,">="&M13-30,$I$6:$I$505,"<="&M13+30,$A$6:$A$505,"<>"&A13)>0,"Yes","No"))) -> No | V13: =IF('1_Data Entry'!$E13="","",IF(OR(A13="",U13<>"Yes",M13=""),"",M13+30)) | W13: =IF('1_Data Entry'!$E13="","",IF(A13="","",IF(S13="OK","Ready","Review row"))) -> Ready | X13: =IF(OR(I13="",M13=""),"",M13-I13) -> 760 | Y13: =IF(X13="","",IF(X13<=365,"Short-Term","Long-Term")) -> Long-Term | Z13: =IF('1_Data Entry'!$E13="","",SUM(SUMIFS('4_Wash Match Table'!R$7:R$500,'4_Wash Match Table'!L$7:L$500,H13),(SUMIFS('4_Wash Match Table'!AA$7:AA$500,'4_Wash Match Table'!U$7:U$500,H13)),(SUMIFS('4_Wash Match Table'!AJ$7:AJ$500,'4_Wash Match Table'!AD$7:AD$500,H13)),(SUMIFS('4_Wash Match Table'!AS$7:AS$500,'4_Wash Match Table'!AM$7:AM$500,H13)))) -> 0 | AA13: =IF('1_Data Entry'!$E13="","",IF(OR(L13="",Z13=""),"",L13+Z13)) -> 15805 | AB13: =IFERROR(IF(OR(J13="",AA13=""),"",AA13/J13),"") -> 27.25 | AC13: =IF(AND($M13<>"",$Q13<0),COUNTIFS($M$6:M13,"<>",$Q$6:Q13,"<0"),"") | AD13: =IF(A13="","",ROW()) -> 13
A14: =IF('1_Data Entry'!$E14="","",IF(COUNTA('1_Data Entry'!C14:N14)=0,"",'1_Data Entry'!A14)) -> 9 | B14: =IF('1_Data Entry'!$E14="","",IF(A14="","",IF(S14<>"OK","Check row",IF(M14="","Open lot",IF(R14=0,"Closed lot","Partially sold"))))) -> Closed lot | C14: =IF(A14="","",'1_Data Entry'!C14) -> US | D14: =IF(A14="","",'1_Data Entry'!D14) -> MLP | E14: =IF(A14="","",'1_Data Entry'!E14) -> EPD | F14: =IF(E14="","",UPPER(TRIM(E14))) -> EPD | G14: =IF(F14="","",IFERROR(VLOOKUP(F14,'6_Reference Lists'!$A$4:$D$64,4,FALSE()),'1_Data Entry'!F14)) -> Enterprise Products Partners L.P. | H14: =IF('1_Data Entry'!$E14="","",IF(OR(F14="",I14="",J14="",K14=""),"",F14&"-"&TEXT(I14,"yyyymmdd")&"-"&SUBSTITUTE(TEXT(ROUND(J14,3),"0.###"),".","D")&"-"&SUBSTITUTE(TEXT(ROUND(K14,3),"0.###"),".","D"))) -> EPD-20240216-351D-27D25 | I14: =IF('1_Data Entry'!$E14="","",IF(A14="","",'1_Data Entry'!G14)) -> 45338 | J14: =IF('1_Data Entry'!$E14="","",IF(A14="","",'1_Data Entry'!H14)) -> 351 | K14: =IF('1_Data Entry'!$E14="","",IF(A14="","",'1_Data Entry'!I14)) -> 27.25 | L14: =IF('1_Data Entry'!$E14="","",IF(OR(J14="",K14=""),"",J14*K14)) -> 9564.75 | M14: =IF(A14="","",IF(OR('1_Data Entry'!L14="",'1_Data Entry'!L14<=0),"",'1_Data Entry'!J14)) -> 46098 | N14: =IF('1_Data Entry'!$E14="","",IF(OR(J14="",R14=""),"",MAX(J14-R14,0))) -> 351 | O14: =IF('1_Data Entry'!$E14="","",IF(A14="","",'1_Data Entry'!L14)) -> 37.79 | P14: =IF(OR(M14="",O14="",O14<=0,N14="",N14<=0),"",O14*N14) -> 13264.29 | Q14: =IF('1_Data Entry'!$E14="","",IF(OR(M14="",P14="",L14=""),"",P14-L14)) -> 3699.54 | R14: =IF(A14="","",IF('1_Data Entry'!M14<>"",'1_Data Entry'!M14,IF('1_Data Entry'!J14="",J14,""))) -> 0 | S14: =IF('1_Data Entry'!$E14="","",IF(A14="","",IF(OR(F14="",I14="",J14="",K14=""),"Check row",IF(AND(M14<>"",M14<I14),"Sell before buy",IF(AND(R14<>"",J14<R14),"Shares remaining exceeds buy",IF(AND(M14<>"",OR(O14="",O14<=0),N14>0),"Missing sale price","OK")))))) -> OK | T14: =IF('1_Data Entry'!$E14="","",IF(A14="","",IF(AND(Q14<0,M14<>""),"Yes","No"))) -> No | U14: =IF('1_Data Entry'!$E14="","",IF(OR(A14="",T14<>"Yes",M14=""),"No",IF(COUNTIFS($F$6:$F$505,F14,$I$6:$I$505,">="&M14-30,$I$6:$I$505,"<="&M14+30,$A$6:$A$505,"<>"&A14)>0,"Yes","No"))) -> No | V14: =IF('1_Data Entry'!$E14="","",IF(OR(A14="",U14<>"Yes",M14=""),"",M14+30)) | W14: =IF('1_Data Entry'!$E14="","",IF(A14="","",IF(S14="OK","Ready","Review row"))) -> Ready | X14: =IF(OR(I14="",M14=""),"",M14-I14) -> 760 | Y14: =IF(X14="","",IF(X14<=365,"Short-Term","Long-Term")) -> Long-Term | Z14: =IF('1_Data Entry'!$E14="","",SUM(SUMIFS('4_Wash Match Table'!R$7:R$500,'4_Wash Match Table'!L$7:L$500,H14),(SUMIFS('4_Wash Match Table'!AA$7:AA$500,'4_Wash Match Table'!U$7:U$500,H14)),(SUMIFS('4_Wash Match Table'!AJ$7:AJ$500,'4_Wash Match Table'!AD$7:AD$500,H14)),(SUMIFS('4_Wash Match Table'!AS$7:AS$500,'4_Wash Match Table'!AM$7:AM$500,H14)))) -> 0 | AA14: =IF('1_Data Entry'!$E14="","",IF(OR(L14="",Z14=""),"",L14+Z14)) -> 9564.75 | AB14: =IFERROR(IF(OR(J14="",AA14=""),"",AA14/J14),"") -> 27.25 | AC14: =IF(AND($M14<>"",$Q14<0),COUNTIFS($M$6:M14,"<>",$Q$6:Q14,"<0"),"") | AD14: =IF(A14="","",ROW()) -> 14
A15: =IF('1_Data Entry'!$E15="","",IF(COUNTA('1_Data Entry'!C15:N15)=0,"",'1_Data Entry'!A15)) -> 10 | B15: =IF('1_Data Entry'!$E15="","",IF(A15="","",IF(S15<>"OK","Check row",IF(M15="","Open lot",IF(R15=0,"Closed lot","Partially sold"))))) -> Closed lot | C15: =IF(A15="","",'1_Data Entry'!C15) -> US | D15: =IF(A15="","",'1_Data Entry'!D15) -> ETF | E15: =IF(A15="","",'1_Data Entry'!E15) -> ITOT | F15: =IF(E15="","",UPPER(TRIM(E15))) -> ITOT | G15: =IF(F15="","",IFERROR(VLOOKUP(F15,'6_Reference Lists'!$A$4:$D$64,4,FALSE()),'1_Data Entry'!F15)) -> iShares Core S&P Total U.S. Stock Market ETF | H15: =IF('1_Data Entry'!$E15="","",IF(OR(F15="",I15="",J15="",K15=""),"",F15&"-"&TEXT(I15,"yyyymmdd")&"-"&SUBSTITUTE(TEXT(ROUND(J15,3),"0.###"),".","D")&"-"&SUBSTITUTE(TEXT(ROUND(K15,3),"0.###"),".","D"))) -> ITOT-20260317-0D883-150D63 | I15: =IF('1_Data Entry'!$E15="","",IF(A15="","",'1_Data Entry'!G15)) -> 46098 | J15: =IF('1_Data Entry'!$E15="","",IF(A15="","",'1_Data Entry'!H15)) -> 0.883 | K15: =IF('1_Data Entry'!$E15="","",IF(A15="","",'1_Data Entry'!I15)) -> 150.63 | L15: =IF('1_Data Entry'!$E15="","",IF(OR(J15="",K15=""),"",J15*K15)) -> 133.00629 | M15: =IF(A15="","",IF(OR('1_Data Entry'!L15="",'1_Data Entry'!L15<=0),"",'1_Data Entry'!J15)) -> 46101 | N15: =IF('1_Data Entry'!$E15="","",IF(OR(J15="",R15=""),"",MAX(J15-R15,0))) -> 0.883 | O15: =IF('1_Data Entry'!$E15="","",IF(A15="","",'1_Data Entry'!L15)) -> 142.93 | P15: =IF(OR(M15="",O15="",O15<=0,N15="",N15<=0),"",O15*N15) -> 126.20719 | Q15: =IF('1_Data Entry'!$E15="","",IF(OR(M15="",P15="",L15=""),"",P15-L15)) -> -6.7991 | R15: =IF(A15="","",IF('1_Data Entry'!M15<>"",'1_Data Entry'!M15,IF('1_Data Entry'!J15="",J15,""))) -> 0 | S15: =IF('1_Data Entry'!$E15="","",IF(A15="","",IF(OR(F15="",I15="",J15="",K15=""),"Check row",IF(AND(M15<>"",M15<I15),"Sell before buy",IF(AND(R15<>"",J15<R15),"Shares remaining exceeds buy",IF(AND(M15<>"",OR(O15="",O15<=0),N15>0),"Missing sale price","OK")))))) -> OK | T15: =IF('1_Data Entry'!$E15="","",IF(A15="","",IF(AND(Q15<0,M15<>""),"Yes","No"))) -> Yes | U15: =IF('1_Data Entry'!$E15="","",IF(OR(A15="",T15<>"Yes",M15=""),"No",IF(COUNTIFS($F$6:$F$505,F15,$I$6:$I$505,">="&M15-30,$I$6:$I$505,"<="&M15+30,$A$6:$A$505,"<>"&A15)>0,"Yes","No"))) -> Yes | V15: =IF('1_Data Entry'!$E15="","",IF(OR(A15="",U15<>"Yes",M15=""),"",M15+30)) -> 46131 | W15: =IF('1_Data Entry'!$E15="","",IF(A15="","",IF(S15="OK","Ready","Review row"))) -> Ready | X15: =IF(OR(I15="",M15=""),"",M15-I15) -> 3 | Y15: =IF(X15="","",IF(X15<=365,"Short-Term","Long-Term")) -> Short-Term | Z15: =IF('1_Data Entry'!$E15="","",SUM(SUMIFS('4_Wash Match Table'!R$7:R$500,'4_Wash Match Table'!L$7:L$500,H15),(SUMIFS('4_Wash Match Table'!AA$7:AA$500,'4_Wash Match Table'!U$7:U$500,H15)),(SUMIFS('4_Wash Match Table'!AJ$7:AJ$500,'4_Wash Match Table'!AD$7:AD$500,H15)),(SUMIFS('4_Wash Match Table'!AS$7:AS$500,'4_Wash Match Table'!AM$7:AM$500,H15)))) -> 0 | AA15: =IF('1_Data Entry'!$E15="","",IF(OR(L15="",Z15=""),"",L15+Z15)) -> 133.00629 | AB15: =IFERROR(IF(OR(J15="",AA15=""),"",AA15/J15),"") -> 150.63 | AC15: =IF(AND($M15<>"",$Q15<0),COUNTIFS($M$6:M15,"<>",$Q$6:Q15,"<0"),"") -> 1 | AD15: =IF(A15="","",ROW()) -> 15
A16: =IF('1_Data Entry'!$E16="","",IF(COUNTA('1_Data Entry'!C16:N16)=0,"",'1_Data Entry'!A16)) -> 11 | B16: =IF('1_Data Entry'!$E16="","",IF(A16="","",IF(S16<>"OK","Check row",IF(M16="","Open lot",IF(R16=0,"Closed lot","Partially sold"))))) -> Closed lot | C16: =IF(A16="","",'1_Data Entry'!C16) -> US | D16: =IF(A16="","",'1_Data Entry'!D16) -> ETF | E16: =IF(A16="","",'1_Data Entry'!E16) -> ITOT | F16: =IF(E16="","",UPPER(TRIM(E16))) -> ITOT | G16: =IF(F16="","",IFERROR(VLOOKUP(F16,'6_Reference Lists'!$A$4:$D$64,4,FALSE()),'1_Data Entry'!F16)) -> iShares Core S&P Total U.S. Stock Market ETF | H16: =IF('1_Data Entry'!$E16="","",IF(OR(F16="",I16="",J16="",K16=""),"",F16&"-"&TEXT(I16,"yyyymmdd")&"-"&SUBSTITUTE(TEXT(ROUND(J16,3),"0.###"),".","D")&"-"&SUBSTITUTE(TEXT(ROUND(K16,3),"0.###"),".","D"))) -> ITOT-20260317-143D-146D76 | I16: =IF('1_Data Entry'!$E16="","",IF(A16="","",'1_Data Entry'!G16)) -> 46098 | J16: =IF('1_Data Entry'!$E16="","",IF(A16="","",'1_Data Entry'!H16)) -> 143 | K16: =IF('1_Data Entry'!$E16="","",IF(A16="","",'1_Data Entry'!I16)) -> 146.76 | L16: =IF('1_Data Entry'!$E16="","",IF(OR(J16="",K16=""),"",J16*K16)) -> 20986.68 | M16: =IF(A16="","",IF(OR('1_Data Entry'!L16="",'1_Data Entry'!L16<=0),"",'1_Data Entry'!J16)) -> 46101 | N16: =IF('1_Data Entry'!$E16="","",IF(OR(J16="",R16=""),"",MAX(J16-R16,0))) -> 143 | O16: =IF('1_Data Entry'!$E16="","",IF(A16="","",'1_Data Entry'!L16)) -> 142.93 | P16: =IF(OR(M16="",O16="",O16<=0,N16="",N16<=0),"",O16*N16) -> 20438.99 | Q16: =IF('1_Data Entry'!$E16="","",IF(OR(M16="",P16="",L16=""),"",P16-L16)) -> -547.69 | R16: =IF(A16="","",IF('1_Data Entry'!M16<>"",'1_Data Entry'!M16,IF('1_Data Entry'!J16="",J16,""))) -> 0 | S16: =IF('1_Data Entry'!$E16="","",IF(A16="","",IF(OR(F16="",I16="",J16="",K16=""),"Check row",IF(AND(M16<>"",M16<I16),"Sell before buy",IF(AND(R16<>"",J16<R16),"Shares remaining exceeds buy",IF(AND(M16<>"",OR(O16="",O16<=0),N16>0),"Missing sale price","OK")))))) -> OK | T16: =IF('1_Data Entry'!$E16="","",IF(A16="","",IF(AND(Q16<0,M16<>""),"Yes","No"))) -> Yes | U16: =IF('1_Data Entry'!$E16="","",IF(OR(A16="",T16<>"Yes",M16=""),"No",IF(COUNTIFS($F$6:$F$505,F16,$I$6:$I$505,">="&M16-30,$I$6:$I$505,"<="&M16+30,$A$6:$A$505,"<>"&A16)>0,"Yes","No"))) -> Yes | V16: =IF('1_Data Entry'!$E16="","",IF(OR(A16="",U16<>"Yes",M16=""),"",M16+30)) -> 46131 | W16: =IF('1_Data Entry'!$E16="","",IF(A16="","",IF(S16="OK","Ready","Review row"))) -> Ready | X16: =IF(OR(I16="",M16=""),"",M16-I16) -> 3 | Y16: =IF(X16="","",IF(X16<=365,"Short-Term","Long-Term")) -> Short-Term | Z16: =IF('1_Data Entry'!$E16="","",SUM(SUMIFS('4_Wash Match Table'!R$7:R$500,'4_Wash Match Table'!L$7:L$500,H16),(SUMIFS('4_Wash Match Table'!AA$7:AA$500,'4_Wash Match Table'!U$7:U$500,H16)),(SUMIFS('4_Wash Match Table'!AJ$7:AJ$500,'4_Wash Match Table'!AD$7:AD$500,H16)),(SUMIFS('4_Wash Match Table'!AS$7:AS$500,'4_Wash Match Table'!AM$7:AM$500,H16)))) -> 0 | AA16: =IF('1_Data Entry'!$E16="","",IF(OR(L16="",Z16=""),"",L16+Z16)) -> 20986.68 | AB16: =IFERROR(IF(OR(J16="",AA16=""),"",AA16/J16),"") -> 146.76 | AC16: =IF(AND($M16<>"",$Q16<0),COUNTIFS($M$6:M16,"<>",$Q$6:Q16,"<0"),"") -> 2 | AD16: =IF(A16="","",ROW()) -> 16
A17: =IF('1_Data Entry'!$E17="","",IF(COUNTA('1_Data Entry'!C17:N17)=0,"",'1_Data Entry'!A17)) -> 12 | B17: =IF('1_Data Entry'!$E17="","",IF(A17="","",IF(S17<>"OK","Check row",IF(M17="","Open lot",IF(R17=0,"Closed lot","Partially sold"))))) -> Closed lot | C17: =IF(A17="","",'1_Data Entry'!C17) -> US | D17: =IF(A17="","",'1_Data Entry'!D17) -> ETF | E17: =IF(A17="","",'1_Data Entry'!E17) -> SCHB | F17: =IF(E17="","",UPPER(TRIM(E17))) -> SCHB | G17: =IF(F17="","",IFERROR(VLOOKUP(F17,'6_Reference Lists'!$A$4:$D$64,4,FALSE()),'1_Data Entry'!F17)) -> Schwab U.S. Broad Market ETF | H17: =IF('1_Data Entry'!$E17="","",IF(OR(F17="",I17="",J17="",K17=""),"",F17&"-"&TEXT(I17,"yyyymmdd")&"-"&SUBSTITUTE(TEXT(ROUND(J17,3),"0.###"),".","D")&"-"&SUBSTITUTE(TEXT(ROUND(K17,3),"0.###"),".","D"))) -> SCHB-20260317-0D872-25D952 | I17: =IF('1_Data Entry'!$E17="","",IF(A17="","",'1_Data Entry'!G17)) -> 46098 | J17: =IF('1_Data Entry'!$E17="","",IF(A17="","",'1_Data Entry'!H17)) -> 0.872 | K17: =IF('1_Data Entry'!$E17="","",IF(A17="","",'1_Data Entry'!I17)) -> 25.951835 | L17: =IF('1_Data Entry'!$E17="","",IF(OR(J17="",K17=""),"",J17*K17)) -> 22.63 | M17: =IF(A17="","",IF(OR('1_Data Entry'!L17="",'1_Data Entry'!L17<=0),"",'1_Data Entry'!J17)) -> 46108 | N17: =IF('1_Data Entry'!$E17="","",IF(OR(J17="",R17=""),"",MAX(J17-R17,0))) -> 0.872 | O17: =IF('1_Data Entry'!$E17="","",IF(A17="","",'1_Data Entry'!L17)) -> 24.610092 | P17: =IF(OR(M17="",O17="",O17<=0,N17="",N17<=0),"",O17*N17) -> 21.46 | Q17: =IF('1_Data Entry'!$E17="","",IF(OR(M17="",P17="",L17=""),"",P17-L17)) -> -1.17 | R17: =IF(A17="","",IF('1_Data Entry'!M17<>"",'1_Data Entry'!M17,IF('1_Data Entry'!J17="",J17,""))) -> 0 | S17: =IF('1_Data Entry'!$E17="","",IF(A17="","",IF(OR(F17="",I17="",J17="",K17=""),"Check row",IF(AND(M17<>"",M17<I17),"Sell before buy",IF(AND(R17<>"",J17<R17),"Shares remaining exceeds buy",IF(AND(M17<>"",OR(O17="",O17<=0),N17>0),"Missing sale price","OK")))))) -> OK | T17: =IF('1_Data Entry'!$E17="","",IF(A17="","",IF(AND(Q17<0,M17<>""),"Yes","No"))) -> Yes | U17: =IF('1_Data Entry'!$E17="","",IF(OR(A17="",T17<>"Yes",M17=""),"No",IF(COUNTIFS($F$6:$F$505,F17,$I$6:$I$505,">="&M17-30,$I$6:$I$505,"<="&M17+30,$A$6:$A$505,"<>"&A17)>0,"Yes","No"))) -> Yes | V17: =IF('1_Data Entry'!$E17="","",IF(OR(A17="",U17<>"Yes",M17=""),"",M17+30)) -> 46138 | W17: =IF('1_Data Entry'!$E17="","",IF(A17="","",IF(S17="OK","Ready","Review row"))) -> Ready | X17: =IF(OR(I17="",M17=""),"",M17-I17) -> 10 | Y17: =IF(X17="","",IF(X17<=365,"Short-Term","Long-Term")) -> Short-Term | Z17: =IF('1_Data Entry'!$E17="","",SUM(SUMIFS('4_Wash Match Table'!R$7:R$500,'4_Wash Match Table'!L$7:L$500,H17),(SUMIFS('4_Wash Match Table'!AA$7:AA$500,'4_Wash Match Table'!U$7:U$500,H17)),(SUMIFS('4_Wash Match Table'!AJ$7:AJ$500,'4_Wash Match Table'!AD$7:AD$500,H17)),(SUMIFS('4_Wash Match Table'!AS$7:AS$500,'4_Wash Match Table'!AM$7:AM$500,H17)))) -> 0 | AA17: =IF('1_Data Entry'!$E17="","",IF(OR(L17="",Z17=""),"",L17+Z17)) -> 22.63 | AB17: =IFERROR(IF(OR(J17="",AA17=""),"",AA17/J17),"") -> 25.951835 | AC17: =IF(AND($M17<>"",$Q17<0),COUNTIFS($M$6:M17,"<>",$Q$6:Q17,"<0"),"") -> 3 | AD17: =IF(A17="","",ROW()) -> 17
... A33: =IF('1_Data Entry'!$E33="","",IF(COUNTA('1_Data Entry'!C33:N33)=0,"",'1_Data Entry'!A33)) -> 28 | B33: =IF('1_Data Entry'!$E33="","",IF(A33="","",IF(S33<>"OK","Check row",IF(M33="","Open lot",IF(R33=0,"Closed lot","Partially sold"))))) -> Open lot | C33: =IF(A33="","",'1_Data Entry'!C33) -> International | D33: =IF(A33="","",'1_Data Entry'!D33) -> ETF | E33: =IF(A33="","",'1_Data Entry'!E33) -> VXUS | F33: =IF(E33="","",UPPER(TRIM(E33))) -> VXUS | G33: =IF(F33="","",IFERROR(VLOOKUP(F33,'6_Reference Lists'!$A$4:$D$64,4,FALSE()),'1_Data Entry'!F33)) -> Vanguard Total International Stock ETF | H33: =IF('1_Data Entry'!$E33="","",IF(OR(F33="",I33="",J33="",K33=""),"",F33&"-"&TEXT(I33,"yyyymmdd")&"-"&SUBSTITUTE(TEXT(ROUND(J33,3),"0.###"),".","D")&"-"&SUBSTITUTE(TEXT(ROUND(K33,3),"0.###"),".","D"))) -> VXUS-20260320-0D98-74D633 | I33: =IF('1_Data Entry'!$E33="","",IF(A33="","",'1_Data Entry'!G33)) -> 46101 | J33: =IF('1_Data Entry'!$E33="","",IF(A33="","",'1_Data Entry'!H33)) -> 0.98 | K33: =IF('1_Data Entry'!$E33="","",IF(A33="","",'1_Data Entry'!I33)) -> 74.632653 | L33: =IF('1_Data Entry'!$E33="","",IF(OR(J33="",K33=""),"",J33*K33)) -> 73.14 | M33: =IF(A33="","",IF(OR('1_Data Entry'!L33="",'1_Data Entry'!L33<=0),"",'1_Data Entry'!J33)) | N33: =IF('1_Data Entry'!$E33="","",IF(OR(J33="",R33=""),"",MAX(J33-R33,0))) -> 0 | O33: =IF('1_Data Entry'!$E33="","",IF(A33="","",'1_Data Entry'!L33)) -> 0 | P33: =IF(OR(M33="",O33="",O33<=0,N33="",N33<=0),"",O33*N33) | Q33: =IF('1_Data Entry'!$E33="","",IF(OR(M33="",P33="",L33=""),"",P33-L33)) | R33: =IF(A33="","",IF('1_Data Entry'!M33<>"",'1_Data Entry'!M33,IF('1_Data Entry'!J33="",J33,""))) -> 0.98 | S33: =IF('1_Data Entry'!$E33="","",IF(A33="","",IF(OR(F33="",I33="",J33="",K33=""),"Check row",IF(AND(M33<>"",M33<I33),"Sell before buy",IF(AND(R33<>"",J33<R33),"Shares remaining exceeds buy",IF(AND(M33<>"",OR(O33="",O33<=0),N33>0),"Missing sale price","OK")))))) -> OK | T33: =IF('1_Data Entry'!$E33="","",IF(A33="","",IF(AND(Q33<0,M33<>""),"Yes","No"))) -> No | U33: =IF('1_Data Entry'!$E33="","",IF(OR(A33="",T33<>"Yes",M33=""),"No",IF(COUNTIFS($F$6:$F$505,F33,$I$6:$I$505,">="&M33-30,$I$6:$I$505,"<="&M33+30,$A$6:$A$505,"<>"&A33)>0,"Yes","No"))) -> No | V33: =IF('1_Data Entry'!$E33="","",IF(OR(A33="",U33<>"Yes",M33=""),"",M33+30)) | W33: =IF('1_Data Entry'!$E33="","",IF(A33="","",IF(S33="OK","Ready","Review row"))) -> Ready | X33: =IF(OR(I33="",M33=""),"",M33-I33) | Y33: =IF(X33="","",IF(X33<=365,"Short-Term","Long-Term")) | Z33: =IF('1_Data Entry'!$E33="","",SUM(SUMIFS('4_Wash Match Table'!R$7:R$500,'4_Wash Match Table'!L$7:L$500,H33),(SUMIFS('4_Wash Match Table'!AA$7:AA$500,'4_Wash Match Table'!U$7:U$500,H33)),(SUMIFS('4_Wash Match Table'!AJ$7:AJ$500,'4_Wash Match Table'!AD$7:AD$500,H33)),(SUMIFS('4_Wash Match Table'!AS$7:AS$500,'4_Wash Match Table'!AM$7:AM$500,H33)))) -> 0 | AA33: =IF('1_Data Entry'!$E33="","",IF(OR(L33="",Z33=""),"",L33+Z33)) -> 73.14 | AB33: =IFERROR(IF(OR(J33="",AA33=""),"",AA33/J33),"") -> 74.632653 | AC33: =IF(AND($M33<>"",$Q33<0),COUNTIFS($M$6:M33,"<>",$Q$6:Q33,"<0"),"") | AD33: =IF(A33="","",ROW()) -> 33
A34: =IF('1_Data Entry'!$E34="","",IF(COUNTA('1_Data Entry'!C34:N34)=0,"",'1_Data Entry'!A34)) -> 29 | B34: Open lot | C34: =IF(A34="","",'1_Data Entry'!C34) -> US | D34: =IF(A34="","",'1_Data Entry'!D34) -> MLP | E34: =IF(A34="","",'1_Data Entry'!E34) -> EPD | F34: =IF(E34="","",UPPER(TRIM(E34))) -> EPD | G34: =IF(F34="","",IFERROR(VLOOKUP(F34,'6_Reference Lists'!$A$4:$D$64,4,FALSE()),'1_Data Entry'!F34)) -> Enterprise Products Partners L.P. | H34: =IF('1_Data Entry'!$E34="","",IF(OR(F34="",I34="",J34="",K34=""),"",F34&"-"&TEXT(I34,"yyyymmdd")&"-"&SUBSTITUTE(TEXT(ROUND(J34,3),"0.###"),".","D")&"-"&SUBSTITUTE(TEXT(ROUND(K34,3),"0.###"),".","D"))) -> EPD-20251030-310D-30D53 | I34: =IF('1_Data Entry'!$E34="","",IF(A34="","",'1_Data Entry'!G34)) -> 45960 | J34: =IF('1_Data Entry'!$E34="","",IF(A34="","",'1_Data Entry'!H34)) -> 310 | K34: =IF('1_Data Entry'!$E34="","",IF(A34="","",'1_Data Entry'!I34)) -> 30.53 | L34: =IF('1_Data Entry'!$E34="","",IF(OR(J34="",K34=""),"",J34*K34)) -> 9464.3 | M34: =IF(A34="","",IF(OR('1_Data Entry'!L34="",'1_Data Entry'!L34<=0),"",'1_Data Entry'!J34)) -> 46111 | N34: =IF('1_Data Entry'!$E34="","",IF(OR(J34="",R34=""),"",MAX(J34-R34,0))) -> 310 | O34: =IF('1_Data Entry'!$E34="","",IF(A34="","",'1_Data Entry'!L34)) -> 39.0514 | P34: =IF(OR(M34="",O34="",O34<=0,N34="",N34<=0),"",O34*N34) -> 12105.934 | Q34: =IF('1_Data Entry'!$E34="","",IF(OR(M34="",P34="",L34=""),"",P34-L34)) -> 2641.634 | R34: =IF(A34="","",IF('1_Data Entry'!M34<>"",'1_Data Entry'!M34,IF('1_Data Entry'!J34="",J34,""))) -> 0 | S34: OK | T34: No | U34: =IF('1_Data Entry'!$E34="","",IF(OR(A34="",T34<>"Yes",M34=""),"No",IF(COUNTIFS($F$6:$F$505,F34,$I$6:$I$505,">="&M34-30,$I$6:$I$505,"<="&M34+30,$A$6:$A$505,"<>"&A34)>0,"Yes","No"))) -> No | V34: =IF('1_Data Entry'!$E34="","",IF(OR(A34="",U34<>"Yes",M34=""),"",M34+30)) | W34: Ready | X34: =IF(OR(I34="",M34=""),"",M34-I34) -> 151 | Y34: =IF(X34="","",IF(X34<=365,"Short-Term","Long-Term")) -> Short-Term | Z34: =IF('1_Data Entry'!$E34="","",SUM(SUMIFS('4_Wash Match Table'!R$7:R$500,'4_Wash Match Table'!L$7:L$500,H34),(SUMIFS('4_Wash Match Table'!AA$7:AA$500,'4_Wash Match Table'!U$7:U$500,H34)),(SUMIFS('4_Wash Match Table'!AJ$7:AJ$500,'4_Wash Match Table'!AD$7:AD$500,H34)),(SUMIFS('4_Wash Match Table'!AS$7:AS$500,'4_Wash Match Table'!AM$7:AM$500,H34)))) -> 0 | AA34: =IF('1_Data Entry'!$E34="","",IF(OR(L34="",Z34=""),"",L34+Z34)) -> 9464.3 | AB34: =IFERROR(IF(OR(J34="",AA34=""),"",AA34/J34),"") -> 30.53 | AC34: =IF(AND($M34<>"",$Q34<0),COUNTIFS($M$6:M34,"<>",$Q$6:Q34,"<0"),"") | AD34: =IF(A34="","",ROW()) -> 34
A35: =IF('1_Data Entry'!$E35="","",IF(COUNTA('1_Data Entry'!C35:N35)=0,"",'1_Data Entry'!A35)) -> 30 | B35: =IF('1_Data Entry'!$E35="","",IF(A35="","",IF(S35<>"OK","Check row",IF(M35="","Open lot",IF(R35=0,"Closed lot","Partially sold"))))) -> Open lot | C35: =IF(A35="","",'1_Data Entry'!C35) -> US | D35: =IF(A35="","",'1_Data Entry'!D35) -> ETF | E35: =IF(A35="","",'1_Data Entry'!E35) -> schb | F35: =IF(E35="","",UPPER(TRIM(E35))) -> SCHB | G35: =IF(F35="","",IFERROR(VLOOKUP(F35,'6_Reference Lists'!$A$4:$D$64,4,FALSE()),'1_Data Entry'!F35)) -> Schwab U.S. Broad Market ETF | H35: =IF('1_Data Entry'!$E35="","",IF(OR(F35="",I35="",J35="",K35=""),"",F35&"-"&TEXT(I35,"yyyymmdd")&"-"&SUBSTITUTE(TEXT(ROUND(J35,3),"0.###"),".","D")&"-"&SUBSTITUTE(TEXT(ROUND(K35,3),"0.###"),".","D"))) -> SCHB-20260330-50D-20D | I35: =IF('1_Data Entry'!$E35="","",IF(A35="","",'1_Data Entry'!G35)) -> 46111 | J35: =IF('1_Data Entry'!$E35="","",IF(A35="","",'1_Data Entry'!H35)) -> 50 | K35: =IF('1_Data Entry'!$E35="","",IF(A35="","",'1_Data Entry'!I35)) -> 20 | L35: =IF('1_Data Entry'!$E35="","",IF(OR(J35="",K35=""),"",J35*K35)) -> 1000 | M35: =IF(A35="","",IF(OR('1_Data Entry'!L35="",'1_Data Entry'!L35<=0),"",'1_Data Entry'!J35)) | N35: =IF('1_Data Entry'!$E35="","",IF(OR(J35="",R35=""),"",MAX(J35-R35,0))) -> 0 | O35: =IF('1_Data Entry'!$E35="","",IF(A35="","",'1_Data Entry'!L35)) -> 0 | P35: =IF(OR(M35="",O35="",O35<=0,N35="",N35<=0),"",O35*N35) | Q35: =IF('1_Data Entry'!$E35="","",IF(OR(M35="",P35="",L35=""),"",P35-L35)) | R35: =IF(A35="","",IF('1_Data Entry'!M35<>"",'1_Data Entry'!M35,IF('1_Data Entry'!J35="",J35,""))) -> 50 | S35: =IF('1_Data Entry'!$E35="","",IF(A35="","",IF(OR(F35="",I35="",J35="",K35=""),"Check row",IF(AND(M35<>"",M35<I35),"Sell before buy",IF(AND(R35<>"",J35<R35),"Shares remaining exceeds buy",IF(AND(M35<>"",OR(O35="",O35<=0),N35>0),"Missing sale price","OK")))))) -> OK | T35: =IF('1_Data Entry'!$E35="","",IF(A35="","",IF(AND(Q35<0,M35<>""),"Yes","No"))) -> No | U35: =IF('1_Data Entry'!$E35="","",IF(OR(A35="",T35<>"Yes",M35=""),"No",IF(COUNTIFS($F$6:$F$505,F35,$I$6:$I$505,">="&M35-30,$I$6:$I$505,"<="&M35+30,$A$6:$A$505,"<>"&A35)>0,"Yes","No"))) -> No | V35: =IF('1_Data Entry'!$E35="","",IF(OR(A35="",U35<>"Yes",M35=""),"",M35+30)) | W35: =IF('1_Data Entry'!$E35="","",IF(A35="","",IF(S35="OK","Ready","Review row"))) -> Ready | X35: =IF(OR(I35="",M35=""),"",M35-I35) | Y35: =IF(X35="","",IF(X35<=365,"Short-Term","Long-Term")) | Z35: =IF('1_Data Entry'!$E35="","",SUM(SUMIFS('4_Wash Match Table'!R$7:R$500,'4_Wash Match Table'!L$7:L$500,H35),(SUMIFS('4_Wash Match Table'!AA$7:AA$500,'4_Wash Match Table'!U$7:U$500,H35)),(SUMIFS('4_Wash Match Table'!AJ$7:AJ$500,'4_Wash Match Table'!AD$7:AD$500,H35)),(SUMIFS('4_Wash Match Table'!AS$7:AS$500,'4_Wash Match Table'!AM$7:AM$500,H35)))) -> 67.478297 | AA35: =IF('1_Data Entry'!$E35="","",IF(OR(L35="",Z35=""),"",L35+Z35)) -> 1067.4783 | AB35: =IFERROR(IF(OR(J35="",AA35=""),"",AA35/J35),"") -> 21.349566 | AC35: =IF(AND($M35<>"",$Q35<0),COUNTIFS($M$6:M35,"<>",$Q$6:Q35,"<0"),"") | AD35: =IF(A35="","",ROW()) -> 35
A36: =IF('1_Data Entry'!$E36="","",IF(COUNTA('1_Data Entry'!C36:N36)=0,"",'1_Data Entry'!A36)) -> 31 | B36: =IF('1_Data Entry'!$E36="","",IF(A36="","",IF(S36<>"OK","Check row",IF(M36="","Open lot",IF(R36=0,"Closed lot","Partially sold"))))) -> Open lot | C36: =IF(A36="","",'1_Data Entry'!C36) -> US | D36: =IF(A36="","",'1_Data Entry'!D36) -> ETF | E36: =IF(A36="","",'1_Data Entry'!E36) -> schb | F36: =IF(E36="","",UPPER(TRIM(E36))) -> SCHB | G36: =IF(F36="","",IFERROR(VLOOKUP(F36,'6_Reference Lists'!$A$4:$D$64,4,FALSE()),'1_Data Entry'!F36)) -> Schwab U.S. Broad Market ETF | H36: =IF('1_Data Entry'!$E36="","",IF(OR(F36="",I36="",J36="",K36=""),"",F36&"-"&TEXT(I36,"yyyymmdd")&"-"&SUBSTITUTE(TEXT(ROUND(J36,3),"0.###"),".","D")&"-"&SUBSTITUTE(TEXT(ROUND(K36,3),"0.###"),".","D"))) -> SCHB-20260331-60D-22D | I36: =IF('1_Data Entry'!$E36="","",IF(A36="","",'1_Data Entry'!G36)) -> 46112 | J36: =IF('1_Data Entry'!$E36="","",IF(A36="","",'1_Data Entry'!H36)) -> 60 | K36: =IF('1_Data Entry'!$E36="","",IF(A36="","",'1_Data Entry'!I36)) -> 22 | L36: =IF('1_Data Entry'!$E36="","",IF(OR(J36="",K36=""),"",J36*K36)) -> 1320 | M36: =IF(A36="","",IF(OR('1_Data Entry'!L36="",'1_Data Entry'!L36<=0),"",'1_Data Entry'!J36)) | N36: =IF('1_Data Entry'!$E36="","",IF(OR(J36="",R36=""),"",MAX(J36-R36,0))) -> 0 | O36: =IF('1_Data Entry'!$E36="","",IF(A36="","",'1_Data Entry'!L36)) -> 0 | P36: =IF(OR(M36="",O36="",O36<=0,N36="",N36<=0),"",O36*N36) | Q36: =IF('1_Data Entry'!$E36="","",IF(OR(M36="",P36="",L36=""),"",P36-L36)) | R36: =IF(A36="","",IF('1_Data Entry'!M36<>"",'1_Data Entry'!M36,IF('1_Data Entry'!J36="",J36,""))) -> 60 | S36: =IF('1_Data Entry'!$E36="","",IF(A36="","",IF(OR(F36="",I36="",J36="",K36=""),"Check row",IF(AND(M36<>"",M36<I36),"Sell before buy",IF(AND(R36<>"",J36<R36),"Shares remaining exceeds buy",IF(AND(M36<>"",OR(O36="",O36<=0),N36>0),"Missing sale price","OK")))))) -> OK | T36: =IF('1_Data Entry'!$E36="","",IF(A36="","",IF(AND(Q36<0,M36<>""),"Yes","No"))) -> No | U36: =IF('1_Data Entry'!$E36="","",IF(OR(A36="",T36<>"Yes",M36=""),"No",IF(COUNTIFS($F$6:$F$505,F36,$I$6:$I$505,">="&M36-30,$I$6:$I$505,"<="&M36+30,$A$6:$A$505,"<>"&A36)>0,"Yes","No"))) -> No | V36: =IF('1_Data Entry'!$E36="","",IF(OR(A36="",U36<>"Yes",M36=""),"",M36+30)) | W36: =IF('1_Data Entry'!$E36="","",IF(A36="","",IF(S36="OK","Ready","Review row"))) -> Ready | X36: =IF(OR(I36="",M36=""),"",M36-I36) | Y36: =IF(X36="","",IF(X36<=365,"Short-Term","Long-Term")) | Z36: =IF('1_Data Entry'!$E36="","",SUM(SUMIFS('4_Wash Match Table'!R$7:R$500,'4_Wash Match Table'!L$7:L$500,H36),(SUMIFS('4_Wash Match Table'!AA$7:AA$500,'4_Wash Match Table'!U$7:U$500,H36)),(SUMIFS('4_Wash Match Table'!AJ$7:AJ$500,'4_Wash Match Table'!AD$7:AD$500,H36)),(SUMIFS('4_Wash Match Table'!AS$7:AS$500,'4_Wash Match Table'!AM$7:AM$500,H36)))) -> 80.982288 | AA36: =IF('1_Data Entry'!$E36="","",IF(OR(L36="",Z36=""),"",L36+Z36)) -> 1400.9823 | AB36: =IFERROR(IF(OR(J36="",AA36=""),"",AA36/J36),"") -> 23.349705 | AC36: =IF(AND($M36<>"",$Q36<0),COUNTIFS($M$6:M36,"<>",$Q$6:Q36,"<0"),"") | AD36: =IF(A36="","",ROW()) -> 36
A37: =IF('1_Data Entry'!$E37="","",IF(COUNTA('1_Data Entry'!C37:N37)=0,"",'1_Data Entry'!A37)) -> 32 | B37: =IF('1_Data Entry'!$E37="","",IF(A37="","",IF(S37<>"OK","Check row",IF(M37="","Open lot",IF(R37=0,"Closed lot","Partially sold"))))) -> Open lot | C37: =IF(A37="","",'1_Data Entry'!C37) -> US | D37: =IF(A37="","",'1_Data Entry'!D37) -> ETF | E37: =IF(A37="","",'1_Data Entry'!E37) -> schb | F37: =IF(E37="","",UPPER(TRIM(E37))) -> SCHB | G37: =IF(F37="","",IFERROR(VLOOKUP(F37,'6_Reference Lists'!$A$4:$D$64,4,FALSE()),'1_Data Entry'!F37)) -> Schwab U.S. Broad Market ETF | H37: =IF('1_Data Entry'!$E37="","",IF(OR(F37="",I37="",J37="",K37=""),"",F37&"-"&TEXT(I37,"yyyymmdd")&"-"&SUBSTITUTE(TEXT(ROUND(J37,3),"0.###"),".","D")&"-"&SUBSTITUTE(TEXT(ROUND(K37,3),"0.###"),".","D"))) -> SCHB-20260421-70D-24D | I37: =IF('1_Data Entry'!$E37="","",IF(A37="","",'1_Data Entry'!G37)) -> 46133 | J37: =IF('1_Data Entry'!$E37="","",IF(A37="","",'1_Data Entry'!H37)) -> 70 | K37: =IF('1_Data Entry'!$E37="","",IF(A37="","",'1_Data Entry'!I37)) -> 24 | L37: =IF('1_Data Entry'!$E37="","",IF(OR(J37="",K37=""),"",J37*K37)) -> 1680 | M37: =IF(A37="","",IF(OR('1_Data Entry'!L37="",'1_Data Entry'!L37<=0),"",'1_Data Entry'!J37)) | N37: =IF('1_Data Entry'!$E37="","",IF(OR(J37="",R37=""),"",MAX(J37-R37,0))) -> 0 | O37: =IF('1_Data Entry'!$E37="","",IF(A37="","",'1_Data Entry'!L37)) -> 0 | P37: =IF(OR(M37="",O37="",O37<=0,N37="",N37<=0),"",O37*N37) | Q37: =IF('1_Data Entry'!$E37="","",IF(OR(M37="",P37="",L37=""),"",P37-L37)) | R37: =IF(A37="","",IF('1_Data Entry'!M37<>"",'1_Data Entry'!M37,IF('1_Data Entry'!J37="",J37,""))) -> 70 | S37: =IF('1_Data Entry'!$E37="","",IF(A37="","",IF(OR(F37="",I37="",J37="",K37=""),"Check row",IF(AND(M37<>"",M37<I37),"Sell before buy",IF(AND(R37<>"",J37<R37),"Shares remaining exceeds buy",IF(AND(M37<>"",OR(O37="",O37<=0),N37>0),"Missing sale price","OK")))))) -> OK | T37: =IF('1_Data Entry'!$E37="","",IF(A37="","",IF(AND(Q37<0,M37<>""),"Yes","No"))) -> No | U37: =IF('1_Data Entry'!$E37="","",IF(OR(A37="",T37<>"Yes",M37=""),"No",IF(COUNTIFS($F$6:$F$505,F37,$I$6:$I$505,">="&M37-30,$I$6:$I$505,"<="&M37+30,$A$6:$A$505,"<>"&A37)>0,"Yes","No"))) -> No | V37: =IF('1_Data Entry'!$E37="","",IF(OR(A37="",U37<>"Yes",M37=""),"",M37+30)) | W37: =IF('1_Data Entry'!$E37="","",IF(A37="","",IF(S37="OK","Ready","Review row"))) -> Ready | X37: =IF(OR(I37="",M37=""),"",M37-I37) | Y37: =IF(X37="","",IF(X37<=365,"Short-Term","Long-Term")) | Z37: =IF('1_Data Entry'!$E37="","",SUM(SUMIFS('4_Wash Match Table'!R$7:R$500,'4_Wash Match Table'!L$7:L$500,H37),(SUMIFS('4_Wash Match Table'!AA$7:AA$500,'4_Wash Match Table'!U$7:U$500,H37)),(SUMIFS('4_Wash Match Table'!AJ$7:AJ$500,'4_Wash Match Table'!AD$7:AD$500,H37)),(SUMIFS('4_Wash Match Table'!AS$7:AS$500,'4_Wash Match Table'!AM$7:AM$500,H37)))) -> 94.479336 | AA37: =IF('1_Data Entry'!$E37="","",IF(OR(L37="",Z37=""),"",L37+Z37)) -> 1774.4793 | AB37: =IFERROR(IF(OR(J37="",AA37=""),"",AA37/J37),"") -> 25.349705 | AC37: =IF(AND($M37<>"",$Q37<0),COUNTIFS($M$6:M37,"<>",$Q$6:Q37,"<0"),"") | AD37: =IF(A37="","",ROW()) -> 37
A38: =IF('1_Data Entry'!$E38="","",IF(COUNTA('1_Data Entry'!C38:N38)=0,"",'1_Data Entry'!A38)) | B38: =IF('1_Data Entry'!$E38="","",IF(A38="","",IF(S38<>"OK","Check row",IF(M38="","Open lot",IF(R38=0,"Closed lot","Partially sold"))))) | C38: =IF(A38="","",'1_Data Entry'!C38) | D38: =IF(A38="","",'1_Data Entry'!D38) | E38: =IF(A38="","",'1_Data Entry'!E38) | F38: =IF(E38="","",UPPER(TRIM(E38))) | G38: =IF(F38="","",IFERROR(VLOOKUP(F38,'6_Reference Lists'!$A$4:$D$64,4,FALSE()),'1_Data Entry'!F38)) | H38: =IF('1_Data Entry'!$E38="","",IF(OR(F38="",I38="",J38="",K38=""),"",F38&"-"&TEXT(I38,"yyyymmdd")&"-"&SUBSTITUTE(TEXT(ROUND(J38,3),"0.###"),".","D")&"-"&SUBSTITUTE(TEXT(ROUND(K38,3),"0.###"),".","D"))) | I38: =IF('1_Data Entry'!$E38="","",IF(A38="","",'1_Data Entry'!G38)) | J38: =IF('1_Data Entry'!$E38="","",IF(A38="","",'1_Data Entry'!H38)) | K38: =IF('1_Data Entry'!$E38="","",IF(A38="","",'1_Data Entry'!I38)) | L38: =IF('1_Data Entry'!$E38="","",IF(OR(J38="",K38=""),"",J38*K38)) | M38: =IF(A38="","",IF(OR('1_Data Entry'!L38="",'1_Data Entry'!L38<=0),"",'1_Data Entry'!J38)) | N38: =IF('1_Data Entry'!$E38="","",IF(OR(J38="",R38=""),"",MAX(J38-R38,0))) | O38: =IF('1_Data Entry'!$E38="","",IF(A38="","",'1_Data Entry'!L38)) | P38: =IF(OR(M38="",O38="",O38<=0,N38="",N38<=0),"",O38*N38) | Q38: =IF('1_Data Entry'!$E38="","",IF(OR(M38="",P38="",L38=""),"",P38-L38)) | R38: =IF(A38="","",IF('1_Data Entry'!M38<>"",'1_Data Entry'!M38,IF('1_Data Entry'!J38="",J38,""))) | S38: =IF('1_Data Entry'!$E38="","",IF(A38="","",IF(OR(F38="",I38="",J38="",K38=""),"Check row",IF(AND(M38<>"",M38<I38),"Sell before buy",IF(AND(R38<>"",J38<R38),"Shares remaining exceeds buy",IF(AND(M38<>"",OR(O38="",O38<=0),N38>0),"Missing sale price","OK")))))) | T38: =IF('1_Data Entry'!$E38="","",IF(A38="","",IF(AND(Q38<0,M38<>""),"Yes","No"))) | U38: =IF('1_Data Entry'!$E38="","",IF(OR(A38="",T38<>"Yes",M38=""),"No",IF(COUNTIFS($F$6:$F$505,F38,$I$6:$I$505,">="&M38-30,$I$6:$I$505,"<="&M38+30,$A$6:$A$505,"<>"&A38)>0,"Yes","No"))) | V38: =IF('1_Data Entry'!$E38="","",IF(OR(A38="",U38<>"Yes",M38=""),"",M38+30)) | W38: =IF('1_Data Entry'!$E38="","",IF(A38="","",IF(S38="OK","Ready","Review row"))) | X38: =IF(OR(I38="",M38=""),"",M38-I38) | Y38: =IF(X38="","",IF(X38<=365,"Short-Term","Long-Term")) | Z38: =IF('1_Data Entry'!$E38="","",SUM(SUMIFS('4_Wash Match Table'!R$7:R$500,'4_Wash Match Table'!L$7:L$500,H38),(SUMIFS('4_Wash Match Table'!AA$7:AA$500,'4_Wash Match Table'!U$7:U$500,H38)),(SUMIFS('4_Wash Match Table'!AJ$7:AJ$500,'4_Wash Match Table'!AD$7:AD$500,H38)),(SUMIFS('4_Wash Match Table'!AS$7:AS$500,'4_Wash Match Table'!AM$7:AM$500,H38)))) | AA38: =IF('1_Data Entry'!$E38="","",IF(OR(L38="",Z38=""),"",L38+Z38)) | AB38: =IFERROR(IF(OR(J38="",AA38=""),"",AA38/J38),"") | AC38: =IF(AND($M38<>"",$Q38<0),COUNTIFS($M$6:M38,"<>",$Q$6:Q38,"<0"),"") | AD38: =IF(A38="","",ROW())
A39: =IF('1_Data Entry'!$E39="","",IF(COUNTA('1_Data Entry'!C39:N39)=0,"",'1_Data Entry'!A39)) | B39: =IF('1_Data Entry'!$E39="","",IF(A39="","",IF(S39<>"OK","Check row",IF(M39="","Open lot",IF(R39=0,"Closed lot","Partially sold"))))) | C39: =IF(A39="","",'1_Data Entry'!C39) | D39: =IF(A39="","",'1_Data Entry'!D39) | E39: =IF(A39="","",'1_Data Entry'!E39) | F39: =IF(E39="","",UPPER(TRIM(E39))) | G39: =IF(F39="","",IFERROR(VLOOKUP(F39,'6_Reference Lists'!$A$4:$D$64,4,FALSE()),'1_Data Entry'!F39)) | H39: =IF('1_Data Entry'!$E39="","",IF(OR(F39="",I39="",J39="",K39=""),"",F39&"-"&TEXT(I39,"yyyymmdd")&"-"&SUBSTITUTE(TEXT(ROUND(J39,3),"0.###"),".","D")&"-"&SUBSTITUTE(TEXT(ROUND(K39,3),"0.###"),".","D"))) | I39: =IF('1_Data Entry'!$E39="","",IF(A39="","",'1_Data Entry'!G39)) | J39: =IF('1_Data Entry'!$E39="","",IF(A39="","",'1_Data Entry'!H39)) | K39: =IF('1_Data Entry'!$E39="","",IF(A39="","",'1_Data Entry'!I39)) | L39: =IF('1_Data Entry'!$E39="","",IF(OR(J39="",K39=""),"",J39*K39)) | M39: =IF(A39="","",IF(OR('1_Data Entry'!L39="",'1_Data Entry'!L39<=0),"",'1_Data Entry'!J39)) | N39: =IF('1_Data Entry'!$E39="","",IF(OR(J39="",R39=""),"",MAX(J39-R39,0))) | O39: =IF('1_Data Entry'!$E39="","",IF(A39="","",'1_Data Entry'!L39)) | P39: =IF(OR(M39="",O39="",O39<=0,N39="",N39<=0),"",O39*N39) | Q39: =IF('1_Data Entry'!$E39="","",IF(OR(M39="",P39="",L39=""),"",P39-L39)) | R39: =IF(A39="","",IF('1_Data Entry'!M39<>"",'1_Data Entry'!M39,IF('1_Data Entry'!J39="",J39,""))) | S39: =IF('1_Data Entry'!$E39="","",IF(A39="","",IF(OR(F39="",I39="",J39="",K39=""),"Check row",IF(AND(M39<>"",M39<I39),"Sell before buy",IF(AND(R39<>"",J39<R39),"Shares remaining exceeds buy",IF(AND(M39<>"",OR(O39="",O39<=0),N39>0),"Missing sale price","OK")))))) | T39: =IF('1_Data Entry'!$E39="","",IF(A39="","",IF(AND(Q39<0,M39<>""),"Yes","No"))) | U39: =IF('1_Data Entry'!$E39="","",IF(OR(A39="",T39<>"Yes",M39=""),"No",IF(COUNTIFS($F$6:$F$505,F39,$I$6:$I$505,">="&M39-30,$I$6:$I$505,"<="&M39+30,$A$6:$A$505,"<>"&A39)>0,"Yes","No"))) | V39: =IF('1_Data Entry'!$E39="","",IF(OR(A39="",U39<>"Yes",M39=""),"",M39+30)) | W39: =IF('1_Data Entry'!$E39="","",IF(A39="","",IF(S39="OK","Ready","Review row"))) | X39: =IF(OR(I39="",M39=""),"",M39-I39) | Y39: =IF(X39="","",IF(X39<=365,"Short-Term","Long-Term")) | Z39: =IF('1_Data Entry'!$E39="","",SUM(SUMIFS('4_Wash Match Table'!R$7:R$500,'4_Wash Match Table'!L$7:L$500,H39),(SUMIFS('4_Wash Match Table'!AA$7:AA$500,'4_Wash Match Table'!U$7:U$500,H39)),(SUMIFS('4_Wash Match Table'!AJ$7:AJ$500,'4_Wash Match Table'!AD$7:AD$500,H39)),(SUMIFS('4_Wash Match Table'!AS$7:AS$500,'4_Wash Match Table'!AM$7:AM$500,H39)))) | AA39: =IF('1_Data Entry'!$E39="","",IF(OR(L39="",Z39=""),"",L39+Z39)) | AB39: =IFERROR(IF(OR(J39="",AA39=""),"",AA39/J39),"") | AC39: =IF(AND($M39<>"",$Q39<0),COUNTIFS($M$6:M39,"<>",$Q$6:Q39,"<0"),"") | AD39: =IF(A39="","",ROW())
A40: =IF('1_Data Entry'!$E40="","",IF(COUNTA('1_Data Entry'!C40:N40)=0,"",'1_Data Entry'!A40)) | B40: =IF('1_Data Entry'!$E40="","",IF(A40="","",IF(S40<>"OK","Check row",IF(M40="","Open lot",IF(R40=0,"Closed lot","Partially sold"))))) | C40: =IF(A40="","",'1_Data Entry'!C40) | D40: =IF(A40="","",'1_Data Entry'!D40) | E40: =IF(A40="","",'1_Data Entry'!E40) | F40: =IF(E40="","",UPPER(TRIM(E40))) | G40: =IF(F40="","",IFERROR(VLOOKUP(F40,'6_Reference Lists'!$A$4:$D$64,4,FALSE()),'1_Data Entry'!F40)) | H40: =IF('1_Data Entry'!$E40="","",IF(OR(F40="",I40="",J40="",K40=""),"",F40&"-"&TEXT(I40,"yyyymmdd")&"-"&SUBSTITUTE(TEXT(ROUND(J40,3),"0.###"),".","D")&"-"&SUBSTITUTE(TEXT(ROUND(K40,3),"0.###"),".","D"))) | I40: =IF('1_Data Entry'!$E40="","",IF(A40="","",'1_Data Entry'!G40)) | J40: =IF('1_Data Entry'!$E40="","",IF(A40="","",'1_Data Entry'!H40)) | K40: =IF('1_Data Entry'!$E40="","",IF(A40="","",'1_Data Entry'!I40)) | L40: =IF('1_Data Entry'!$E40="","",IF(OR(J40="",K40=""),"",J40*K40)) | M40: =IF(A40="","",IF(OR('1_Data Entry'!L40="",'1_Data Entry'!L40<=0),"",'1_Data Entry'!J40)) | N40: =IF('1_Data Entry'!$E40="","",IF(OR(J40="",R40=""),"",MAX(J40-R40,0))) | O40: =IF('1_Data Entry'!$E40="","",IF(A40="","",'1_Data Entry'!L40)) | P40: =IF(OR(M40="",O40="",O40<=0,N40="",N40<=0),"",O40*N40) | Q40: =IF('1_Data Entry'!$E40="","",IF(OR(M40="",P40="",L40=""),"",P40-L40)) | R40: =IF(A40="","",IF('1_Data Entry'!M40<>"",'1_Data Entry'!M40,IF('1_Data Entry'!J40="",J40,""))) | S40: =IF('1_Data Entry'!$E40="","",IF(A40="","",IF(OR(F40="",I40="",J40="",K40=""),"Check row",IF(AND(M40<>"",M40<I40),"Sell before buy",IF(AND(R40<>"",J40<R40),"Shares remaining exceeds buy",IF(AND(M40<>"",OR(O40="",O40<=0),N40>0),"Missing sale price","OK")))))) | T40: =IF('1_Data Entry'!$E40="","",IF(A40="","",IF(AND(Q40<0,M40<>""),"Yes","No"))) | U40: =IF('1_Data Entry'!$E40="","",IF(OR(A40="",T40<>"Yes",M40=""),"No",IF(COUNTIFS($F$6:$F$505,F40,$I$6:$I$505,">="&M40-30,$I$6:$I$505,"<="&M40+30,$A$6:$A$505,"<>"&A40)>0,"Yes","No"))) | V40: =IF('1_Data Entry'!$E40="","",IF(OR(A40="",U40<>"Yes",M40=""),"",M40+30)) | W40: =IF('1_Data Entry'!$E40="","",IF(A40="","",IF(S40="OK","Ready","Review row"))) | X40: =IF(OR(I40="",M40=""),"",M40-I40) | Y40: =IF(X40="","",IF(X40<=365,"Short-Term","Long-Term")) | Z40: =IF('1_Data Entry'!$E40="","",SUM(SUMIFS('4_Wash Match Table'!R$7:R$500,'4_Wash Match Table'!L$7:L$500,H40),(SUMIFS('4_Wash Match Table'!AA$7:AA$500,'4_Wash Match Table'!U$7:U$500,H40)),(SUMIFS('4_Wash Match Table'!AJ$7:AJ$500,'4_Wash Match Table'!AD$7:AD$500,H40)),(SUMIFS('4_Wash Match Table'!AS$7:AS$500,'4_Wash Match Table'!AM$7:AM$500,H40)))) | AA40: =IF('1_Data Entry'!$E40="","",IF(OR(L40="",Z40=""),"",L40+Z40)) | AB40: =IFERROR(IF(OR(J40="",AA40=""),"",AA40/J40),"") | AC40: =IF(AND($M40<>"",$Q40<0),COUNTIFS($M$6:M40,"<>",$Q$6:Q40,"<0"),"") | AD40: =IF(A40="","",ROW())
A41: =IF('1_Data Entry'!$E41="","",IF(COUNTA('1_Data Entry'!C41:N41)=0,"",'1_Data Entry'!A41)) | B41: =IF('1_Data Entry'!$E41="","",IF(A41="","",IF(S41<>"OK","Check row",IF(M41="","Open lot",IF(R41=0,"Closed lot","Partially sold"))))) | C41: =IF(A41="","",'1_Data Entry'!C41) | D41: =IF(A41="","",'1_Data Entry'!D41) | E41: =IF(A41="","",'1_Data Entry'!E41) | F41: =IF(E41="","",UPPER(TRIM(E41))) | G41: =IF(F41="","",IFERROR(VLOOKUP(F41,'6_Reference Lists'!$A$4:$D$64,4,FALSE()),'1_Data Entry'!F41)) | H41: =IF('1_Data Entry'!$E41="","",IF(OR(F41="",I41="",J41="",K41=""),"",F41&"-"&TEXT(I41,"yyyymmdd")&"-"&SUBSTITUTE(TEXT(ROUND(J41,3),"0.###"),".","D")&"-"&SUBSTITUTE(TEXT(ROUND(K41,3),"0.###"),".","D"))) | I41: =IF('1_Data Entry'!$E41="","",IF(A41="","",'1_Data Entry'!G41)) | J41: =IF('1_Data Entry'!$E41="","",IF(A41="","",'1_Data Entry'!H41)) | K41: =IF('1_Data Entry'!$E41="","",IF(A41="","",'1_Data Entry'!I41)) | L41: =IF('1_Data Entry'!$E41="","",IF(OR(J41="",K41=""),"",J41*K41)) | M41: =IF(A41="","",IF(OR('1_Data Entry'!L41="",'1_Data Entry'!L41<=0),"",'1_Data Entry'!J41)) | N41: =IF('1_Data Entry'!$E41="","",IF(OR(J41="",R41=""),"",MAX(J41-R41,0))) | O41: =IF('1_Data Entry'!$E41="","",IF(A41="","",'1_Data Entry'!L41)) | P41: =IF(OR(M41="",O41="",O41<=0,N41="",N41<=0),"",O41*N41) | Q41: =IF('1_Data Entry'!$E41="","",IF(OR(M41="",P41="",L41=""),"",P41-L41)) | R41: =IF(A41="","",IF('1_Data Entry'!M41<>"",'1_Data Entry'!M41,IF('1_Data Entry'!J41="",J41,""))) | S41: =IF('1_Data Entry'!$E41="","",IF(A41="","",IF(OR(F41="",I41="",J41="",K41=""),"Check row",IF(AND(M41<>"",M41<I41),"Sell before buy",IF(AND(R41<>"",J41<R41),"Shares remaining exceeds buy",IF(AND(M41<>"",OR(O41="",O41<=0),N41>0),"Missing sale price","OK")))))) | T41: =IF('1_Data Entry'!$E41="","",IF(A41="","",IF(AND(Q41<0,M41<>""),"Yes","No"))) | U41: =IF('1_Data Entry'!$E41="","",IF(OR(A41="",T41<>"Yes",M41=""),"No",IF(COUNTIFS($F$6:$F$505,F41,$I$6:$I$505,">="&M41-30,$I$6:$I$505,"<="&M41+30,$A$6:$A$505,"<>"&A41)>0,"Yes","No"))) | V41: =IF('1_Data Entry'!$E41="","",IF(OR(A41="",U41<>"Yes",M41=""),"",M41+30)) | W41: =IF('1_Data Entry'!$E41="","",IF(A41="","",IF(S41="OK","Ready","Review row"))) | X41: =IF(OR(I41="",M41=""),"",M41-I41) | Y41: =IF(X41="","",IF(X41<=365,"Short-Term","Long-Term")) | Z41: =IF('1_Data Entry'!$E41="","",SUM(SUMIFS('4_Wash Match Table'!R$7:R$500,'4_Wash Match Table'!L$7:L$500,H41),(SUMIFS('4_Wash Match Table'!AA$7:AA$500,'4_Wash Match Table'!U$7:U$500,H41)),(SUMIFS('4_Wash Match Table'!AJ$7:AJ$500,'4_Wash Match Table'!AD$7:AD$500,H41)),(SUMIFS('4_Wash Match Table'!AS$7:AS$500,'4_Wash Match Table'!AM$7:AM$500,H41)))) | AA41: =IF('1_Data Entry'!$E41="","",IF(OR(L41="",Z41=""),"",L41+Z41)) | AB41: =IFERROR(IF(OR(J41="",AA41=""),"",AA41/J41),"") | AC41: =IF(AND($M41<>"",$Q41<0),COUNTIFS($M$6:M41,"<>",$Q$6:Q41,"<0"),"") | AD41: =IF(A41="","",ROW())
A42: =IF('1_Data Entry'!$E42="","",IF(COUNTA('1_Data Entry'!C42:N42)=0,"",'1_Data Entry'!A42)) | B42: =IF('1_Data Entry'!$E42="","",IF(A42="","",IF(S42<>"OK","Check row",IF(M42="","Open lot",IF(R42=0,"Closed lot","Partially sold"))))) | C42: =IF(A42="","",'1_Data Entry'!C42) | D42: =IF(A42="","",'1_Data Entry'!D42) | E42: =IF(A42="","",'1_Data Entry'!E42) | F42: =IF(E42="","",UPPER(TRIM(E42))) | G42: =IF(F42="","",IFERROR(VLOOKUP(F42,'6_Reference Lists'!$A$4:$D$64,4,FALSE()),'1_Data Entry'!F42)) | H42: =IF('1_Data Entry'!$E42="","",IF(OR(F42="",I42="",J42="",K42=""),"",F42&"-"&TEXT(I42,"yyyymmdd")&"-"&SUBSTITUTE(TEXT(ROUND(J42,3),"0.###"),".","D")&"-"&SUBSTITUTE(TEXT(ROUND(K42,3),"0.###"),".","D"))) | I42: =IF('1_Data Entry'!$E42="","",IF(A42="","",'1_Data Entry'!G42)) | J42: =IF('1_Data Entry'!$E42="","",IF(A42="","",'1_Data Entry'!H42)) | K42: =IF('1_Data Entry'!$E42="","",IF(A42="","",'1_Data Entry'!I42)) | L42: =IF('1_Data Entry'!$E42="","",IF(OR(J42="",K42=""),"",J42*K42)) | M42: =IF(A42="","",IF(OR('1_Data Entry'!L42="",'1_Data Entry'!L42<=0),"",'1_Data Entry'!J42)) | N42: =IF('1_Data Entry'!$E42="","",IF(OR(J42="",R42=""),"",MAX(J42-R42,0))) | O42: =IF('1_Data Entry'!$E42="","",IF(A42="","",'1_Data Entry'!L42)) | P42: =IF(OR(M42="",O42="",O42<=0,N42="",N42<=0),"",O42*N42) | Q42: =IF('1_Data Entry'!$E42="","",IF(OR(M42="",P42="",L42=""),"",P42-L42)) | R42: =IF(A42="","",IF('1_Data Entry'!M42<>"",'1_Data Entry'!M42,IF('1_Data Entry'!J42="",J42,""))) | S42: =IF('1_Data Entry'!$E42="","",IF(A42="","",IF(OR(F42="",I42="",J42="",K42=""),"Check row",IF(AND(M42<>"",M42<I42),"Sell before buy",IF(AND(R42<>"",J42<R42),"Shares remaining exceeds buy",IF(AND(M42<>"",OR(O42="",O42<=0),N42>0),"Missing sale price","OK")))))) | T42: =IF('1_Data Entry'!$E42="","",IF(A42="","",IF(AND(Q42<0,M42<>""),"Yes","No"))) | U42: =IF('1_Data Entry'!$E42="","",IF(OR(A42="",T42<>"Yes",M42=""),"No",IF(COUNTIFS($F$6:$F$505,F42,$I$6:$I$505,">="&M42-30,$I$6:$I$505,"<="&M42+30,$A$6:$A$505,"<>"&A42)>0,"Yes","No"))) | V42: =IF('1_Data Entry'!$E42="","",IF(OR(A42="",U42<>"Yes",M42=""),"",M42+30)) | W42: =IF('1_Data Entry'!$E42="","",IF(A42="","",IF(S42="OK","Ready","Review row"))) | X42: =IF(OR(I42="",M42=""),"",M42-I42) | Y42: =IF(X42="","",IF(X42<=365,"Short-Term","Long-Term")) | Z42: =IF('1_Data Entry'!$E42="","",SUM(SUMIFS('4_Wash Match Table'!R$7:R$500,'4_Wash Match Table'!L$7:L$500,H42),(SUMIFS('4_Wash Match Table'!AA$7:AA$500,'4_Wash Match Table'!U$7:U$500,H42)),(SUMIFS('4_Wash Match Table'!AJ$7:AJ$500,'4_Wash Match Table'!AD$7:AD$500,H42)),(SUMIFS('4_Wash Match Table'!AS$7:AS$500,'4_Wash Match Table'!AM$7:AM$500,H42)))) | AA42: =IF('1_Data Entry'!$E42="","",IF(OR(L42="",Z42=""),"",L42+Z42)) | AB42: =IFERROR(IF(OR(J42="",AA42=""),"",AA42/J42),"") | AC42: =IF(AND($M42<>"",$Q42<0),COUNTIFS($M$6:M42,"<>",$Q$6:Q42,"<0"),"") | AD42: =IF(A42="","",ROW())
A43: =IF('1_Data Entry'!$E43="","",IF(COUNTA('1_Data Entry'!C43:N43)=0,"",'1_Data Entry'!A43)) | B43: =IF('1_Data Entry'!$E43="","",IF(A43="","",IF(S43<>"OK","Check row",IF(M43="","Open lot",IF(R43=0,"Closed lot","Partially sold"))))) | C43: =IF(A43="","",'1_Data Entry'!C43) | D43: =IF(A43="","",'1_Data Entry'!D43) | E43: =IF(A43="","",'1_Data Entry'!E43) | F43: =IF(E43="","",UPPER(TRIM(E43))) | G43: =IF(F43="","",IFERROR(VLOOKUP(F43,'6_Reference Lists'!$A$4:$D$64,4,FALSE()),'1_Data Entry'!F43)) | H43: =IF('1_Data Entry'!$E43="","",IF(OR(F43="",I43="",J43="",K43=""),"",F43&"-"&TEXT(I43,"yyyymmdd")&"-"&SUBSTITUTE(TEXT(ROUND(J43,3),"0.###"),".","D")&"-"&SUBSTITUTE(TEXT(ROUND(K43,3),"0.###"),".","D"))) | I43: =IF('1_Data Entry'!$E43="","",IF(A43="","",'1_Data Entry'!G43)) | J43: =IF('1_Data Entry'!$E43="","",IF(A43="","",'1_Data Entry'!H43)) | K43: =IF('1_Data Entry'!$E43="","",IF(A43="","",'1_Data Entry'!I43)) | L43: =IF('1_Data Entry'!$E43="","",IF(OR(J43="",K43=""),"",J43*K43)) | M43: =IF(A43="","",IF(OR('1_Data Entry'!L43="",'1_Data Entry'!L43<=0),"",'1_Data Entry'!J43)) | N43: =IF('1_Data Entry'!$E43="","",IF(OR(J43="",R43=""),"",MAX(J43-R43,0))) | O43: =IF('1_Data Entry'!$E43="","",IF(A43="","",'1_Data Entry'!L43)) | P43: =IF(OR(M43="",O43="",O43<=0,N43="",N43<=0),"",O43*N43) | Q43: =IF('1_Data Entry'!$E43="","",IF(OR(M43="",P43="",L43=""),"",P43-L43)) | R43: =IF(A43="","",IF('1_Data Entry'!M43<>"",'1_Data Entry'!M43,IF('1_Data Entry'!J43="",J43,""))) | S43: =IF('1_Data Entry'!$E43="","",IF(A43="","",IF(OR(F43="",I43="",J43="",K43=""),"Check row",IF(AND(M43<>"",M43<I43),"Sell before buy",IF(AND(R43<>"",J43<R43),"Shares remaining exceeds buy",IF(AND(M43<>"",OR(O43="",O43<=0),N43>0),"Missing sale price","OK")))))) | T43: =IF('1_Data Entry'!$E43="","",IF(A43="","",IF(AND(Q43<0,M43<>""),"Yes","No"))) | U43: =IF('1_Data Entry'!$E43="","",IF(OR(A43="",T43<>"Yes",M43=""),"No",IF(COUNTIFS($F$6:$F$505,F43,$I$6:$I$505,">="&M43-30,$I$6:$I$505,"<="&M43+30,$A$6:$A$505,"<>"&A43)>0,"Yes","No"))) | V43: =IF('1_Data Entry'!$E43="","",IF(OR(A43="",U43<>"Yes",M43=""),"",M43+30)) | W43: =IF('1_Data Entry'!$E43="","",IF(A43="","",IF(S43="OK","Ready","Review row"))) | X43: =IF(OR(I43="",M43=""),"",M43-I43) | Y43: =IF(X43="","",IF(X43<=365,"Short-Term","Long-Term")) | Z43: =IF('1_Data Entry'!$E43="","",SUM(SUMIFS('4_Wash Match Table'!R$7:R$500,'4_Wash Match Table'!L$7:L$500,H43),(SUMIFS('4_Wash Match Table'!AA$7:AA$500,'4_Wash Match Table'!U$7:U$500,H43)),(SUMIFS('4_Wash Match Table'!AJ$7:AJ$500,'4_Wash Match Table'!AD$7:AD$500,H43)),(SUMIFS('4_Wash Match Table'!AS$7:AS$500,'4_Wash Match Table'!AM$7:AM$500,H43)))) | AA43: =IF('1_Data Entry'!$E43="","",IF(OR(L43="",Z43=""),"",L43+Z43)) | AB43: =IFERROR(IF(OR(J43="",AA43=""),"",AA43/J43),"") | AC43: =IF(AND($M43<>"",$Q43<0),COUNTIFS($M$6:M43,"<>",$Q$6:Q43,"<0"),"") | AD43: =IF(A43="","",ROW())
A44: =IF('1_Data Entry'!$E44="","",IF(COUNTA('1_Data Entry'!C44:N44)=0,"",'1_Data Entry'!A44)) | B44: =IF('1_Data Entry'!$E44="","",IF(A44="","",IF(S44<>"OK","Check row",IF(M44="","Open lot",IF(R44=0,"Closed lot","Partially sold"))))) | C44: =IF(A44="","",'1_Data Entry'!C44) | D44: =IF(A44="","",'1_Data Entry'!D44) | E44: =IF(A44="","",'1_Data Entry'!E44) | F44: =IF(E44="","",UPPER(TRIM(E44))) | G44: =IF(F44="","",IFERROR(VLOOKUP(F44,'6_Reference Lists'!$A$4:$D$64,4,FALSE()),'1_Data Entry'!F44)) | H44: =IF('1_Data Entry'!$E44="","",IF(OR(F44="",I44="",J44="",K44=""),"",F44&"-"&TEXT(I44,"yyyymmdd")&"-"&SUBSTITUTE(TEXT(ROUND(J44,3),"0.###"),".","D")&"-"&SUBSTITUTE(TEXT(ROUND(K44,3),"0.###"),".","D"))) | I44: =IF('1_Data Entry'!$E44="","",IF(A44="","",'1_Data Entry'!G44)) | J44: =IF('1_Data Entry'!$E44="","",IF(A44="","",'1_Data Entry'!H44)) | K44: =IF('1_Data Entry'!$E44="","",IF(A44="","",'1_Data Entry'!I44)) | L44: =IF('1_Data Entry'!$E44="","",IF(OR(J44="",K44=""),"",J44*K44)) | M44: =IF(A44="","",IF(OR('1_Data Entry'!L44="",'1_Data Entry'!L44<=0),"",'1_Data Entry'!J44)) | N44: =IF('1_Data Entry'!$E44="","",IF(OR(J44="",R44=""),"",MAX(J44-R44,0))) | O44: =IF('1_Data Entry'!$E44="","",IF(A44="","",'1_Data Entry'!L44)) | P44: =IF(OR(M44="",O44="",O44<=0,N44="",N44<=0),"",O44*N44) | Q44: =IF('1_Data Entry'!$E44="","",IF(OR(M44="",P44="",L44=""),"",P44-L44)) | R44: =IF(A44="","",IF('1_Data Entry'!M44<>"",'1_Data Entry'!M44,IF('1_Data Entry'!J44="",J44,""))) | S44: =IF('1_Data Entry'!$E44="","",IF(A44="","",IF(OR(F44="",I44="",J44="",K44=""),"Check row",IF(AND(M44<>"",M44<I44),"Sell before buy",IF(AND(R44<>"",J44<R44),"Shares remaining exceeds buy",IF(AND(M44<>"",OR(O44="",O44<=0),N44>0),"Missing sale price","OK")))))) | T44: =IF('1_Data Entry'!$E44="","",IF(A44="","",IF(AND(Q44<0,M44<>""),"Yes","No"))) | U44: =IF('1_Data Entry'!$E44="","",IF(OR(A44="",T44<>"Yes",M44=""),"No",IF(COUNTIFS($F$6:$F$505,F44,$I$6:$I$505,">="&M44-30,$I$6:$I$505,"<="&M44+30,$A$6:$A$505,"<>"&A44)>0,"Yes","No"))) | V44: =IF('1_Data Entry'!$E44="","",IF(OR(A44="",U44<>"Yes",M44=""),"",M44+30)) | W44: =IF('1_Data Entry'!$E44="","",IF(A44="","",IF(S44="OK","Ready","Review row"))) | X44: =IF(OR(I44="",M44=""),"",M44-I44) | Y44: =IF(X44="","",IF(X44<=365,"Short-Term","Long-Term")) | Z44: =IF('1_Data Entry'!$E44="","",SUM(SUMIFS('4_Wash Match Table'!R$7:R$500,'4_Wash Match Table'!L$7:L$500,H44),(SUMIFS('4_Wash Match Table'!AA$7:AA$500,'4_Wash Match Table'!U$7:U$500,H44)),(SUMIFS('4_Wash Match Table'!AJ$7:AJ$500,'4_Wash Match Table'!AD$7:AD$500,H44)),(SUMIFS('4_Wash Match Table'!AS$7:AS$500,'4_Wash Match Table'!AM$7:AM$500,H44)))) | AA44: =IF('1_Data Entry'!$E44="","",IF(OR(L44="",Z44=""),"",L44+Z44)) | AB44: =IFERROR(IF(OR(J44="",AA44=""),"",AA44/J44),"") | AC44: =IF(AND($M44<>"",$Q44<0),COUNTIFS($M$6:M44,"<>",$Q$6:Q44,"<0"),"") | AD44: =IF(A44="","",ROW())
A45: =IF('1_Data Entry'!$E45="","",IF(COUNTA('1_Data Entry'!C45:N45)=0,"",'1_Data Entry'!A45)) | B45: =IF('1_Data Entry'!$E45="","",IF(A45="","",IF(S45<>"OK","Check row",IF(M45="","Open lot",IF(R45=0,"Closed lot","Partially sold"))))) | C45: =IF(A45="","",'1_Data Entry'!C45) | D45: =IF(A45="","",'1_Data Entry'!D45) | E45: =IF(A45="","",'1_Data Entry'!E45) | F45: =IF(E45="","",UPPER(TRIM(E45))) | G45: =IF(F45="","",IFERROR(VLOOKUP(F45,'6_Reference Lists'!$A$4:$D$64,4,FALSE()),'1_Data Entry'!F45)) | H45: =IF('1_Data Entry'!$E45="","",IF(OR(F45="",I45="",J45="",K45=""),"",F45&"-"&TEXT(I45,"yyyymmdd")&"-"&SUBSTITUTE(TEXT(ROUND(J45,3),"0.###"),".","D")&"-"&SUBSTITUTE(TEXT(ROUND(K45,3),"0.###"),".","D"))) | I45: =IF('1_Data Entry'!$E45="","",IF(A45="","",'1_Data Entry'!G45)) | J45: =IF('1_Data Entry'!$E45="","",IF(A45="","",'1_Data Entry'!H45)) | K45: =IF('1_Data Entry'!$E45="","",IF(A45="","",'1_Data Entry'!I45)) | L45: =IF('1_Data Entry'!$E45="","",IF(OR(J45="",K45=""),"",J45*K45)) | M45: =IF(A45="","",IF(OR('1_Data Entry'!L45="",'1_Data Entry'!L45<=0),"",'1_Data Entry'!J45)) | N45: =IF('1_Data Entry'!$E45="","",IF(OR(J45="",R45=""),"",MAX(J45-R45,0))) | O45: =IF('1_Data Entry'!$E45="","",IF(A45="","",'1_Data Entry'!L45)) | P45: =IF(OR(M45="",O45="",O45<=0,N45="",N45<=0),"",O45*N45) | Q45: =IF('1_Data Entry'!$E45="","",IF(OR(M45="",P45="",L45=""),"",P45-L45)) | R45: =IF(A45="","",IF('1_Data Entry'!M45<>"",'1_Data Entry'!M45,IF('1_Data Entry'!J45="",J45,""))) | S45: =IF('1_Data Entry'!$E45="","",IF(A45="","",IF(OR(F45="",I45="",J45="",K45=""),"Check row",IF(AND(M45<>"",M45<I45),"Sell before buy",IF(AND(R45<>"",J45<R45),"Shares remaining exceeds buy",IF(AND(M45<>"",OR(O45="",O45<=0),N45>0),"Missing sale price","OK")))))) | T45: =IF('1_Data Entry'!$E45="","",IF(A45="","",IF(AND(Q45<0,M45<>""),"Yes","No"))) | U45: =IF('1_Data Entry'!$E45="","",IF(OR(A45="",T45<>"Yes",M45=""),"No",IF(COUNTIFS($F$6:$F$505,F45,$I$6:$I$505,">="&M45-30,$I$6:$I$505,"<="&M45+30,$A$6:$A$505,"<>"&A45)>0,"Yes","No"))) | V45: =IF('1_Data Entry'!$E45="","",IF(OR(A45="",U45<>"Yes",M45=""),"",M45+30)) | W45: =IF('1_Data Entry'!$E45="","",IF(A45="","",IF(S45="OK","Ready","Review row"))) | X45: =IF(OR(I45="",M45=""),"",M45-I45) | Y45: =IF(X45="","",IF(X45<=365,"Short-Term","Long-Term")) | Z45: =IF('1_Data Entry'!$E45="","",SUM(SUMIFS('4_Wash Match Table'!R$7:R$500,'4_Wash Match Table'!L$7:L$500,H45),(SUMIFS('4_Wash Match Table'!AA$7:AA$500,'4_Wash Match Table'!U$7:U$500,H45)),(SUMIFS('4_Wash Match Table'!AJ$7:AJ$500,'4_Wash Match Table'!AD$7:AD$500,H45)),(SUMIFS('4_Wash Match Table'!AS$7:AS$500,'4_Wash Match Table'!AM$7:AM$500,H45)))) | AA45: =IF('1_Data Entry'!$E45="","",IF(OR(L45="",Z45=""),"",L45+Z45)) | AB45: =IFERROR(IF(OR(J45="",AA45=""),"",AA45/J45),"") | AC45: =IF(AND($M45<>"",$Q45<0),COUNTIFS($M$6:M45,"<>",$Q$6:Q45,"<0"),"") | AD45: =IF(A45="","",ROW())
A46: =IF('1_Data Entry'!$E46="","",IF(COUNTA('1_Data Entry'!C46:N46)=0,"",'1_Data Entry'!A46)) | B46: =IF('1_Data Entry'!$E46="","",IF(A46="","",IF(S46<>"OK","Check row",IF(M46="","Open lot",IF(R46=0,"Closed lot","Partially sold"))))) | C46: =IF(A46="","",'1_Data Entry'!C46) | D46: =IF(A46="","",'1_Data Entry'!D46) | E46: =IF(A46="","",'1_Data Entry'!E46) | F46: =IF(E46="","",UPPER(TRIM(E46))) | G46: =IF(F46="","",IFERROR(VLOOKUP(F46,'6_Reference Lists'!$A$4:$D$64,4,FALSE()),'1_Data Entry'!F46)) | H46: =IF('1_Data Entry'!$E46="","",IF(OR(F46="",I46="",J46="",K46=""),"",F46&"-"&TEXT(I46,"yyyymmdd")&"-"&SUBSTITUTE(TEXT(ROUND(J46,3),"0.###"),".","D")&"-"&SUBSTITUTE(TEXT(ROUND(K46,3),"0.###"),".","D"))) | I46: =IF('1_Data Entry'!$E46="","",IF(A46="","",'1_Data Entry'!G46)) | J46: =IF('1_Data Entry'!$E46="","",IF(A46="","",'1_Data Entry'!H46)) | K46: =IF('1_Data Entry'!$E46="","",IF(A46="","",'1_Data Entry'!I46)) | L46: =IF('1_Data Entry'!$E46="","",IF(OR(J46="",K46=""),"",J46*K46)) | M46: =IF(A46="","",IF(OR('1_Data Entry'!L46="",'1_Data Entry'!L46<=0),"",'1_Data Entry'!J46)) | N46: =IF('1_Data Entry'!$E46="","",IF(OR(J46="",R46=""),"",MAX(J46-R46,0))) | O46: =IF('1_Data Entry'!$E46="","",IF(A46="","",'1_Data Entry'!L46)) | P46: =IF(OR(M46="",O46="",O46<=0,N46="",N46<=0),"",O46*N46) | Q46: =IF('1_Data Entry'!$E46="","",IF(OR(M46="",P46="",L46=""),"",P46-L46)) | R46: =IF(A46="","",IF('1_Data Entry'!M46<>"",'1_Data Entry'!M46,IF('1_Data Entry'!J46="",J46,""))) | S46: =IF('1_Data Entry'!$E46="","",IF(A46="","",IF(OR(F46="",I46="",J46="",K46=""),"Check row",IF(AND(M46<>"",M46<I46),"Sell before buy",IF(AND(R46<>"",J46<R46),"Shares remaining exceeds buy",IF(AND(M46<>"",OR(O46="",O46<=0),N46>0),"Missing sale price","OK")))))) | T46: =IF('1_Data Entry'!$E46="","",IF(A46="","",IF(AND(Q46<0,M46<>""),"Yes","No"))) | U46: =IF('1_Data Entry'!$E46="","",IF(OR(A46="",T46<>"Yes",M46=""),"No",IF(COUNTIFS($F$6:$F$505,F46,$I$6:$I$505,">="&M46-30,$I$6:$I$505,"<="&M46+30,$A$6:$A$505,"<>"&A46)>0,"Yes","No"))) | V46: =IF('1_Data Entry'!$E46="","",IF(OR(A46="",U46<>"Yes",M46=""),"",M46+30)) | W46: =IF('1_Data Entry'!$E46="","",IF(A46="","",IF(S46="OK","Ready","Review row"))) | X46: =IF(OR(I46="",M46=""),"",M46-I46) | Y46: =IF(X46="","",IF(X46<=365,"Short-Term","Long-Term")) | Z46: =IF('1_Data Entry'!$E46="","",SUM(SUMIFS('4_Wash Match Table'!R$7:R$500,'4_Wash Match Table'!L$7:L$500,H46),(SUMIFS('4_Wash Match Table'!AA$7:AA$500,'4_Wash Match Table'!U$7:U$500,H46)),(SUMIFS('4_Wash Match Table'!AJ$7:AJ$500,'4_Wash Match Table'!AD$7:AD$500,H46)),(SUMIFS('4_Wash Match Table'!AS$7:AS$500,'4_Wash Match Table'!AM$7:AM$500,H46)))) | AA46: =IF('1_Data Entry'!$E46="","",IF(OR(L46="",Z46=""),"",L46+Z46)) | AB46: =IFERROR(IF(OR(J46="",AA46=""),"",AA46/J46),"") | AC46: =IF(AND($M46<>"",$Q46<0),COUNTIFS($M$6:M46,"<>",$Q$6:Q46,"<0"),"") | AD46: =IF(A46="","",ROW())
... A505: =IF('1_Data Entry'!$E505="","",IF(COUNTA('1_Data Entry'!C505:N505)=0,"",'1_Data Entry'!A505)) | B505: =IF('1_Data Entry'!$E505="","",IF(A505="","",IF(S505<>"OK","Check row",IF(M505="","Open lot",IF(R505=0,"Closed lot","Partially sold"))))) | C505: =IF(A505="","",'1_Data Entry'!C505) | D505: =IF(A505="","",'1_Data Entry'!D505) | E505: =IF(A505="","",'1_Data Entry'!E505) | F505: =IF(E505="","",UPPER(TRIM(E505))) | G505: =IF(F505="","",IFERROR(VLOOKUP(F505,'6_Reference Lists'!$A$4:$D$64,4,FALSE()),'1_Data Entry'!F505)) | H505: =IF('1_Data Entry'!$E505="","",IF(OR(F505="",I505="",J505="",K505=""),"",F505&"-"&TEXT(I505,"yyyymmdd")&"-"&SUBSTITUTE(TEXT(ROUND(J505,3),"0.###"),".","D")&"-"&SUBSTITUTE(TEXT(ROUND(K505,3),"0.###"),".","D"))) | I505: =IF('1_Data Entry'!$E505="","",IF(A505="","",'1_Data Entry'!G505)) | J505: =IF('1_Data Entry'!$E505="","",IF(A505="","",'1_Data Entry'!H505)) | K505: =IF('1_Data Entry'!$E505="","",IF(A505="","",'1_Data Entry'!I505)) | L505: =IF('1_Data Entry'!$E505="","",IF(OR(J505="",K505=""),"",J505*K505)) | M505: =IF(A505="","",IF(OR('1_Data Entry'!L505="",'1_Data Entry'!L505<=0),"",'1_Data Entry'!J505)) | N505: =IF('1_Data Entry'!$E505="","",IF(OR(J505="",R505=""),"",MAX(J505-R505,0))) | O505: =IF('1_Data Entry'!$E505="","",IF(A505="","",'1_Data Entry'!L505)) | P505: =IF(OR(M505="",O505="",O505<=0,N505="",N505<=0),"",O505*N505) | Q505: =IF('1_Data Entry'!$E505="","",IF(OR(M505="",P505="",L505=""),"",P505-L505)) | R505: =IF(A505="","",IF('1_Data Entry'!M505<>"",'1_Data Entry'!M505,IF('1_Data Entry'!J505="",J505,""))) | S505: =IF('1_Data Entry'!$E505="","",IF(A505="","",IF(OR(F505="",I505="",J505="",K505=""),"Check row",IF(AND(M505<>"",M505<I505),"Sell before buy",IF(AND(R505<>"",J505<R505),"Shares remaining exceeds buy",IF(AND(M505<>"",OR(O505="",O505<=0),N505>0),"Missing sale price","OK")))))) | T505: =IF('1_Data Entry'!$E505="","",IF(A505="","",IF(AND(Q505<0,M505<>""),"Yes","No"))) | U505: =IF('1_Data Entry'!$E505="","",IF(OR(A505="",T505<>"Yes",M505=""),"No",IF(COUNTIFS($F$6:$F$505,F505,$I$6:$I$505,">="&M505-30,$I$6:$I$505,"<="&M505+30,$A$6:$A$505,"<>"&A505)>0,"Yes","No"))) | V505: =IF('1_Data Entry'!$E505="","",IF(OR(A505="",U505<>"Yes",M505=""),"",M505+30)) | W505: =IF('1_Data Entry'!$E505="","",IF(A505="","",IF(S505="OK","Ready","Review row"))) | X505: =IF(OR(I505="",M505=""),"",M505-I505) | Y505: =IF(X505="","",IF(X505<=365,"Short-Term","Long-Term")) | Z505: =IF('1_Data Entry'!$E505="","",SUM(SUMIFS('4_Wash Match Table'!R$7:R$500,'4_Wash Match Table'!L$7:L$500,H505),(SUMIFS('4_Wash Match Table'!AA$7:AA$500,'4_Wash Match Table'!U$7:U$500,H505)),(SUMIFS('4_Wash Match Table'!AJ$7:AJ$500,'4_Wash Match Table'!AD$7:AD$500,H505)),(SUMIFS('4_Wash Match Table'!AS$7:AS$500,'4_Wash Match Table'!AM$7:AM$500,H505)))) | AA505: =IF('1_Data Entry'!$E505="","",IF(OR(L505="",Z505=""),"",L505+Z505)) | AB505: =IFERROR(IF(OR(J505="",AA505=""),"",AA505/J505),"") | AC505: =IF(AND($M505<>"",$Q505<0),COUNTIFS($M$6:M505,"<>",$Q$6:Q505,"<0"),"") | AD505: =IF(A505="","",ROW())

Sheet 3_Wash Engine
A1: 3_Wash Engine — Summary + Transaction Detail
A2: Top = ticker summary with short-term and long-term splits. Bottom = transaction-level audit trail. Default match method = FIFO by earliest eligible replacement lot; manual override supported via Data Entry column L.
A4: Ticker Summary | N4: Overall Summary
A5: Ticker | B5: Open Shares | C5: Recent Rebuy? | D5: Recent Rebuy Ends | E5: Short-Term Gains | F5: Short-Term Losses | G5: Long-Term Gains | H5: Long-Term Losses | I5: YTD Net Realized Gain / (Loss) | J5: Latest Loss Sale Date | K5: Wash Sale End Date | L5: Wash Rows | N5: Short-Term Gains | O5: =SUMIFS('2_Review & Audit'!$Q$6:$Q$505,'2_Review & Audit'!$Q$6:$Q$505,">0",'2_Review & Audit'!$Y$6:$Y$505,"Short-Term") -> 9457.634
A6: =IF('6_Reference Lists'!A4="", "", '6_Reference Lists'!A4) -> EPD | B6: =IF(A6="","",SUMIFS('2_Review & Audit'!$R$6:$R$505,'2_Review & Audit'!$F$6:$F$505,A6)) -> 0 | C6: =IF(A6="","",IF(COUNTIFS('2_Review & Audit'!$F$6:$F$505,A6,'2_Review & Audit'!$U$6:$U$505,"Yes")>0,"Yes","No")) -> No | D6: =IF(A6="","",IF(C6<>"Yes","",IFERROR(LOOKUP(2,1/(('2_Review & Audit'!$F$6:$F$505=A6)*('2_Review & Audit'!$U$6:$U$505="Yes")),'2_Review & Audit'!$V$6:$V$505),""))) | E6: =IF(A6="","",SUMIFS('2_Review & Audit'!$Q$6:$Q$505,'2_Review & Audit'!$F$6:$F$505,A6,'2_Review & Audit'!$Y$6:$Y$505,"Short-Term",'2_Review & Audit'!$Q$6:$Q$505,">0")) -> 9457.634 | F6: =IF(A6="","",SUMIFS('2_Review & Audit'!$Q$6:$Q$505,'2_Review & Audit'!$F$6:$F$505,A6,'2_Review & Audit'!$Y$6:$Y$505,"Short-Term",'2_Review & Audit'!$Q$6:$Q$505,"<0")) -> 0 | G6: =IF(A6="","",SUMIFS('2_Review & Audit'!$Q$6:$Q$505,'2_Review & Audit'!$F$6:$F$505,A6,'2_Review & Audit'!$Y$6:$Y$505,"Long-Term",'2_Review & Audit'!$Q$6:$Q$505,">0")) -> 32927.6 | H6: =IF(A6="","",SUMIFS('2_Review & Audit'!$Q$6:$Q$505,'2_Review & Audit'!$F$6:$F$505,A6,'2_Review & Audit'!$Y$6:$Y$505,"Long-Term",'2_Review & Audit'!$Q$6:$Q$505,"<0")) -> 0 | I6: =IF(A6="","",SUM(E6:H6)) -> 42385.234 | J6: =IF(A6="","",IFERROR(LOOKUP(2,1/(('2_Review & Audit'!$F$6:$F$505=A6)*('2_Review & Audit'!$Q$6:$Q$505<0)*('2_Review & Audit'!$M$6:$M$505<>"")),'2_Review & Audit'!$M$6:$M$505),"")) | K6: =IF(A6="","",IF(C6<>"Yes","",D6)) | L6: =IF(A6="","",COUNTIFS('4_Wash Match Table'!$A$7:$A$506,A6,'4_Wash Match Table'!$P$7:$P$506,">0")) -> 0 | N6: Short-Term Losses | O6: =SUMIFS('2_Review & Audit'!$Q$6:$Q$505,'2_Review & Audit'!$Q$6:$Q$505,"<0",'2_Review & Audit'!$Y$6:$Y$505,"Short-Term") -> -2447.9641
A7: =IF('6_Reference Lists'!A5="", "", '6_Reference Lists'!A5) -> ITOT | B7: =IF(A7="","",SUMIFS('2_Review & Audit'!$R$6:$R$505,'2_Review & Audit'!$F$6:$F$505,A7)) -> 0 | C7: =IF(A7="","",IF(COUNTIFS('2_Review & Audit'!$F$6:$F$505,A7,'2_Review & Audit'!$U$6:$U$505,"Yes")>0,"Yes","No")) -> Yes | D7: =IF(A7="","",IF(C7<>"Yes","",IFERROR(LOOKUP(2,1/(('2_Review & Audit'!$F$6:$F$505=A7)*('2_Review & Audit'!$U$6:$U$505="Yes")),'2_Review & Audit'!$V$6:$V$505),""))) -> 46131 | E7: =IF(A7="","",SUMIFS('2_Review & Audit'!$Q$6:$Q$505,'2_Review & Audit'!$F$6:$F$505,A7,'2_Review & Audit'!$Y$6:$Y$505,"Short-Term",'2_Review & Audit'!$Q$6:$Q$505,">0")) -> 0 | F7: =IF(A7="","",SUMIFS('2_Review & Audit'!$Q$6:$Q$505,'2_Review & Audit'!$F$6:$F$505,A7,'2_Review & Audit'!$Y$6:$Y$505,"Short-Term",'2_Review & Audit'!$Q$6:$Q$505,"<0")) -> -554.4891 | G7: =IF(A7="","",SUMIFS('2_Review & Audit'!$Q$6:$Q$505,'2_Review & Audit'!$F$6:$F$505,A7,'2_Review & Audit'!$Y$6:$Y$505,"Long-Term",'2_Review & Audit'!$Q$6:$Q$505,">0")) -> 0 | H7: =IF(A7="","",SUMIFS('2_Review & Audit'!$Q$6:$Q$505,'2_Review & Audit'!$F$6:$F$505,A7,'2_Review & Audit'!$Y$6:$Y$505,"Long-Term",'2_Review & Audit'!$Q$6:$Q$505,"<0")) -> 0 | I7: =IF(A7="","",SUM(E7:H7)) -> -554.4891 | J7: =IF(A7="","",IFERROR(LOOKUP(2,1/(('2_Review & Audit'!$F$6:$F$505=A7)*('2_Review & Audit'!$Q$6:$Q$505<0)*('2_Review & Audit'!$M$6:$M$505<>"")),'2_Review & Audit'!$M$6:$M$505),"")) -> 46101 | K7: =IF(A7="","",IF(C7<>"Yes","",D7)) -> 46131 | L7: =IF(A7="","",COUNTIFS('4_Wash Match Table'!$A$7:$A$506,A7,'4_Wash Match Table'!$P$7:$P$506,">0")) -> 0 | N7: Long-Term Gains | O7: =SUMIFS('2_Review & Audit'!$Q$6:$Q$505,'2_Review & Audit'!$Q$6:$Q$505,">0",'2_Review & Audit'!$Y$6:$Y$505,"Long-Term") -> 32927.6
A8: =IF('6_Reference Lists'!A6="", "", '6_Reference Lists'!A6) -> IWB | B8: =IF(A8="","",SUMIFS('2_Review & Audit'!$R$6:$R$505,'2_Review & Audit'!$F$6:$F$505,A8)) -> 0 | C8: =IF(A8="","",IF(COUNTIFS('2_Review & Audit'!$F$6:$F$505,A8,'2_Review & Audit'!$U$6:$U$505,"Yes")>0,"Yes","No")) -> No | D8: =IF(A8="","",IF(C8<>"Yes","",IFERROR(LOOKUP(2,1/(('2_Review & Audit'!$F$6:$F$505=A8)*('2_Review & Audit'!$U$6:$U$505="Yes")),'2_Review & Audit'!$V$6:$V$505),""))) | E8: =IF(A8="","",SUMIFS('2_Review & Audit'!$Q$6:$Q$505,'2_Review & Audit'!$F$6:$F$505,A8,'2_Review & Audit'!$Y$6:$Y$505,"Short-Term",'2_Review & Audit'!$Q$6:$Q$505,">0")) -> 0 | F8: =IF(A8="","",SUMIFS('2_Review & Audit'!$Q$6:$Q$505,'2_Review & Audit'!$F$6:$F$505,A8,'2_Review & Audit'!$Y$6:$Y$505,"Short-Term",'2_Review & Audit'!$Q$6:$Q$505,"<0")) -> 0 | G8: =IF(A8="","",SUMIFS('2_Review & Audit'!$Q$6:$Q$505,'2_Review & Audit'!$F$6:$F$505,A8,'2_Review & Audit'!$Y$6:$Y$505,"Long-Term",'2_Review & Audit'!$Q$6:$Q$505,">0")) -> 0 | H8: =IF(A8="","",SUMIFS('2_Review & Audit'!$Q$6:$Q$505,'2_Review & Audit'!$F$6:$F$505,A8,'2_Review & Audit'!$Y$6:$Y$505,"Long-Term",'2_Review & Audit'!$Q$6:$Q$505,"<0")) -> 0 | I8: =IF(A8="","",SUM(E8:H8)) -> 0 | J8: =IF(A8="","",IFERROR(LOOKUP(2,1/(('2_Review & Audit'!$F$6:$F$505=A8)*('2_Review & Audit'!$Q$6:$Q$505<0)*('2_Review & Audit'!$M$6:$M$505<>"")),'2_Review & Audit'!$M$6:$M$505),"")) | K8: =IF(A8="","",IF(C8<>"Yes","",D8)) | L8: =IF(A8="","",COUNTIFS('4_Wash Match Table'!$A$7:$A$506,A8,'4_Wash Match Table'!$P$7:$P$506,">0")) -> 0 | N8: Long-Term Losses | O8: =SUMIFS('2_Review & Audit'!$Q$6:$Q$505,'2_Review & Audit'!$Q$6:$Q$505,"<0",'2_Review & Audit'!$Y$6:$Y$505,"Long-Term") -> 0
A9: =IF('6_Reference Lists'!A7="", "", '6_Reference Lists'!A7) -> IXUS | B9: =IF(A9="","",SUMIFS('2_Review & Audit'!$R$6:$R$505,'2_Review & Audit'!$F$6:$F$505,A9)) -> 0 | C9: =IF(A9="","",IF(COUNTIFS('2_Review & Audit'!$F$6:$F$505,A9,'2_Review & Audit'!$U$6:$U$505,"Yes")>0,"Yes","No")) -> Yes | D9: =IF(A9="","",IF(C9<>"Yes","",IFERROR(LOOKUP(2,1/(('2_Review & Audit'!$F$6:$F$505=A9)*('2_Review & Audit'!$U$6:$U$505="Yes")),'2_Review & Audit'!$V$6:$V$505),""))) -> 46131 | E9: =IF(A9="","",SUMIFS('2_Review & Audit'!$Q$6:$Q$505,'2_Review & Audit'!$F$6:$F$505,A9,'2_Review & Audit'!$Y$6:$Y$505,"Short-Term",'2_Review & Audit'!$Q$6:$Q$505,">0")) -> 0 | F9: =IF(A9="","",SUMIFS('2_Review & Audit'!$Q$6:$Q$505,'2_Review & Audit'!$F$6:$F$505,A9,'2_Review & Audit'!$Y$6:$Y$505,"Short-Term",'2_Review & Audit'!$Q$6:$Q$505,"<0")) -> -794.99497 | G9: =IF(A9="","",SUMIFS('2_Review & Audit'!$Q$6:$Q$505,'2_Review & Audit'!$F$6:$F$505,A9,'2_Review & Audit'!$Y$6:$Y$505,"Long-Term",'2_Review & Audit'!$Q$6:$Q$505,">0")) -> 0 | H9: =IF(A9="","",SUMIFS('2_Review & Audit'!$Q$6:$Q$505,'2_Review & Audit'!$F$6:$F$505,A9,'2_Review & Audit'!$Y$6:$Y$505,"Long-Term",'2_Review & Audit'!$Q$6:$Q$505,"<0")) -> 0 | I9: =IF(A9="","",SUM(E9:H9)) -> -794.99497 | J9: =IF(A9="","",IFERROR(LOOKUP(2,1/(('2_Review & Audit'!$F$6:$F$505=A9)*('2_Review & Audit'!$Q$6:$Q$505<0)*('2_Review & Audit'!$M$6:$M$505<>"")),'2_Review & Audit'!$M$6:$M$505),"")) -> 46101 | K9: =IF(A9="","",IF(C9<>"Yes","",D9)) -> 46131 | L9: =IF(A9="","",COUNTIFS('4_Wash Match Table'!$A$7:$A$506,A9,'4_Wash Match Table'!$P$7:$P$506,">0")) -> 0 | N9: Net Realized Gain / (Loss) | O9: =SUM(O5:O8) -> 39937.27
A10: =IF('6_Reference Lists'!A8="", "", '6_Reference Lists'!A8) -> RSP | B10: =IF(A10="","",SUMIFS('2_Review & Audit'!$R$6:$R$505,'2_Review & Audit'!$F$6:$F$505,A10)) -> 0 | C10: =IF(A10="","",IF(COUNTIFS('2_Review & Audit'!$F$6:$F$505,A10,'2_Review & Audit'!$U$6:$U$505,"Yes")>0,"Yes","No")) -> No | D10: =IF(A10="","",IF(C10<>"Yes","",IFERROR(LOOKUP(2,1/(('2_Review & Audit'!$F$6:$F$505=A10)*('2_Review & Audit'!$U$6:$U$505="Yes")),'2_Review & Audit'!$V$6:$V$505),""))) | E10: =IF(A10="","",SUMIFS('2_Review & Audit'!$Q$6:$Q$505,'2_Review & Audit'!$F$6:$F$505,A10,'2_Review & Audit'!$Y$6:$Y$505,"Short-Term",'2_Review & Audit'!$Q$6:$Q$505,">0")) -> 0 | F10: =IF(A10="","",SUMIFS('2_Review & Audit'!$Q$6:$Q$505,'2_Review & Audit'!$F$6:$F$505,A10,'2_Review & Audit'!$Y$6:$Y$505,"Short-Term",'2_Review & Audit'!$Q$6:$Q$505,"<0")) -> 0 | G10: =IF(A10="","",SUMIFS('2_Review & Audit'!$Q$6:$Q$505,'2_Review & Audit'!$F$6:$F$505,A10,'2_Review & Audit'!$Y$6:$Y$505,"Long-Term",'2_Review & Audit'!$Q$6:$Q$505,">0")) -> 0 | H10: =IF(A10="","",SUMIFS('2_Review & Audit'!$Q$6:$Q$505,'2_Review & Audit'!$F$6:$F$505,A10,'2_Review & Audit'!$Y$6:$Y$505,"Long-Term",'2_Review & Audit'!$Q$6:$Q$505,"<0")) -> 0 | I10: =IF(A10="","",SUM(E10:H10)) -> 0 | J10: =IF(A10="","",IFERROR(LOOKUP(2,1/(('2_Review & Audit'!$F$6:$F$505=A10)*('2_Review & Audit'!$Q$6:$Q$505<0)*('2_Review & Audit'!$M$6:$M$505<>"")),'2_Review & Audit'!$M$6:$M$505),"")) | K10: =IF(A10="","",IF(C10<>"Yes","",D10)) | L10: =IF(A10="","",COUNTIFS('4_Wash Match Table'!$A$7:$A$506,A10,'4_Wash Match Table'!$P$7:$P$506,">0")) -> 0
A11: =IF('6_Reference Lists'!A9="", "", '6_Reference Lists'!A9) -> SCHB | B11: =IF(A11="","",SUMIFS('2_Review & Audit'!$R$6:$R$505,'2_Review & Audit'!$F$6:$F$505,A11)) -> 180 | C11: =IF(A11="","",IF(COUNTIFS('2_Review & Audit'!$F$6:$F$505,A11,'2_Review & Audit'!$U$6:$U$505,"Yes")>0,"Yes","No")) -> Yes | D11: =IF(A11="","",IF(C11<>"Yes","",IFERROR(LOOKUP(2,1/(('2_Review & Audit'!$F$6:$F$505=A11)*('2_Review & Audit'!$U$6:$U$505="Yes")),'2_Review & Audit'!$V$6:$V$505),""))) -> 46138 | E11: =IF(A11="","",SUMIFS('2_Review & Audit'!$Q$6:$Q$505,'2_Review & Audit'!$F$6:$F$505,A11,'2_Review & Audit'!$Y$6:$Y$505,"Short-Term",'2_Review & Audit'!$Q$6:$Q$505,">0")) -> 0 | F11: =IF(A11="","",SUMIFS('2_Review & Audit'!$Q$6:$Q$505,'2_Review & Audit'!$F$6:$F$505,A11,'2_Review & Audit'!$Y$6:$Y$505,"Short-Term",'2_Review & Audit'!$Q$6:$Q$505,"<0")) -> -1098.48 | G11: =IF(A11="","",SUMIFS('2_Review & Audit'!$Q$6:$Q$505,'2_Review & Audit'!$F$6:$F$505,A11,'2_Review & Audit'!$Y$6:$Y$505,"Long-Term",'2_Review & Audit'!$Q$6:$Q$505,">0")) -> 0 | H11: =IF(A11="","",SUMIFS('2_Review & Audit'!$Q$6:$Q$505,'2_Review & Audit'!$F$6:$F$505,A11,'2_Review & Audit'!$Y$6:$Y$505,"Long-Term",'2_Review & Audit'!$Q$6:$Q$505,"<0")) -> 0 | I11: =IF(A11="","",SUM(E11:H11)) -> -1098.48 | J11: =IF(A11="","",IFERROR(LOOKUP(2,1/(('2_Review & Audit'!$F$6:$F$505=A11)*('2_Review & Audit'!$Q$6:$Q$505<0)*('2_Review & Audit'!$M$6:$M$505<>"")),'2_Review & Audit'!$M$6:$M$505),"")) -> 46108 | K11: =IF(A11="","",IF(C11<>"Yes","",D11)) -> 46138 | L11: =IF(A11="","",COUNTIFS('4_Wash Match Table'!$A$7:$A$506,A11,'4_Wash Match Table'!$P$7:$P$506,">0")) -> 2
A12: =IF('6_Reference Lists'!A10="", "", '6_Reference Lists'!A10) -> SCHF | B12: =IF(A12="","",SUMIFS('2_Review & Audit'!$R$6:$R$505,'2_Review & Audit'!$F$6:$F$505,A12)) -> 0 | C12: =IF(A12="","",IF(COUNTIFS('2_Review & Audit'!$F$6:$F$505,A12,'2_Review & Audit'!$U$6:$U$505,"Yes")>0,"Yes","No")) -> No | D12: =IF(A12="","",IF(C12<>"Yes","",IFERROR(LOOKUP(2,1/(('2_Review & Audit'!$F$6:$F$505=A12)*('2_Review & Audit'!$U$6:$U$505="Yes")),'2_Review & Audit'!$V$6:$V$505),""))) | E12: =IF(A12="","",SUMIFS('2_Review & Audit'!$Q$6:$Q$505,'2_Review & Audit'!$F$6:$F$505,A12,'2_Review & Audit'!$Y$6:$Y$505,"Short-Term",'2_Review & Audit'!$Q$6:$Q$505,">0")) -> 0 | F12: =IF(A12="","",SUMIFS('2_Review & Audit'!$Q$6:$Q$505,'2_Review & Audit'!$F$6:$F$505,A12,'2_Review & Audit'!$Y$6:$Y$505,"Short-Term",'2_Review & Audit'!$Q$6:$Q$505,"<0")) -> 0 | G12: =IF(A12="","",SUMIFS('2_Review & Audit'!$Q$6:$Q$505,'2_Review & Audit'!$F$6:$F$505,A12,'2_Review & Audit'!$Y$6:$Y$505,"Long-Term",'2_Review & Audit'!$Q$6:$Q$505,">0")) -> 0 | H12: =IF(A12="","",SUMIFS('2_Review & Audit'!$Q$6:$Q$505,'2_Review & Audit'!$F$6:$F$505,A12,'2_Review & Audit'!$Y$6:$Y$505,"Long-Term",'2_Review & Audit'!$Q$6:$Q$505,"<0")) -> 0 | I12: =IF(A12="","",SUM(E12:H12)) -> 0 | J12: =IF(A12="","",IFERROR(LOOKUP(2,1/(('2_Review & Audit'!$F$6:$F$505=A12)*('2_Review & Audit'!$Q$6:$Q$505<0)*('2_Review & Audit'!$M$6:$M$505<>"")),'2_Review & Audit'!$M$6:$M$505),"")) | K12: =IF(A12="","",IF(C12<>"Yes","",D12)) | L12: =IF(A12="","",COUNTIFS('4_Wash Match Table'!$A$7:$A$506,A12,'4_Wash Match Table'!$P$7:$P$506,">0")) -> 0
A13: =IF('6_Reference Lists'!A11="", "", '6_Reference Lists'!A11) -> SCHX | B13: =IF(A13="","",SUMIFS('2_Review & Audit'!$R$6:$R$505,'2_Review & Audit'!$F$6:$F$505,A13)) -> 0 | C13: =IF(A13="","",IF(COUNTIFS('2_Review & Audit'!$F$6:$F$505,A13,'2_Review & Audit'!$U$6:$U$505,"Yes")>0,"Yes","No")) -> No | D13: =IF(A13="","",IF(C13<>"Yes","",IFERROR(LOOKUP(2,1/(('2_Review & Audit'!$F$6:$F$505=A13)*('2_Review & Audit'!$U$6:$U$505="Yes")),'2_Review & Audit'!$V$6:$V$505),""))) | E13: =IF(A13="","",SUMIFS('2_Review & Audit'!$Q$6:$Q$505,'2_Review & Audit'!$F$6:$F$505,A13,'2_Review & Audit'!$Y$6:$Y$505,"Short-Term",'2_Review & Audit'!$Q$6:$Q$505,">0")) -> 0 | F13: =IF(A13="","",SUMIFS('2_Review & Audit'!$Q$6:$Q$505,'2_Review & Audit'!$F$6:$F$505,A13,'2_Review & Audit'!$Y$6:$Y$505,"Short-Term",'2_Review & Audit'!$Q$6:$Q$505,"<0")) -> 0 | G13: =IF(A13="","",SUMIFS('2_Review & Audit'!$Q$6:$Q$505,'2_Review & Audit'!$F$6:$F$505,A13,'2_Review & Audit'!$Y$6:$Y$505,"Long-Term",'2_Review & Audit'!$Q$6:$Q$505,">0")) -> 0 | H13: =IF(A13="","",SUMIFS('2_Review & Audit'!$Q$6:$Q$505,'2_Review & Audit'!$F$6:$F$505,A13,'2_Review & Audit'!$Y$6:$Y$505,"Long-Term",'2_Review & Audit'!$Q$6:$Q$505,"<0")) -> 0 | I13: =IF(A13="","",SUM(E13:H13)) -> 0 | J13: =IF(A13="","",IFERROR(LOOKUP(2,1/(('2_Review & Audit'!$F$6:$F$505=A13)*('2_Review & Audit'!$Q$6:$Q$505<0)*('2_Review & Audit'!$M$6:$M$505<>"")),'2_Review & Audit'!$M$6:$M$505),"")) | K13: =IF(A13="","",IF(C13<>"Yes","",D13)) | L13: =IF(A13="","",COUNTIFS('4_Wash Match Table'!$A$7:$A$506,A13,'4_Wash Match Table'!$P$7:$P$506,">0")) -> 0
A14: =IF('6_Reference Lists'!A12="", "", '6_Reference Lists'!A12) -> VOO | B14: =IF(A14="","",SUMIFS('2_Review & Audit'!$R$6:$R$505,'2_Review & Audit'!$F$6:$F$505,A14)) -> 75.128 | C14: =IF(A14="","",IF(COUNTIFS('2_Review & Audit'!$F$6:$F$505,A14,'2_Review & Audit'!$U$6:$U$505,"Yes")>0,"Yes","No")) -> No | D14: =IF(A14="","",IF(C14<>"Yes","",IFERROR(LOOKUP(2,1/(('2_Review & Audit'!$F$6:$F$505=A14)*('2_Review & Audit'!$U$6:$U$505="Yes")),'2_Review & Audit'!$V$6:$V$505),""))) | E14: =IF(A14="","",SUMIFS('2_Review & Audit'!$Q$6:$Q$505,'2_Review & Audit'!$F$6:$F$505,A14,'2_Review & Audit'!$Y$6:$Y$505,"Short-Term",'2_Review & Audit'!$Q$6:$Q$505,">0")) -> 0 | F14: =IF(A14="","",SUMIFS('2_Review & Audit'!$Q$6:$Q$505,'2_Review & Audit'!$F$6:$F$505,A14,'2_Review & Audit'!$Y$6:$Y$505,"Short-Term",'2_Review & Audit'!$Q$6:$Q$505,"<0")) -> 0 | G14: =IF(A14="","",SUMIFS('2_Review & Audit'!$Q$6:$Q$505,'2_Review & Audit'!$F$6:$F$505,A14,'2_Review & Audit'!$Y$6:$Y$505,"Long-Term",'2_Review & Audit'!$Q$6:$Q$505,">0")) -> 0 | H14: =IF(A14="","",SUMIFS('2_Review & Audit'!$Q$6:$Q$505,'2_Review & Audit'!$F$6:$F$505,A14,'2_Review & Audit'!$Y$6:$Y$505,"Long-Term",'2_Review & Audit'!$Q$6:$Q$505,"<0")) -> 0 | I14: =IF(A14="","",SUM(E14:H14)) -> 0 | J14: =IF(A14="","",IFERROR(LOOKUP(2,1/(('2_Review & Audit'!$F$6:$F$505=A14)*('2_Review & Audit'!$Q$6:$Q$505<0)*('2_Review & Audit'!$M$6:$M$505<>"")),'2_Review & Audit'!$M$6:$M$505),"")) | K14: =IF(A14="","",IF(C14<>"Yes","",D14)) | L14: =IF(A14="","",COUNTIFS('4_Wash Match Table'!$A$7:$A$506,A14,'4_Wash Match Table'!$P$7:$P$506,">0")) -> 0
A15: =IF('6_Reference Lists'!A13="", "", '6_Reference Lists'!A13) -> VTI | B15: =IF(A15="","",SUMIFS('2_Review & Audit'!$R$6:$R$505,'2_Review & Audit'!$F$6:$F$505,A15)) -> 275.987 | C15: =IF(A15="","",IF(COUNTIFS('2_Review & Audit'!$F$6:$F$505,A15,'2_Review & Audit'!$U$6:$U$505,"Yes")>0,"Yes","No")) -> No | D15: =IF(A15="","",IF(C15<>"Yes","",IFERROR(LOOKUP(2,1/(('2_Review & Audit'!$F$6:$F$505=A15)*('2_Review & Audit'!$U$6:$U$505="Yes")),'2_Review & Audit'!$V$6:$V$505),""))) | E15: =IF(A15="","",SUMIFS('2_Review & Audit'!$Q$6:$Q$505,'2_Review & Audit'!$F$6:$F$505,A15,'2_Review & Audit'!$Y$6:$Y$505,"Short-Term",'2_Review & Audit'!$Q$6:$Q$505,">0")) -> 0 | F15: =IF(A15="","",SUMIFS('2_Review & Audit'!$Q$6:$Q$505,'2_Review & Audit'!$F$6:$F$505,A15,'2_Review & Audit'!$Y$6:$Y$505,"Short-Term",'2_Review & Audit'!$Q$6:$Q$505,"<0")) -> 0 | G15: =IF(A15="","",SUMIFS('2_Review & Audit'!$Q$6:$Q$505,'2_Review & Audit'!$F$6:$F$505,A15,'2_Review & Audit'!$Y$6:$Y$505,"Long-Term",'2_Review & Audit'!$Q$6:$Q$505,">0")) -> 0 | H15: =IF(A15="","",SUMIFS('2_Review & Audit'!$Q$6:$Q$505,'2_Review & Audit'!$F$6:$F$505,A15,'2_Review & Audit'!$Y$6:$Y$505,"Long-Term",'2_Review & Audit'!$Q$6:$Q$505,"<0")) -> 0 | I15: =IF(A15="","",SUM(E15:H15)) -> 0 | J15: =IF(A15="","",IFERROR(LOOKUP(2,1/(('2_Review & Audit'!$F$6:$F$505=A15)*('2_Review & Audit'!$Q$6:$Q$505<0)*('2_Review & Audit'!$M$6:$M$505<>"")),'2_Review & Audit'!$M$6:$M$505),"")) | K15: =IF(A15="","",IF(C15<>"Yes","",D15)) | L15: =IF(A15="","",COUNTIFS('4_Wash Match Table'!$A$7:$A$506,A15,'4_Wash Match Table'!$P$7:$P$506,">0")) -> 0
A16: =IF('6_Reference Lists'!A14="", "", '6_Reference Lists'!A14) -> VXUS | B16: =IF(A16="","",SUMIFS('2_Review & Audit'!$R$6:$R$505,'2_Review & Audit'!$F$6:$F$505,A16)) -> 356.162 | C16: =IF(A16="","",IF(COUNTIFS('2_Review & Audit'!$F$6:$F$505,A16,'2_Review & Audit'!$U$6:$U$505,"Yes")>0,"Yes","No")) -> No | D16: =IF(A16="","",IF(C16<>"Yes","",IFERROR(LOOKUP(2,1/(('2_Review & Audit'!$F$6:$F$505=A16)*('2_Review & Audit'!$U$6:$U$505="Yes")),'2_Review & Audit'!$V$6:$V$505),""))) | E16: =IF(A16="","",SUMIFS('2_Review & Audit'!$Q$6:$Q$505,'2_Review & Audit'!$F$6:$F$505,A16,'2_Review & Audit'!$Y$6:$Y$505,"Short-Term",'2_Review & Audit'!$Q$6:$Q$505,">0")) -> 0 | F16: =IF(A16="","",SUMIFS('2_Review & Audit'!$Q$6:$Q$505,'2_Review & Audit'!$F$6:$F$505,A16,'2_Review & Audit'!$Y$6:$Y$505,"Short-Term",'2_Review & Audit'!$Q$6:$Q$505,"<0")) -> 0 | G16: =IF(A16="","",SUMIFS('2_Review & Audit'!$Q$6:$Q$505,'2_Review & Audit'!$F$6:$F$505,A16,'2_Review & Audit'!$Y$6:$Y$505,"Long-Term",'2_Review & Audit'!$Q$6:$Q$505,">0")) -> 0 | H16: =IF(A16="","",SUMIFS('2_Review & Audit'!$Q$6:$Q$505,'2_Review & Audit'!$F$6:$F$505,A16,'2_Review & Audit'!$Y$6:$Y$505,"Long-Term",'2_Review & Audit'!$Q$6:$Q$505,"<0")) -> 0 | I16: =IF(A16="","",SUM(E16:H16)) -> 0 | J16: =IF(A16="","",IFERROR(LOOKUP(2,1/(('2_Review & Audit'!$F$6:$F$505=A16)*('2_Review & Audit'!$Q$6:$Q$505<0)*('2_Review & Audit'!$M$6:$M$505<>"")),'2_Review & Audit'!$M$6:$M$505),"")) | K16: =IF(A16="","",IF(C16<>"Yes","",D16)) | L16: =IF(A16="","",COUNTIFS('4_Wash Match Table'!$A$7:$A$506,A16,'4_Wash Match Table'!$P$7:$P$506,">0")) -> 0
C17: =IF(A17="","",IF(COUNTIFS('2_Review & Audit'!$F$6:$F$505,A17,'2_Review & Audit'!$U$6:$U$505,"Yes")>0,"Yes","No")) | D17: =IF(A17="","",IF(C17<>"Yes","",IFERROR(LOOKUP(2,1/(('2_Review & Audit'!$F$6:$F$505=A17)*('2_Review & Audit'!$U$6:$U$505="Yes")),'2_Review & Audit'!$V$6:$V$505),""))) | E17: =IF(A17="","",SUMIFS('2_Review & Audit'!$Q$6:$Q$505,'2_Review & Audit'!$F$6:$F$505,A17,'2_Review & Audit'!$Y$6:$Y$505,"Short-Term",'2_Review & Audit'!$Q$6:$Q$505,">0")) | F17: =IF(A17="","",SUMIFS('2_Review & Audit'!$Q$6:$Q$505,'2_Review & Audit'!$F$6:$F$505,A17,'2_Review & Audit'!$Y$6:$Y$505,"Short-Term",'2_Review & Audit'!$Q$6:$Q$505,"<0")) | G17: =IF(A17="","",SUMIFS('2_Review & Audit'!$Q$6:$Q$505,'2_Review & Audit'!$F$6:$F$505,A17,'2_Review & Audit'!$Y$6:$Y$505,"Long-Term",'2_Review & Audit'!$Q$6:$Q$505,">0")) | H17: =IF(A17="","",SUMIFS('2_Review & Audit'!$Q$6:$Q$505,'2_Review & Audit'!$F$6:$F$505,A17,'2_Review & Audit'!$Y$6:$Y$505,"Long-Term",'2_Review & Audit'!$Q$6:$Q$505,"<0")) | I17: =IF(A17="","",SUM(E17:H17)) | J17: =IF(A17="","",IFERROR(LOOKUP(2,1/(('2_Review & Audit'!$F$6:$F$505=A17)*('2_Review & Audit'!$Q$6:$Q$505<0)*('2_Review & Audit'!$M$6:$M$505<>"")),'2_Review & Audit'!$M$6:$M$505),"")) | K17: =IF(A17="","",IF(C17<>"Yes","",D17)) | L17: =IF(A17="","",COUNTIFS('4_Wash Match Table'!$A$7:$A$506,A17,'4_Wash Match Table'!$P$7:$P$506,">0"))
C18: =IF(A18="","",IF(COUNTIFS('2_Review & Audit'!$F$6:$F$505,A18,'2_Review & Audit'!$U$6:$U$505,"Yes")>0,"Yes","No")) | D18: =IF(A18="","",IF(C18<>"Yes","",IFERROR(LOOKUP(2,1/(('2_Review & Audit'!$F$6:$F$505=A18)*('2_Review & Audit'!$U$6:$U$505="Yes")),'2_Review & Audit'!$V$6:$V$505),""))) | E18: =IF(A18="","",SUMIFS('2_Review & Audit'!$Q$6:$Q$505,'2_Review & Audit'!$F$6:$F$505,A18,'2_Review & Audit'!$Y$6:$Y$505,"Short-Term",'2_Review & Audit'!$Q$6:$Q$505,">0")) | F18: =IF(A18="","",SUMIFS('2_Review & Audit'!$Q$6:$Q$505,'2_Review & Audit'!$F$6:$F$505,A18,'2_Review & Audit'!$Y$6:$Y$505,"Short-Term",'2_Review & Audit'!$Q$6:$Q$505,"<0")) | G18: =IF(A18="","",SUMIFS('2_Review & Audit'!$Q$6:$Q$505,'2_Review & Audit'!$F$6:$F$505,A18,'2_Review & Audit'!$Y$6:$Y$505,"Long-Term",'2_Review & Audit'!$Q$6:$Q$505,">0")) | H18: =IF(A18="","",SUMIFS('2_Review & Audit'!$Q$6:$Q$505,'2_Review & Audit'!$F$6:$F$505,A18,'2_Review & Audit'!$Y$6:$Y$505,"Long-Term",'2_Review & Audit'!$Q$6:$Q$505,"<0")) | I18: =IF(A18="","",SUM(E18:H18)) | J18: =IF(A18="","",IFERROR(LOOKUP(2,1/(('2_Review & Audit'!$F$6:$F$505=A18)*('2_Review & Audit'!$Q$6:$Q$505<0)*('2_Review & Audit'!$M$6:$M$505<>"")),'2_Review & Audit'!$M$6:$M$505),"")) | K18: =IF(A18="","",IF(C18<>"Yes","",D18)) | L18: =IF(A18="","",COUNTIFS('4_Wash Match Table'!$A$7:$A$506,A18,'4_Wash Match Table'!$P$7:$P$506,">0"))
A19: Transaction-Level Audit Detail
A20: Entry # | B20: Sleeve | C20: Asset Type | D20: Ticker | E20: Generated Lot ID | F20: Buy Date | G20: Sell Date | H20: Shares Bought | I20: Shares Sold | J20: Shares Remaining | K20: Total Cost | L20: Sale Proceeds | M20: Realized Gain / (Loss) | N20: Loss / Share | O20: Candidate Matched Shares | P20: Candidate Replacement Count | Q20: Wash Sale? | R20: Disallowed Wash Loss | S20: Basis Adj In | T20: Adjusted Total Basis | U20: Adjusted Cost / Share | V20: Wash Sale Window End Date | W20: Holding Period (Days) | X20: Tax Term
A21: =IF('2_Review & Audit'!A6="","",'2_Review & Audit'!A6) -> 1 | B21: =IF(A21="","",'2_Review & Audit'!C6) -> US | C21: =IF(A21="","",'2_Review & Audit'!D6) -> MLP | D21: =IF(A21="","",'2_Review & Audit'!F6) -> EPD | E21: =IF(A21="","",'2_Review & Audit'!H6) -> EPD-20240216-580D-27D25 | F21: =IF(A21="","",'2_Review & Audit'!I6) -> 45338 | G21: =IF(A21="","",'2_Review & Audit'!M6) -> 46090 | H21: =IF(A21="","",'2_Review & Audit'!J6) -> 580 | I21: =IF(A21="","",'2_Review & Audit'!N6) -> 580 | J21: =IF(A21="","",'2_Review & Audit'!R6) -> 0 | K21: =IF(A21="","",'2_Review & Audit'!L6) -> 15805 | L21: =IF(A21="","",'2_Review & Audit'!P6) -> 22127 | M21: =IF(A21="","",'2_Review & Audit'!Q6) -> 6322 | N21: =IF(OR(M21>=0,I21<=0),"",ABS(M21/I21)) | O21: =IF(OR(D21="",G21="",M21>=0),"",MIN(I21,SUMIFS('2_Review & Audit'!$J$6:$J$505,'2_Review & Audit'!$F$6:$F$505,D21,'2_Review & Audit'!$I$6:$I$505,">="&G21-30,'2_Review & Audit'!$I$6:$I$505,"<="&G21+30,'2_Review & Audit'!$A$6:$A$505,"<>"&A21))) | P21: =IF(OR(D21="",G21="",M21>=0),"",COUNTIFS('2_Review & Audit'!$F$6:$F$505,D21,'2_Review & Audit'!$I$6:$I$505,">="&G21-30,'2_Review & Audit'!$I$6:$I$505,"<="&G21+30,'2_Review & Audit'!$A$6:$A$505,"<>"&A21)) | Q21: =IF(A21="","",IF(AND(M21<0,P21>0),"Yes","No")) -> No | R21: =IF(TransactionAuditTable[[#This Row],[Ticker]]="","",IF(Q21<>"Yes",0,ABS(M21)*MIN(1,O21/I21))) -> 0 | S21: =IF(Q21<>"Yes","",R21) | T21: =IF(A21="","",K21+IF(S21="",0,S21)) -> 15805 | U21: =IF(OR(H21="",T21=""),"",T21/H21) -> 27.25 | V21: =IF(Q21<>"Yes","",G21+30) | W21: =IF(OR(F21="",G21=""),"",G21-F21) -> 752 | X21: =IF(OR(F21="",G21=""),"",IF(W21>365,"Long-Term","Short-Term")) -> Long-Term
A22: =IF('2_Review & Audit'!A7="","",'2_Review & Audit'!A7) -> 2 | B22: =IF(A22="","",'2_Review & Audit'!C7) -> US | C22: =IF(A22="","",'2_Review & Audit'!D7) -> MLP | D22: =IF(A22="","",'2_Review & Audit'!F7) -> EPD | E22: =IF(A22="","",'2_Review & Audit'!H7) -> EPD-20240216-615D-27D25 | F22: =IF(A22="","",'2_Review & Audit'!I7) -> 45338 | G22: =IF(A22="","",'2_Review & Audit'!M7) -> 46090 | H22: =IF(A22="","",'2_Review & Audit'!J7) -> 615 | I22: =IF(A22="","",'2_Review & Audit'!N7) -> 615 | J22: =IF(A22="","",'2_Review & Audit'!R7) -> 0 | K22: =IF(A22="","",'2_Review & Audit'!L7) -> 16758.75 | L22: =IF(A22="","",'2_Review & Audit'!P7) -> 23462.25 | M22: =IF(A22="","",'2_Review & Audit'!Q7) -> 6703.5 | N22: =IF(OR(M22>=0,I22<=0),"",ABS(M22/I22)) | O22: =IF(OR(D22="",G22="",M22>=0),"",MIN(I22,SUMIFS('2_Review & Audit'!$J$6:$J$505,'2_Review & Audit'!$F$6:$F$505,D22,'2_Review & Audit'!$I$6:$I$505,">="&G22-30,'2_Review & Audit'!$I$6:$I$505,"<="&G22+30,'2_Review & Audit'!$A$6:$A$505,"<>"&A22))) | P22: =IF(OR(D22="",G22="",M22>=0),"",COUNTIFS('2_Review & Audit'!$F$6:$F$505,D22,'2_Review & Audit'!$I$6:$I$505,">="&G22-30,'2_Review & Audit'!$I$6:$I$505,"<="&G22+30,'2_Review & Audit'!$A$6:$A$505,"<>"&A22)) | Q22: =IF(A22="","",IF(AND(M22<0,P22>0),"Yes","No")) -> No | R22: =IF(TransactionAuditTable[[#This Row],[Ticker]]="","",IF(Q22<>"Yes",0,ABS(M22)*MIN(1,O22/I22))) -> 0 | S22: =IF(Q22<>"Yes","",R22) | T22: =IF(A22="","",K22+IF(S22="",0,S22)) -> 16758.75 | U22: =IF(OR(H22="",T22=""),"",T22/H22) -> 27.25 | V22: =IF(Q22<>"Yes","",G22+30) | W22: =IF(OR(F22="",G22=""),"",G22-F22) -> 752 | X22: =IF(OR(F22="",G22=""),"",IF(W22>365,"Long-Term","Short-Term")) -> Long-Term
A23: =IF('2_Review & Audit'!A8="","",'2_Review & Audit'!A8) -> 3 | B23: =IF(A23="","",'2_Review & Audit'!C8) -> US | C23: =IF(A23="","",'2_Review & Audit'!D8) -> MLP | D23: =IF(A23="","",'2_Review & Audit'!F8) -> EPD | E23: =IF(A23="","",'2_Review & Audit'!H8) -> EPD-20250218-580D-33D72 | F23: =IF(A23="","",'2_Review & Audit'!I8) -> 45706 | G23: =IF(A23="","",'2_Review & Audit'!M8) -> 46090 | H23: =IF(A23="","",'2_Review & Audit'!J8) -> 580 | I23: =IF(A23="","",'2_Review & Audit'!N8) -> 580 | J23: =IF(A23="","",'2_Review & Audit'!R8) -> 0 | K23: =IF(A23="","",'2_Review & Audit'!L8) -> 19557.6 | L23: =IF(A23="","",'2_Review & Audit'!P8) -> 22127 | M23: =IF(A23="","",'2_Review & Audit'!Q8) -> 2569.4 | N23: =IF(OR(M23>=0,I23<=0),"",ABS(M23/I23)) | O23: =IF(OR(D23="",G23="",M23>=0),"",MIN(I23,SUMIFS('2_Review & Audit'!$J$6:$J$505,'2_Review & Audit'!$F$6:$F$505,D23,'2_Review & Audit'!$I$6:$I$505,">="&G23-30,'2_Review & Audit'!$I$6:$I$505,"<="&G23+30,'2_Review & Audit'!$A$6:$A$505,"<>"&A23))) | P23: =IF(OR(D23="",G23="",M23>=0),"",COUNTIFS('2_Review & Audit'!$F$6:$F$505,D23,'2_Review & Audit'!$I$6:$I$505,">="&G23-30,'2_Review & Audit'!$I$6:$I$505,"<="&G23+30,'2_Review & Audit'!$A$6:$A$505,"<>"&A23)) | Q23: =IF(A23="","",IF(AND(M23<0,P23>0),"Yes","No")) -> No | R23: =IF(TransactionAuditTable[[#This Row],[Ticker]]="","",IF(Q23<>"Yes",0,ABS(M23)*MIN(1,O23/I23))) -> 0 | S23: =IF(Q23<>"Yes","",R23) | T23: =IF(A23="","",K23+IF(S23="",0,S23)) -> 19557.6 | U23: =IF(OR(H23="",T23=""),"",T23/H23) -> 33.72 | V23: =IF(Q23<>"Yes","",G23+30) | W23: =IF(OR(F23="",G23=""),"",G23-F23) -> 384 | X23: =IF(OR(F23="",G23=""),"",IF(W23>365,"Long-Term","Short-Term")) -> Long-Term
A24: =IF('2_Review & Audit'!A9="","",'2_Review & Audit'!A9) -> 4 | B24: =IF(A24="","",'2_Review & Audit'!C9) -> US | C24: =IF(A24="","",'2_Review & Audit'!D9) -> MLP | D24: =IF(A24="","",'2_Review & Audit'!F9) -> EPD | E24: =IF(A24="","",'2_Review & Audit'!H9) -> EPD-20250218-30D-33D72 | F24: =IF(A24="","",'2_Review & Audit'!I9) -> 45706 | G24: =IF(A24="","",'2_Review & Audit'!M9) -> 46090 | H24: =IF(A24="","",'2_Review & Audit'!J9) -> 30 | I24: =IF(A24="","",'2_Review & Audit'!N9) -> 30 | J24: =IF(A24="","",'2_Review & Audit'!R9) -> 0 | K24: =IF(A24="","",'2_Review & Audit'!L9) -> 1011.6 | L24: =IF(A24="","",'2_Review & Audit'!P9) -> 1140 | M24: =IF(A24="","",'2_Review & Audit'!Q9) -> 128.4 | N24: =IF(OR(M24>=0,I24<=0),"",ABS(M24/I24)) | O24: =IF(OR(D24="",G24="",M24>=0),"",MIN(I24,SUMIFS('2_Review & Audit'!$J$6:$J$505,'2_Review & Audit'!$F$6:$F$505,D24,'2_Review & Audit'!$I$6:$I$505,">="&G24-30,'2_Review & Audit'!$I$6:$I$505,"<="&G24+30,'2_Review & Audit'!$A$6:$A$505,"<>"&A24))) | P24: =IF(OR(D24="",G24="",M24>=0),"",COUNTIFS('2_Review & Audit'!$F$6:$F$505,D24,'2_Review & Audit'!$I$6:$I$505,">="&G24-30,'2_Review & Audit'!$I$6:$I$505,"<="&G24+30,'2_Review & Audit'!$A$6:$A$505,"<>"&A24)) | Q24: =IF(A24="","",IF(AND(M24<0,P24>0),"Yes","No")) -> No | R24: =IF(TransactionAuditTable[[#This Row],[Ticker]]="","",IF(Q24<>"Yes",0,ABS(M24)*MIN(1,O24/I24))) -> 0 | S24: =IF(Q24<>"Yes","",R24) | T24: =IF(A24="","",K24+IF(S24="",0,S24)) -> 1011.6 | U24: =IF(OR(H24="",T24=""),"",T24/H24) -> 33.72 | V24: =IF(Q24<>"Yes","",G24+30) | W24: =IF(OR(F24="",G24=""),"",G24-F24) -> 384 | X24: =IF(OR(F24="",G24=""),"",IF(W24>365,"Long-Term","Short-Term")) -> Long-Term
A25: =IF('2_Review & Audit'!A10="","",'2_Review & Audit'!A10) -> 5 | B25: =IF(A25="","",'2_Review & Audit'!C10) -> US | C25: =IF(A25="","",'2_Review & Audit'!D10) -> MLP | D25: =IF(A25="","",'2_Review & Audit'!F10) -> EPD | E25: =IF(A25="","",'2_Review & Audit'!H10) -> EPD-20250218-585D-33D72 | F25: =IF(A25="","",'2_Review & Audit'!I10) -> 45706 | G25: =IF(A25="","",'2_Review & Audit'!M10) -> 46090 | H25: =IF(A25="","",'2_Review & Audit'!J10) -> 585 | I25: =IF(A25="","",'2_Review & Audit'!N10) -> 585 | J25: =IF(A25="","",'2_Review & Audit'!R10) -> 0 | K25: =IF(A25="","",'2_Review & Audit'!L10) -> 19726.2 | L25: =IF(A25="","",'2_Review & Audit'!P10) -> 22230 | M25: =IF(A25="","",'2_Review & Audit'!Q10) -> 2503.8 | N25: =IF(OR(M25>=0,I25<=0),"",ABS(M25/I25)) | O25: =IF(OR(D25="",G25="",M25>=0),"",MIN(I25,SUMIFS('2_Review & Audit'!$J$6:$J$505,'2_Review & Audit'!$F$6:$F$505,D25,'2_Review & Audit'!$I$6:$I$505,">="&G25-30,'2_Review & Audit'!$I$6:$I$505,"<="&G25+30,'2_Review & Audit'!$A$6:$A$505,"<>"&A25))) | P25: =IF(OR(D25="",G25="",M25>=0),"",COUNTIFS('2_Review & Audit'!$F$6:$F$505,D25,'2_Review & Audit'!$I$6:$I$505,">="&G25-30,'2_Review & Audit'!$I$6:$I$505,"<="&G25+30,'2_Review & Audit'!$A$6:$A$505,"<>"&A25)) | Q25: =IF(A25="","",IF(AND(M25<0,P25>0),"Yes","No")) -> No | R25: =IF(TransactionAuditTable[[#This Row],[Ticker]]="","",IF(Q25<>"Yes",0,ABS(M25)*MIN(1,O25/I25))) -> 0 | S25: =IF(Q25<>"Yes","",R25) | T25: =IF(A25="","",K25+IF(S25="",0,S25)) -> 19726.2 | U25: =IF(OR(H25="",T25=""),"",T25/H25) -> 33.72 | V25: =IF(Q25<>"Yes","",G25+30) | W25: =IF(OR(F25="",G25=""),"",G25-F25) -> 384 | X25: =IF(OR(F25="",G25=""),"",IF(W25>365,"Long-Term","Short-Term")) -> Long-Term
A26: =IF('2_Review & Audit'!A11="","",'2_Review & Audit'!A11) -> 6 | B26: =IF(A26="","",'2_Review & Audit'!C11) -> US | C26: =IF(A26="","",'2_Review & Audit'!D11) -> MLP | D26: =IF(A26="","",'2_Review & Audit'!F11) -> EPD | E26: =IF(A26="","",'2_Review & Audit'!H11) -> EPD-20250218-562D-33D72 | F26: =IF(A26="","",'2_Review & Audit'!I11) -> 45706 | G26: =IF(A26="","",'2_Review & Audit'!M11) -> 46090 | H26: =IF(A26="","",'2_Review & Audit'!J11) -> 562 | I26: =IF(A26="","",'2_Review & Audit'!N11) -> 562 | J26: =IF(A26="","",'2_Review & Audit'!R11) -> 0 | K26: =IF(A26="","",'2_Review & Audit'!L11) -> 18950.64 | L26: =IF(A26="","",'2_Review & Audit'!P11) -> 21356 | M26: =IF(A26="","",'2_Review & Audit'!Q11) -> 2405.36 | N26: =IF(OR(M26>=0,I26<=0),"",ABS(M26/I26)) | O26: =IF(OR(D26="",G26="",M26>=0),"",MIN(I26,SUMIFS('2_Review & Audit'!$J$6:$J$505,'2_Review & Audit'!$F$6:$F$505,D26,'2_Review & Audit'!$I$6:$I$505,">="&G26-30,'2_Review & Audit'!$I$6:$I$505,"<="&G26+30,'2_Review & Audit'!$A$6:$A$505,"<>"&A26))) | P26: =IF(OR(D26="",G26="",M26>=0),"",COUNTIFS('2_Review & Audit'!$F$6:$F$505,D26,'2_Review & Audit'!$I$6:$I$505,">="&G26-30,'2_Review & Audit'!$I$6:$I$505,"<="&G26+30,'2_Review & Audit'!$A$6:$A$505,"<>"&A26)) | Q26: =IF(A26="","",IF(AND(M26<0,P26>0),"Yes","No")) -> No | R26: =IF(TransactionAuditTable[[#This Row],[Ticker]]="","",IF(Q26<>"Yes",0,ABS(M26)*MIN(1,O26/I26))) -> 0 | S26: =IF(Q26<>"Yes","",R26) | T26: =IF(A26="","",K26+IF(S26="",0,S26)) -> 18950.64 | U26: =IF(OR(H26="",T26=""),"",T26/H26) -> 33.72 | V26: =IF(Q26<>"Yes","",G26+30) | W26: =IF(OR(F26="",G26=""),"",G26-F26) -> 384 | X26: =IF(OR(F26="",G26=""),"",IF(W26>365,"Long-Term","Short-Term")) -> Long-Term
A27: =IF('2_Review & Audit'!A12="","",'2_Review & Audit'!A12) -> 7 | B27: =IF(A27="","",'2_Review & Audit'!C12) -> US | C27: =IF(A27="","",'2_Review & Audit'!D12) -> MLP | D27: =IF(A27="","",'2_Review & Audit'!F12) -> EPD | E27: =IF(A27="","",'2_Review & Audit'!H12) -> EPD-20250218-580D-33D72 | F27: =IF(A27="","",'2_Review & Audit'!I12) -> 45706 | G27: =IF(A27="","",'2_Review & Audit'!M12) -> 46090 | H27: =IF(A27="","",'2_Review & Audit'!J12) -> 580 | I27: =IF(A27="","",'2_Review & Audit'!N12) -> 580 | J27: =IF(A27="","",'2_Review & Audit'!R12) -> 0 | K27: =IF(A27="","",'2_Review & Audit'!L12) -> 19557.6 | L27: =IF(A27="","",'2_Review & Audit'!P12) -> 22040 | M27: =IF(A27="","",'2_Review & Audit'!Q12) -> 2482.4 | N27: =IF(OR(M27>=0,I27<=0),"",ABS(M27/I27)) | O27: =IF(OR(D27="",G27="",M27>=0),"",MIN(I27,SUMIFS('2_Review & Audit'!$J$6:$J$505,'2_Review & Audit'!$F$6:$F$505,D27,'2_Review & Audit'!$I$6:$I$505,">="&G27-30,'2_Review & Audit'!$I$6:$I$505,"<="&G27+30,'2_Review & Audit'!$A$6:$A$505,"<>"&A27))) | P27: =IF(OR(D27="",G27="",M27>=0),"",COUNTIFS('2_Review & Audit'!$F$6:$F$505,D27,'2_Review & Audit'!$I$6:$I$505,">="&G27-30,'2_Review & Audit'!$I$6:$I$505,"<="&G27+30,'2_Review & Audit'!$A$6:$A$505,"<>"&A27)) | Q27: =IF(A27="","",IF(AND(M27<0,P27>0),"Yes","No")) -> No | R27: =IF(TransactionAuditTable[[#This Row],[Ticker]]="","",IF(Q27<>"Yes",0,ABS(M27)*MIN(1,O27/I27))) -> 0 | S27: =IF(Q27<>"Yes","",R27) | T27: =IF(A27="","",K27+IF(S27="",0,S27)) -> 19557.6 | U27: =IF(OR(H27="",T27=""),"",T27/H27) -> 33.72 | V27: =IF(Q27<>"Yes","",G27+30) | W27: =IF(OR(F27="",G27=""),"",G27-F27) -> 384 | X27: =IF(OR(F27="",G27=""),"",IF(W27>365,"Long-Term","Short-Term")) -> Long-Term
A28: =IF('2_Review & Audit'!A13="","",'2_Review & Audit'!A13) -> 8 | B28: =IF(A28="","",'2_Review & Audit'!C13) -> US | C28: =IF(A28="","",'2_Review & Audit'!D13) -> MLP | D28: =IF(A28="","",'2_Review & Audit'!F13) -> EPD | E28: =IF(A28="","",'2_Review & Audit'!H13) -> EPD-20240216-580D-27D25 | F28: =IF(A28="","",'2_Review & Audit'!I13) -> 45338 | G28: =IF(A28="","",'2_Review & Audit'!M13) -> 46098 | H28: =IF(A28="","",'2_Review & Audit'!J13) -> 580 | I28: =IF(A28="","",'2_Review & Audit'!N13) -> 580 | J28: =IF(A28="","",'2_Review & Audit'!R13) -> 0 | K28: =IF(A28="","",'2_Review & Audit'!L13) -> 15805 | L28: =IF(A28="","",'2_Review & Audit'!P13) -> 21918.2 | M28: =IF(A28="","",'2_Review & Audit'!Q13) -> 6113.2 | N28: =IF(OR(M28>=0,I28<=0),"",ABS(M28/I28)) | O28: =IF(OR(D28="",G28="",M28>=0),"",MIN(I28,SUMIFS('2_Review & Audit'!$J$6:$J$505,'2_Review & Audit'!$F$6:$F$505,D28,'2_Review & Audit'!$I$6:$I$505,">="&G28-30,'2_Review & Audit'!$I$6:$I$505,"<="&G28+30,'2_Review & Audit'!$A$6:$A$505,"<>"&A28))) | P28: =IF(OR(D28="",G28="",M28>=0),"",COUNTIFS('2_Review & Audit'!$F$6:$F$505,D28,'2_Review & Audit'!$I$6:$I$505,">="&G28-30,'2_Review & Audit'!$I$6:$I$505,"<="&G28+30,'2_Review & Audit'!$A$6:$A$505,"<>"&A28)) | Q28: =IF(A28="","",IF(AND(M28<0,P28>0),"Yes","No")) -> No | R28: =IF(TransactionAuditTable[[#This Row],[Ticker]]="","",IF(Q28<>"Yes",0,ABS(M28)*MIN(1,O28/I28))) -> 0 | S28: =IF(Q28<>"Yes","",R28) | T28: =IF(A28="","",K28+IF(S28="",0,S28)) -> 15805 | U28: =IF(OR(H28="",T28=""),"",T28/H28) -> 27.25 | V28: =IF(Q28<>"Yes","",G28+30) | W28: =IF(OR(F28="",G28=""),"",G28-F28) -> 760 | X28: =IF(OR(F28="",G28=""),"",IF(W28>365,"Long-Term","Short-Term")) -> Long-Term
A29: =IF('2_Review & Audit'!A14="","",'2_Review & Audit'!A14) -> 9 | B29: =IF(A29="","",'2_Review & Audit'!C14) -> US | C29: =IF(A29="","",'2_Review & Audit'!D14) -> MLP | D29: =IF(A29="","",'2_Review & Audit'!F14) -> EPD | E29: =IF(A29="","",'2_Review & Audit'!H14) -> EPD-20240216-351D-27D25 | F29: =IF(A29="","",'2_Review & Audit'!I14) -> 45338 | G29: =IF(A29="","",'2_Review & Audit'!M14) -> 46098 | H29: =IF(A29="","",'2_Review & Audit'!J14) -> 351 | I29: =IF(A29="","",'2_Review & Audit'!N14) -> 351 | J29: =IF(A29="","",'2_Review & Audit'!R14) -> 0 | K29: =IF(A29="","",'2_Review & Audit'!L14) -> 9564.75 | L29: =IF(A29="","",'2_Review & Audit'!P14) -> 13264.29 | M29: =IF(A29="","",'2_Review & Audit'!Q14) -> 3699.54 | N29: =IF(OR(M29>=0,I29<=0),"",ABS(M29/I29)) | O29: =IF(OR(D29="",G29="",M29>=0),"",MIN(I29,SUMIFS('2_Review & Audit'!$J$6:$J$505,'2_Review & Audit'!$F$6:$F$505,D29,'2_Review & Audit'!$I$6:$I$505,">="&G29-30,'2_Review & Audit'!$I$6:$I$505,"<="&G29+30,'2_Review & Audit'!$A$6:$A$505,"<>"&A29))) | P29: =IF(OR(D29="",G29="",M29>=0),"",COUNTIFS('2_Review & Audit'!$F$6:$F$505,D29,'2_Review & Audit'!$I$6:$I$505,">="&G29-30,'2_Review & Audit'!$I$6:$I$505,"<="&G29+30,'2_Review & Audit'!$A$6:$A$505,"<>"&A29)) | Q29: =IF(A29="","",IF(AND(M29<0,P29>0),"Yes","No")) -> No | R29: =IF(TransactionAuditTable[[#This Row],[Ticker]]="","",IF(Q29<>"Yes",0,ABS(M29)*MIN(1,O29/I29))) -> 0 | S29: =IF(Q29<>"Yes","",R29) | T29: =IF(A29="","",K29+IF(S29="",0,S29)) -> 9564.75 | U29: =IF(OR(H29="",T29=""),"",T29/H29) -> 27.25 | V29: =IF(Q29<>"Yes","",G29+30) | W29: =IF(OR(F29="",G29=""),"",G29-F29) -> 760 | X29: =IF(OR(F29="",G29=""),"",IF(W29>365,"Long-Term","Short-Term")) -> Long-Term
A30: =IF('2_Review & Audit'!A15="","",'2_Review & Audit'!A15) -> 10 | B30: =IF(A30="","",'2_Review & Audit'!C15) -> US | C30: =IF(A30="","",'2_Review & Audit'!D15) -> ETF | D30: =IF(A30="","",'2_Review & Audit'!F15) -> ITOT | E30: =IF(A30="","",'2_Review & Audit'!H15) -> ITOT-20260317-0D883-150D63 | F30: =IF(A30="","",'2_Review & Audit'!I15) -> 46098 | G30: =IF(A30="","",'2_Review & Audit'!M15) -> 46101 | H30: =IF(A30="","",'2_Review & Audit'!J15) -> 0.883 | I30: =IF(A30="","",'2_Review & Audit'!N15) -> 0.883 | J30: =IF(A30="","",'2_Review & Audit'!R15) -> 0 | K30: =IF(A30="","",'2_Review & Audit'!L15) -> 133.00629 | L30: =IF(A30="","",'2_Review & Audit'!P15) -> 126.20719 | M30: =IF(A30="","",'2_Review & Audit'!Q15) -> -6.7991 | N30: =IF(OR(M30>=0,I30<=0),"",ABS(M30/I30)) -> 7.7 | O30: =IF(OR(D30="",G30="",M30>=0),"",MIN(I30,SUMIFS('2_Review & Audit'!$J$6:$J$505,'2_Review & Audit'!$F$6:$F$505,D30,'2_Review & Audit'!$I$6:$I$505,">="&G30-30,'2_Review & Audit'!$I$6:$I$505,"<="&G30+30,'2_Review & Audit'!$A$6:$A$505,"<>"&A30))) -> 0.883 | P30: =IF(OR(D30="",G30="",M30>=0),"",COUNTIFS('2_Review & Audit'!$F$6:$F$505,D30,'2_Review & Audit'!$I$6:$I$505,">="&G30-30,'2_Review & Audit'!$I$6:$I$505,"<="&G30+30,'2_Review & Audit'!$A$6:$A$505,"<>"&A30)) -> 1 | Q30: =IF(A30="","",IF(AND(M30<0,P30>0),"Yes","No")) -> Yes | R30: =IF(TransactionAuditTable[[#This Row],[Ticker]]="","",IF(Q30<>"Yes",0,ABS(M30)*MIN(1,O30/I30))) -> 6.7991 | S30: =IF(Q30<>"Yes","",R30) -> 6.7991 | T30: =IF(A30="","",K30+IF(S30="",0,S30)) -> 139.80539 | U30: =IF(OR(H30="",T30=""),"",T30/H30) -> 158.33 | V30: =IF(Q30<>"Yes","",G30+30) -> 46131 | W30: =IF(OR(F30="",G30=""),"",G30-F30) -> 3 | X30: =IF(OR(F30="",G30=""),"",IF(W30>365,"Long-Term","Short-Term")) -> Short-Term
A31: =IF('2_Review & Audit'!A16="","",'2_Review & Audit'!A16) -> 11 | B31: =IF(A31="","",'2_Review & Audit'!C16) -> US | C31: =IF(A31="","",'2_Review & Audit'!D16) -> ETF | D31: =IF(A31="","",'2_Review & Audit'!F16) -> ITOT | E31: =IF(A31="","",'2_Review & Audit'!H16) -> ITOT-20260317-143D-146D76 | F31: =IF(A31="","",'2_Review & Audit'!I16) -> 46098 | G31: =IF(A31="","",'2_Review & Audit'!M16) -> 46101 | H31: =IF(A31="","",'2_Review & Audit'!J16) -> 143 | I31: =IF(A31="","",'2_Review & Audit'!N16) -> 143 | J31: =IF(A31="","",'2_Review & Audit'!R16) -> 0 | K31: =IF(A31="","",'2_Review & Audit'!L16) -> 20986.68 | L31: =IF(A31="","",'2_Review & Audit'!P16) -> 20438.99 | M31: =IF(A31="","",'2_Review & Audit'!Q16) -> -547.69 | N31: =IF(OR(M31>=0,I31<=0),"",ABS(M31/I31)) -> 3.83 | O31: =IF(OR(D31="",G31="",M31>=0),"",MIN(I31,SUMIFS('2_Review & Audit'!$J$6:$J$505,'2_Review & Audit'!$F$6:$F$505,D31,'2_Review & Audit'!$I$6:$I$505,">="&G31-30,'2_Review & Audit'!$I$6:$I$505,"<="&G31+30,'2_Review & Audit'!$A$6:$A$505,"<>"&A31))) -> 0.883 | P31: =IF(OR(D31="",G31="",M31>=0),"",COUNTIFS('2_Review & Audit'!$F$6:$F$505,D31,'2_Review & Audit'!$I$6:$I$505,">="&G31-30,'2_Review & Audit'!$I$6:$I$505,"<="&G31+30,'2_Review & Audit'!$A$6:$A$505,"<>"&A31)) -> 1 | Q31: =IF(A31="","",IF(AND(M31<0,P31>0),"Yes","No")) -> Yes | R31: =IF(TransactionAuditTable[[#This Row],[Ticker]]="","",IF(Q31<>"Yes",0,ABS(M31)*MIN(1,O31/I31))) -> 3.38189 | S31: =IF(Q31<>"Yes","",R31) -> 3.38189 | T31: =IF(A31="","",K31+IF(S31="",0,S31)) -> 20990.062 | U31: =IF(OR(H31="",T31=""),"",T31/H31) -> 146.78365 | V31: =IF(Q31<>"Yes","",G31+30) -> 46131 | W31: =IF(OR(F31="",G31=""),"",G31-F31) -> 3 | X31: =IF(OR(F31="",G31=""),"",IF(W31>365,"Long-Term","Short-Term")) -> Short-Term
A32: =IF('2_Review & Audit'!A17="","",'2_Review & Audit'!A17) -> 12 | B32: =IF(A32="","",'2_Review & Audit'!C17) -> US | C32: =IF(A32="","",'2_Review & Audit'!D17) -> ETF | D32: =IF(A32="","",'2_Review & Audit'!F17) -> SCHB | E32: =IF(A32="","",'2_Review & Audit'!H17) -> SCHB-20260317-0D872-25D952 | F32: =IF(A32="","",'2_Review & Audit'!I17) -> 46098 | G32: =IF(A32="","",'2_Review & Audit'!M17) -> 46108 | H32: =IF(A32="","",'2_Review & Audit'!J17) -> 0.872 | I32: =IF(A32="","",'2_Review & Audit'!N17) -> 0.872 | J32: =IF(A32="","",'2_Review & Audit'!R17) -> 0 | K32: =IF(A32="","",'2_Review & Audit'!L17) -> 22.63 | L32: =IF(A32="","",'2_Review & Audit'!P17) -> 21.46 | M32: =IF(A32="","",'2_Review & Audit'!Q17) -> -1.17 | N32: =IF(OR(M32>=0,I32<=0),"",ABS(M32/I32)) -> 1.3417431 | O32: =IF(OR(D32="",G32="",M32>=0),"",MIN(I32,SUMIFS('2_Review & Audit'!$J$6:$J$505,'2_Review & Audit'!$F$6:$F$505,D32,'2_Review & Audit'!$I$6:$I$505,">="&G32-30,'2_Review & Audit'!$I$6:$I$505,"<="&G32+30,'2_Review & Audit'!$A$6:$A$505,"<>"&A32))) -> 0.872 | P32: =IF(OR(D32="",G32="",M32>=0),"",COUNTIFS('2_Review & Audit'!$F$6:$F$505,D32,'2_Review & Audit'!$I$6:$I$505,">="&G32-30,'2_Review & Audit'!$I$6:$I$505,"<="&G32+30,'2_Review & Audit'!$A$6:$A$505,"<>"&A32)) -> 4 | Q32: =IF(A32="","",IF(AND(M32<0,P32>0),"Yes","No")) -> Yes | R32: =IF(TransactionAuditTable[[#This Row],[Ticker]]="","",IF(Q32<>"Yes",0,ABS(M32)*MIN(1,O32/I32))) -> 1.17 | S32: =IF(Q32<>"Yes","",R32) -> 1.17 | T32: =IF(A32="","",K32+IF(S32="",0,S32)) -> 23.8 | U32: =IF(OR(H32="",T32=""),"",T32/H32) -> 27.293578 | V32: =IF(Q32<>"Yes","",G32+30) -> 46138 | W32: =IF(OR(F32="",G32=""),"",G32-F32) -> 10 | X32: =IF(OR(F32="",G32=""),"",IF(W32>365,"Long-Term","Short-Term")) -> Short-Term
... A520: =IF('2_Review & Audit'!A505="","",'2_Review & Audit'!A505) | B520: =IF(A520="","",'2_Review & Audit'!C505) | C520: =IF(A520="","",'2_Review & Audit'!D505) | D520: =IF(A520="","",'2_Review & Audit'!F505) | E520: =IF(A520="","",'2_Review & Audit'!H505) | F520: =IF(A520="","",'2_Review & Audit'!I505) | G520: =IF(A520="","",'2_Review & Audit'!M505) | H520: =IF(A520="","",'2_Review & Audit'!J505) | I520: =IF(A520="","",'2_Review & Audit'!N505) | J520: =IF(A520="","",'2_Review & Audit'!R505) | K520: =IF(A520="","",'2_Review & Audit'!L505) | L520: =IF(A520="","",'2_Review & Audit'!P505) | M520: =IF(A520="","",'2_Review & Audit'!Q505) | N520: =IF(OR(M520>=0,I520<=0),"",ABS(M520/I520)) | O520: =IF(OR(D520="",G520="",M520>=0),"",MIN(I520,SUMIFS('2_Review & Audit'!$J$6:$J$505,'2_Review & Audit'!$F$6:$F$505,D520,'2_Review & Audit'!$I$6:$I$505,">="&G520-30,'2_Review & Audit'!$I$6:$I$505,"<="&G520+30,'2_Review & Audit'!$A$6:$A$505,"<>"&A520))) | P520: =IF(OR(D520="",G520="",M520>=0),"",COUNTIFS('2_Review & Audit'!$F$6:$F$505,D520,'2_Review & Audit'!$I$6:$I$505,">="&G520-30,'2_Review & Audit'!$I$6:$I$505,"<="&G520+30,'2_Review & Audit'!$A$6:$A$505,"<>"&A520)) | Q520: =IF(A520="","",IF(AND(M520<0,P520>0),"Yes","No")) | R520: =IF(TransactionAuditTable[[#This Row],[Ticker]]="","",IF(Q520<>"Yes",0,ABS(M520)*MIN(1,O520/I520))) | S520: =IF(Q520<>"Yes","",R520) | T520: =IF(A520="","",K520+IF(S520="",0,S520)) | U520: =IF(OR(H520="",T520=""),"",T520/H520) | V520: =IF(Q520<>"Yes","",G520+30) | W520: =IF(OR(F520="",G520=""),"",G520-F520) | X520: =IF(OR(F520="",G520=""),"",IF(W520>365,"Long-Term","Short-Term"))

Sheet 4_Wash Match Table
A1: 4_Wash Match Table | T1: Total Basis Adjustments | V1: =SUM($R$7:$R$506) -> 67.478297
A2: Each row is one wash-sale match segment. Default logic = same-ticker FIFO within ±30 days across all accounts. Multi-lot matching enabled with up to 6 replacement segments per loss sale. Manual override only changes replacement-lot selection. | T2: Loss Rows | V2: {=SUMPRODUCT(--(LEN(TRIM($A$7:$A$506&""))>0))} -> 5
T3: Total Disallowed Loss | V3: =SUM($P$7:$P$506,$Y$7:$Y$506,$AH$7:$AH$506,$AQ$7:$AQ$506) -> 242.93992
T4: Total Allowed Loss | V4: =SUM($Q$7:$Q$506) -> 855.54008
L5: REPLACEMENT SHARES
A6: Ticker | B6: Sleeve | C6: Asset Type | D6: Sold Lot ID | E6: Sell Date | F6: Shares Sold | G6: Loss / Share | H6: Total Loss | I6: Tax Term | J6: Loss Review Row | K6: Effective Buy Row | L6: Slot 1 Lot ID | M6: Slot 1 Buy Date | N6: Slot 1 Shares Available | O6: Slot 1 Matched Shares | P6: Slot 1 Disallowed Loss | Q6: Slot 1 Allowed Loss | R6: Slot 1 Basis Adj. | S6: Slot 1 Remaining Shares | T6: Slot 2 Row Ptr | U6: Slot 2 Lot ID | V6: Slot 2 Buy Date | W6: Slot 2 Shares Available | X6: Slot 2 Matched Shares | Y6: Slot 2 Disallowed Loss | Z6: Slot 2 Allowed Loss | AA6: Slot 2 Basis Adj. | AB6: Slot 2 Remaining Shares | AC6: Slot 3 Row Ptr | AD6: Slot 3 Lot ID | AE6: Slot 3 Buy Date | AF6: Slot 3 Shares Available | AG6: Slot 3 Matched Shares | AH6: Slot 3 Disallowed Loss | AI6: Slot 3 Allowed Loss | AJ6: Slot 3 Basis Adj. | AK6: Slot 3 Remaining Shares | AL6: Slot 4 Row Ptr | AM6: Slot 4 Lot ID | AN6: Slot 4 Buy Date | AO6: Slot 4 Shares Available | AP6: Slot 4 Matched Shares | AQ6: Slot 4 Disallowed Loss | AR6: Slot 4 Allowed Loss | AS6: Slot 4 Basis Adj. | AT6: Slot 4 Shares Remaining | AU6: DO NOT DELETE
A7: =IFERROR(INDEX('2_Review & Audit'!$F$6:$F$505,MATCH(ROW()-5,'2_Review & Audit'!$AC$6:$AC$505,0)),"") -> ITOT | B7: =IF($A7="","",INDEX('2_Review & Audit'!$C$6:$C$505,MATCH(ROW()-5,'2_Review & Audit'!$AC$6:$AC$505,0))) -> US | C7: =IF($A7="","",INDEX('2_Review & Audit'!$D$6:$D$505,MATCH(ROW()-5,'2_Review & Audit'!$AC$6:$AC$505,0))) -> ETF | D7: =IF($A7="","",INDEX('2_Review & Audit'!$H$6:$H$505,MATCH(ROW()-5,'2_Review & Audit'!$AC$6:$AC$505,0))) -> ITOT-20260317-143D-146D76 | E7: =IF($A7="","",INDEX('2_Review & Audit'!$M$6:$M$505,MATCH(ROW()-5,'2_Review & Audit'!$AC$6:$AC$505,0))) -> 46101 | F7: =IF($A7="","",IF(INDEX('2_Review & Audit'!$N$6:$N$505,MATCH(ROW()-5,'2_Review & Audit'!$AC$6:$AC$505,0))="",INDEX('2_Review & Audit'!$J$6:$J$505,MATCH(ROW()-5,'2_Review & Audit'!$AC$6:$AC$505,0))-INDEX('2_Review & Audit'!$R$6:$R$505,MATCH(ROW()-5,'2_Review & Audit'!$AC$6:$AC$505,0)),INDEX('2_Review & Audit'!$N$6:$N$505,MATCH(ROW()-5,'2_Review & Audit'!$AC$6:$AC$505,0)))) -> 143 | G7: =IF(OR($A7="",$F7=0),"",ABS(INDEX('2_Review & Audit'!$Q$6:$Q$505,MATCH(ROW()-5,'2_Review & Audit'!$AC$6:$AC$505,0))/$F7)) -> 3.83 | H7: =IF($A7="","",ABS(INDEX('2_Review & Audit'!$Q$6:$Q$505,MATCH(ROW()-5,'2_Review & Audit'!$AC$6:$AC$505,0)))) -> 547.69 | I7: =IF($A7="","",INDEX('2_Review & Audit'!$Y$6:$Y$505,MATCH(ROW()-5,'2_Review & Audit'!$AC$6:$AC$505,0))) -> Short-Term | J7: =IF($A7="","",IFERROR(MATCH(ROW()-5,'2_Review & Audit'!$AC$6:$AC$505,0)+5,"")) -> 16 | K7: {=IF($A7="","",IF($AU7<>"",IFERROR(MATCH($AU7,'2_Review & Audit'!$H$6:$H$505,0)+5,""),IFERROR(MATCH(1,INDEX(('2_Review & Audit'!$F$6:$F$505=$A7)*('2_Review & Audit'!$I$6:$I$505>=$E7-30)*('2_Review & Audit'!$I$6:$I$505<=$E7+30)*('2_Review & Audit'!$R$6:$R$505>0),0),0)+5,"")))} | L7: {=IF($K7="","",INDEX('2_Review & Audit'!$H:$H,$K7))} | M7: {=IF($K7="","",INDEX('2_Review & Audit'!$I:$I,$K7))} | N7: {=IF($K7="","",MAX(0,INDEX('2_Review & Audit'!$R:$R,$K7)-SUMIFS($O6:O$7,$K6:K$7,$K7)))} | O7: =IF(OR($K7="",$N7="",$F7=""),"",MIN($F7,$N7)) | P7: =IF($O7="","",$O7*$G7) | Q7: =IF($M7="","",$H7-IF($P7="",0,$P7)-IF($Y7="",0,$Y7)-IF($AH7="",0,$AH7)-IF($AQ7="",0,$AQ7)) | R7: =IF($M7="","",IF($P7="",0,$P7)) | S7: =IF($M7="","",MAX(0,N($F7)-N($O7))) | T7: {=IF(OR($D7="",$S7="",N($S7)<=0),"",IFERROR(MATCH(1,INDEX(('2_Review & Audit'!$F$6:$F$505=$A7)*('2_Review & Audit'!$I$6:$I$505>=$E7-30)*('2_Review & Audit'!$I$6:$I$505<=$E7+30)*('2_Review & Audit'!$R$6:$R$505>0)*(ROW('2_Review & Audit'!$R$6:$R$505)>$K7),0),0)+5,""))} | U7: {=IF($T7="","",INDEX('2_Review & Audit'!$H:$H,$T7))} | V7: {=IF($T7="","",INDEX('2_Review & Audit'!$I:$I,$T7))} | W7: {=IF($T7="","",MAX(0,INDEX('2_Review & Audit'!$J:$J,$T7)-SUMIFS($X6:X$7,$T6:T$7,$T7)))} | X7: =IF(OR($T7="",$W7="",$S7=""),"",MIN($S7,$W7)) | Y7: =IF($X7="","",$X7*$G7) | Z7: =IF($T7="","",$H7-IF($P7="",0,$P7)-IF($Y7="",0,$Y7)) | AA7: =IF($Y7="","",$Y7) | AB7: =IF($T7="","",MAX(0,N($S7)-N($X7))) | AC7: {=IF(OR($D7="",$AB7="",N($AB7)<=0),"",IFERROR(MATCH(1,INDEX(('2_Review & Audit'!$F$6:$F$505=$A7)*('2_Review & Audit'!$I$6:$I$505>=$E7-30)*('2_Review & Audit'!$I$6:$I$505<=$E7+30)*('2_Review & Audit'!$R$6:$R$505>0)*(ROW('2_Review & Audit'!$R$6:$R$505)>$T7),0),0)+5,""))} | AD7: {=IF($AC7="","",INDEX('2_Review & Audit'!$H:$H,$AC7))} | AE7: {=IF($AC7="","",INDEX('2_Review & Audit'!$I:$I,$AC7))} | AF7: {=IF($AC7="","",MAX(0,INDEX('2_Review & Audit'!$J:$J,$AC7)-SUMIFS($AG6:AG$7,$AC6:AC$7,$AC7)))} | AG7: =IF(OR($AC7="",$AF7="",$AB7=""),"",MIN($AB7,$AF7)) | AH7: =IF($AG7="","",$AG7*$G7) | AI7: =IF($AC7="","",$H7-IF($P7="",0,$P7)-IF($Y7="",0,$Y7)-IF($AH7="",0,$AH7)) | AJ7: =IF($AH7="","",$AH7) | AK7: =IF($AC7="","",MAX(0,N($AB7)-N($AG7))) | AL7: {=IF(OR($D7="",$AK7="",N($AK7)<=0),"",IFERROR(MATCH(1,INDEX(('2_Review & Audit'!$F$6:$F$505=$A7)*('2_Review & Audit'!$I$6:$I$505>=$E7-30)*('2_Review & Audit'!$I$6:$I$505<=$E7+30)*('2_Review & Audit'!$R$6:$R$505>0)*(ROW('2_Review & Audit'!$R$6:$R$505)>$AC7),0),0)+5,""))} | AM7: =IF($AL7="","",INDEX('2_Review & Audit'!$H:$H,$AL7)) | AN7: =IF($AL7="","",INDEX('2_Review & Audit'!$I:$I,$AL7)) | AO7: =IF($AL7="","",MAX(0,INDEX('2_Review & Audit'!$H:$H,$AL7)-SUMIFS($AP6:AP$7,$AL6:AL$7,$AL7))) | AP7: =IF(OR($D7="",$AK7="",$AO7=""),"",MIN($AK7,$AO7)) | AQ7: =IF($AP7="","",$AP7*$G7) | AR7: =IF($AL7="","",$H7-IF($P7="",0,$P7)-IF($Y7="",0,$Y7)-IF($AH7="",0,$AH7)-IF($AQ7="",0,$AQ7)) | AS7: =IF($AQ7="","",$AQ7) | AT7: =IF($AL7="","",IF(ABS(N($AK7)-N($AP7))<0.000001,0,MAX(0,N($AK7)-N($AP7))))
A8: =IFERROR(INDEX('2_Review & Audit'!$F$6:$F$505,MATCH(ROW()-5,'2_Review & Audit'!$AC$6:$AC$505,0)),"") -> SCHB | B8: =IF($A8="","",INDEX('2_Review & Audit'!$C$6:$C$505,MATCH(ROW()-5,'2_Review & Audit'!$AC$6:$AC$505,0))) -> US | C8: =IF($A8="","",INDEX('2_Review & Audit'!$D$6:$D$505,MATCH(ROW()-5,'2_Review & Audit'!$AC$6:$AC$505,0))) -> ETF | D8: =IF($A8="","",INDEX('2_Review & Audit'!$H$6:$H$505,MATCH(ROW()-5,'2_Review & Audit'!$AC$6:$AC$505,0))) -> SCHB-20260317-0D872-25D952 | E8: =IF($A8="","",INDEX('2_Review & Audit'!$M$6:$M$505,MATCH(ROW()-5,'2_Review & Audit'!$AC$6:$AC$505,0))) -> 46108 | F8: =IF($A8="","",IF(INDEX('2_Review & Audit'!$N$6:$N$505,MATCH(ROW()-5,'2_Review & Audit'!$AC$6:$AC$505,0))="",INDEX('2_Review & Audit'!$J$6:$J$505,MATCH(ROW()-5,'2_Review & Audit'!$AC$6:$AC$505,0))-INDEX('2_Review & Audit'!$R$6:$R$505,MATCH(ROW()-5,'2_Review & Audit'!$AC$6:$AC$505,0)),INDEX('2_Review & Audit'!$N$6:$N$505,MATCH(ROW()-5,'2_Review & Audit'!$AC$6:$AC$505,0)))) -> 0.872 | G8: =IF(OR($A8="",$F8=0),"",ABS(INDEX('2_Review & Audit'!$Q$6:$Q$505,MATCH(ROW()-5,'2_Review & Audit'!$AC$6:$AC$505,0))/$F8)) -> 1.3417431 | H8: =IF($A8="","",ABS(INDEX('2_Review & Audit'!$Q$6:$Q$505,MATCH(ROW()-5,'2_Review & Audit'!$AC$6:$AC$505,0)))) -> 1.17 | I8: =IF($A8="","",INDEX('2_Review & Audit'!$Y$6:$Y$505,MATCH(ROW()-5,'2_Review & Audit'!$AC$6:$AC$505,0))) -> Short-Term | J8: =IF($A8="","",IFERROR(MATCH(ROW()-5,'2_Review & Audit'!$AC$6:$AC$505,0)+5,"")) -> 17 | K8: {=IF($A8="","",IF($AU8<>"",IFERROR(MATCH($AU8,'2_Review & Audit'!$H$6:$H$505,0)+5,""),IFERROR(MATCH(1,INDEX(('2_Review & Audit'!$F$6:$F$505=$A8)*('2_Review & Audit'!$I$6:$I$505>=$E8-30)*('2_Review & Audit'!$I$6:$I$505<=$E8+30)*('2_Review & Audit'!$R$6:$R$505>0),0),0)+5,"")))} -> 35 | L8: {=IF($K8="","",INDEX('2_Review & Audit'!$H:$H,$K8))} -> SCHB-20260330-50D-20D | M8: {=IF($K8="","",INDEX('2_Review & Audit'!$I:$I,$K8))} -> 46111 | N8: {=IF($K8="","",MAX(0,INDEX('2_Review & Audit'!$R:$R,$K8)-SUMIFS($O7:O$7,$K7:K$7,$K8)))} -> 50 | O8: =IF(OR($K8="",$N8="",$F8=""),"",MIN($F8,$N8)) -> 0.872 | P8: =IF($O8="","",$O8*$G8) -> 1.17 | Q8: =IF($M8="","",$H8-IF($P8="",0,$P8)-IF($Y8="",0,$Y8)-IF($AH8="",0,$AH8)-IF($AQ8="",0,$AQ8)) -> 0 | R8: =IF($M8="","",IF($P8="",0,$P8)) -> 1.17 | S8: =IF($M8="","",MAX(0,N($F8)-N($O8))) -> 0 | T8: {=IF(OR($D8="",$S8="",N($S8)<=0),"",IFERROR(MATCH(1,INDEX(('2_Review & Audit'!$F$6:$F$505=$A8)*('2_Review & Audit'!$I$6:$I$505>=$E8-30)*('2_Review & Audit'!$I$6:$I$505<=$E8+30)*('2_Review & Audit'!$R$6:$R$505>0)*(ROW('2_Review & Audit'!$R$6:$R$505)>$K8),0),0)+5,""))} | U8: {=IF($T8="","",INDEX('2_Review & Audit'!$H:$H,$T8))} | V8: {=IF($T8="","",INDEX('2_Review & Audit'!$I:$I,$T8))} | W8: {=IF($T8="","",MAX(0,INDEX('2_Review & Audit'!$J:$J,$T8)-SUMIFS($X7:X$7,$T7:T$7,$T8)))} | X8: =IF(OR($T8="",$W8="",$S8=""),"",MIN($S8,$W8)) | Y8: =IF($X8="","",$X8*$G8) | Z8: =IF($T8="","",$H8-IF($P8="",0,$P8)-IF($Y8="",0,$Y8)) | AA8: =IF($Y8="","",$Y8) | AB8: =IF($T8="","",MAX(0,N($S8)-N($X8))) | AC8: {=IF(OR($D8="",$AB8="",N($AB8)<=0),"",IFERROR(MATCH(1,INDEX(('2_Review & Audit'!$F$6:$F$505=$A8)*('2_Review & Audit'!$I$6:$I$505>=$E8-30)*('2_Review & Audit'!$I$6:$I$505<=$E8+30)*('2_Review & Audit'!$R$6:$R$505>0)*(ROW('2_Review & Audit'!$R$6:$R$505)>$T8),0),0)+5,""))} | AD8: {=IF($AC8="","",INDEX('2_Review & Audit'!$H:$H,$AC8))} | AE8: {=IF($AC8="","",INDEX('2_Review & Audit'!$I:$I,$AC8))} | AF8: {=IF($AC8="","",MAX(0,INDEX('2_Review & Audit'!$J:$J,$AC8)-SUMIFS($AG7:AG$7,$AC7:AC$7,$AC8)))} | AG8: =IF(OR($AC8="",$AF8="",$AB8=""),"",MIN($AB8,$AF8)) | AH8: =IF($AG8="","",$AG8*$G8) | AI8: =IF($AC8="","",$H8-IF($P8="",0,$P8)-IF($Y8="",0,$Y8)-IF($AH8="",0,$AH8)) | AJ8: =IF($AH8="","",$AH8) | AK8: =IF($AC8="","",MAX(0,N($AB8)-N($AG8))) | AL8: {=IF(OR($D8="",$AK8="",N($AK8)<=0),"",IFERROR(MATCH(1,INDEX(('2_Review & Audit'!$F$6:$F$505=$A8)*('2_Review & Audit'!$I$6:$I$505>=$E8-30)*('2_Review & Audit'!$I$6:$I$505<=$E8+30)*('2_Review & Audit'!$R$6:$R$505>0)*(ROW('2_Review & Audit'!$R$6:$R$505)>$AC8),0),0)+5,""))} | AM8: =IF($AL8="","",INDEX('2_Review & Audit'!$H:$H,$AL8)) | AN8: =IF($AL8="","",INDEX('2_Review & Audit'!$I:$I,$AL8)) | AO8: =IF($AL8="","",MAX(0,INDEX('2_Review & Audit'!$H:$H,$AL8)-SUMIFS($AP7:AP$7,$AL7:AL$7,$AL8))) | AP8: =IF(OR($D8="",$AK8="",$AO8=""),"",MIN($AK8,$AO8)) | AQ8: =IF($AP8="","",$AP8*$G8) | AR8: =IF($AL8="","",$H8-IF($P8="",0,$P8)-IF($Y8="",0,$Y8)-IF($AH8="",0,$AH8)-IF($AQ8="",0,$AQ8)) | AS8: =IF($AQ8="","",$AQ8) | AT8: =IF($AL8="","",IF(ABS(N($AK8)-N($AP8))<0.000001,0,MAX(0,N($AK8)-N($AP8))))
A9: =IFERROR(INDEX('2_Review & Audit'!$F$6:$F$505,MATCH(ROW()-5,'2_Review & Audit'!$AC$6:$AC$505,0)),"") -> SCHB | B9: =IF($A9="","",INDEX('2_Review & Audit'!$C$6:$C$505,MATCH(ROW()-5,'2_Review & Audit'!$AC$6:$AC$505,0))) -> US | C9: =IF($A9="","",INDEX('2_Review & Audit'!$D$6:$D$505,MATCH(ROW()-5,'2_Review & Audit'!$AC$6:$AC$505,0))) -> ETF | D9: =IF($A9="","",INDEX('2_Review & Audit'!$H$6:$H$505,MATCH(ROW()-5,'2_Review & Audit'!$AC$6:$AC$505,0))) -> SCHB-20260317-813D-25D95 | E9: =IF($A9="","",INDEX('2_Review & Audit'!$M$6:$M$505,MATCH(ROW()-5,'2_Review & Audit'!$AC$6:$AC$505,0))) -> 46108 | F9: =IF($A9="","",IF(INDEX('2_Review & Audit'!$N$6:$N$505,MATCH(ROW()-5,'2_Review & Audit'!$AC$6:$AC$505,0))="",INDEX('2_Review & Audit'!$J$6:$J$505,MATCH(ROW()-5,'2_Review & Audit'!$AC$6:$AC$505,0))-INDEX('2_Review & Audit'!$R$6:$R$505,MATCH(ROW()-5,'2_Review & Audit'!$AC$6:$AC$505,0)),INDEX('2_Review & Audit'!$N$6:$N$505,MATCH(ROW()-5,'2_Review & Audit'!$AC$6:$AC$505,0)))) -> 813 | G9: =IF(OR($A9="",$F9=0),"",ABS(INDEX('2_Review & Audit'!$Q$6:$Q$505,MATCH(ROW()-5,'2_Review & Audit'!$AC$6:$AC$505,0))/$F9)) -> 1.3497048 | H9: =IF($A9="","",ABS(INDEX('2_Review & Audit'!$Q$6:$Q$505,MATCH(ROW()-5,'2_Review & Audit'!$AC$6:$AC$505,0)))) -> 1097.31 | I9: =IF($A9="","",INDEX('2_Review & Audit'!$Y$6:$Y$505,MATCH(ROW()-5,'2_Review & Audit'!$AC$6:$AC$505,0))) -> Short-Term | J9: =IF($A9="","",IFERROR(MATCH(ROW()-5,'2_Review & Audit'!$AC$6:$AC$505,0)+5,"")) -> 18 | K9: {=IF($A9="","",IF($AU9<>"",IFERROR(MATCH($AU9,'2_Review & Audit'!$H$6:$H$505,0)+5,""),IFERROR(MATCH(1,INDEX(('2_Review & Audit'!$F$6:$F$505=$A9)*('2_Review & Audit'!$I$6:$I$505>=$E9-30)*('2_Review & Audit'!$I$6:$I$505<=$E9+30)*('2_Review & Audit'!$R$6:$R$505>0),0),0)+5,"")))} -> 35 | L9: {=IF($K9="","",INDEX('2_Review & Audit'!$H:$H,$K9))} -> SCHB-20260330-50D-20D | M9: {=IF($K9="","",INDEX('2_Review & Audit'!$I:$I,$K9))} -> 46111 | N9: {=IF($K9="","",MAX(0,INDEX('2_Review & Audit'!$R:$R,$K9)-SUMIFS($O$7:O8,$K$7:K8,$K9)))} -> 49.128 | O9: =IF(OR($K9="",$N9="",$F9=""),"",MIN($F9,$N9)) -> 49.128 | P9: =IF($O9="","",$O9*$G9) -> 66.308297 | Q9: =IF($M9="","",$H9-IF($P9="",0,$P9)-IF($Y9="",0,$Y9)-IF($AH9="",0,$AH9)-IF($AQ9="",0,$AQ9)) -> 855.54008 | R9: =IF($M9="","",IF($P9="",0,$P9)) -> 66.308297 | S9: =IF($M9="","",MAX(0,N($F9)-N($O9))) -> 763.872 | T9: {=IF(OR($D9="",$S9="",N($S9)<=0),"",IFERROR(MATCH(1,INDEX(('2_Review & Audit'!$F$6:$F$505=$A9)*('2_Review & Audit'!$I$6:$I$505>=$E9-30)*('2_Review & Audit'!$I$6:$I$505<=$E9+30)*('2_Review & Audit'!$R$6:$R$505>0)*(ROW('2_Review & Audit'!$R$6:$R$505)>$K9),0),0)+5,""))} -> 36 | U9: {=IF($T9="","",INDEX('2_Review & Audit'!$H:$H,$T9))} -> SCHB-20260331-60D-22D | V9: {=IF($T9="","",INDEX('2_Review & Audit'!$I:$I,$T9))} -> 46112 | W9: {=IF($T9="","",MAX(0,INDEX('2_Review & Audit'!$J:$J,$T9)-SUMIFS($X$7:X8,$T$7:T8,$T9)))} -> 60 | X9: =IF(OR($T9="",$W9="",$S9=""),"",MIN($S9,$W9)) -> 60 | Y9: =IF($X9="","",$X9*$G9) -> 80.982288 | Z9: =IF($T9="","",$H9-IF($P9="",0,$P9)-IF($Y9="",0,$Y9)) -> 950.01941 | AA9: =IF($Y9="","",$Y9) -> 80.982288 | AB9: =IF($T9="","",MAX(0,N($S9)-N($X9))) -> 703.872 | AC9: {=IF(OR($D9="",$AB9="",N($AB9)<=0),"",IFERROR(MATCH(1,INDEX(('2_Review & Audit'!$F$6:$F$505=$A9)*('2_Review & Audit'!$I$6:$I$505>=$E9-30)*('2_Review & Audit'!$I$6:$I$505<=$E9+30)*('2_Review & Audit'!$R$6:$R$505>0)*(ROW('2_Review & Audit'!$R$6:$R$505)>$T9),0),0)+5,""))} -> 37 | AD9: {=IF($AC9="","",INDEX('2_Review & Audit'!$H:$H,$AC9))} -> SCHB-20260421-70D-24D | AE9: {=IF($AC9="","",INDEX('2_Review & Audit'!$I:$I,$AC9))} -> 46133 | AF9: {=IF($AC9="","",MAX(0,INDEX('2_Review & Audit'!$J:$J,$AC9)-SUMIFS($AG$7:AG8,$AC$7:AC8,$AC9)))} -> 70 | AG9: =IF(OR($AC9="",$AF9="",$AB9=""),"",MIN($AB9,$AF9)) -> 70 | AH9: =IF($AG9="","",$AG9*$G9) -> 94.479336 | AI9: =IF($AC9="","",$H9-IF($P9="",0,$P9)-IF($Y9="",0,$Y9)-IF($AH9="",0,$AH9)) -> 855.54008 | AJ9: =IF($AH9="","",$AH9) -> 94.479336 | AK9: =IF($AC9="","",MAX(0,N($AB9)-N($AG9))) -> 633.872 | AL9: {=IF(OR($D9="",$AK9="",N($AK9)<=0),"",IFERROR(MATCH(1,INDEX(('2_Review & Audit'!$F$6:$F$505=$A9)*('2_Review & Audit'!$I$6:$I$505>=$E9-30)*('2_Review & Audit'!$I$6:$I$505<=$E9+30)*('2_Review & Audit'!$R$6:$R$505>0)*(ROW('2_Review & Audit'!$R$6:$R$505)>$AC9),0),0)+5,""))} | AM9: =IF($AL9="","",INDEX('2_Review & Audit'!$H:$H,$AL9)) | AN9: =IF($AL9="","",INDEX('2_Review & Audit'!$I:$I,$AL9)) | AO9: =IF($AL9="","",MAX(0,INDEX('2_Review & Audit'!$H:$H,$AL9)-SUMIFS($AP$7:AP8,$AL$7:AL8,$AL9))) | AP9: =IF(OR($D9="",$AK9="",$AO9=""),"",MIN($AK9,$AO9)) | AQ9: =IF($AP9="","",$AP9*$G9) | AR9: =IF($AL9="","",$H9-IF($P9="",0,$P9)-IF($Y9="",0,$Y9)-IF($AH9="",0,$AH9)-IF($AQ9="",0,$AQ9)) | AS9: =IF($AQ9="","",$AQ9) | AT9: =IF($AL9="","",IF(ABS(N($AK9)-N($AP9))<0.000001,0,MAX(0,N($AK9)-N($AP9))))
A10: =IFERROR(INDEX('2_Review & Audit'!$F$6:$F$505,MATCH(ROW()-5,'2_Review & Audit'!$AC$6:$AC$505,0)),"") -> IXUS | B10: =IF($A10="","",INDEX('2_Review & Audit'!$C$6:$C$505,MATCH(ROW()-5,'2_Review & Audit'!$AC$6:$AC$505,0))) -> International | C10: =IF($A10="","",INDEX('2_Review & Audit'!$D$6:$D$505,MATCH(ROW()-5,'2_Review & Audit'!$AC$6:$AC$505,0))) -> ETF | D10: =IF($A10="","",INDEX('2_Review & Audit'!$H$6:$H$505,MATCH(ROW()-5,'2_Review & Audit'!$AC$6:$AC$505,0))) -> IXUS-20260317-157D003-88D55 | E10: =IF($A10="","",INDEX('2_Review & Audit'!$M$6:$M$505,MATCH(ROW()-5,'2_Review & Audit'!$AC$6:$AC$505,0))) -> 46101 | F10: =IF($A10="","",IF(INDEX('2_Review & Audit'!$N$6:$N$505,MATCH(ROW()-5,'2_Review & Audit'!$AC$6:$AC$505,0))="",INDEX('2_Review & Audit'!$J$6:$J$505,MATCH(ROW()-5,'2_Review & Audit'!$AC$6:$AC$505,0))-INDEX('2_Review & Audit'!$R$6:$R$505,MATCH(ROW()-5,'2_Review & Audit'!$AC$6:$AC$505,0)),INDEX('2_Review & Audit'!$N$6:$N$505,MATCH(ROW()-5,'2_Review & Audit'!$AC$6:$AC$505,0)))) -> 157.003 | G10: =IF(OR($A10="",$F10=0),"",ABS(INDEX('2_Review & Audit'!$Q$6:$Q$505,MATCH(ROW()-5,'2_Review & Audit'!$AC$6:$AC$505,0))/$F10)) -> 5 | H10: =IF($A10="","",ABS(INDEX('2_Review & Audit'!$Q$6:$Q$505,MATCH(ROW()-5,'2_Review & Audit'!$AC$6:$AC$505,0)))) -> 785.015 | I10: =IF($A10="","",INDEX('2_Review & Audit'!$Y$6:$Y$505,MATCH(ROW()-5,'2_Review & Audit'!$AC$6:$AC$505,0))) -> Short-Term | J10: =IF($A10="","",IFERROR(MATCH(ROW()-5,'2_Review & Audit'!$AC$6:$AC$505,0)+5,"")) -> 28 | K10: {=IF($A10="","",IF($AU10<>"",IFERROR(MATCH($AU10,'2_Review & Audit'!$H$6:$H$505,0)+5,""),IFERROR(MATCH(1,INDEX(('2_Review & Audit'!$F$6:$F$505=$A10)*('2_Review & Audit'!$I$6:$I$505>=$E10-30)*('2_Review & Audit'!$I$6:$I$505<=$E10+30)*('2_Review & Audit'!$R$6:$R$505>0),0),0)+5,"")))} | L10: {=IF($K10="","",INDEX('2_Review & Audit'!$H:$H,$K10))} | M10: {=IF($K10="","",INDEX('2_Review & Audit'!$I:$I,$K10))} | N10: {=IF($K10="","",MAX(0,INDEX('2_Review & Audit'!$R:$R,$K10)-SUMIFS($O$7:O9,$K$7:K9,$K10)))} | O10: =IF(OR($K10="",$N10="",$F10=""),"",MIN($F10,$N10)) | P10: =IF($O10="","",$O10*$G10) | Q10: =IF($M10="","",$H10-IF($P10="",0,$P10)-IF($Y10="",0,$Y10)-IF($AH10="",0,$AH10)-IF($AQ10="",0,$AQ10)) | R10: =IF($M10="","",IF($P10="",0,$P10)) | S10: =IF($M10="","",MAX(0,N($F10)-N($O10))) | T10: {=IF(OR($D10="",$S10="",N($S10)<=0),"",IFERROR(MATCH(1,INDEX(('2_Review & Audit'!$F$6:$F$505=$A10)*('2_Review & Audit'!$I$6:$I$505>=$E10-30)*('2_Review & Audit'!$I$6:$I$505<=$E10+30)*('2_Review & Audit'!$R$6:$R$505>0)*(ROW('2_Review & Audit'!$R$6:$R$505)>$K10),0),0)+5,""))} | U10: {=IF($T10="","",INDEX('2_Review & Audit'!$H:$H,$T10))} | V10: {=IF($T10="","",INDEX('2_Review & Audit'!$I:$I,$T10))} | W10: {=IF($T10="","",MAX(0,INDEX('2_Review & Audit'!$J:$J,$T10)-SUMIFS($X$7:X9,$T$7:T9,$T10)))} | X10: =IF(OR($T10="",$W10="",$S10=""),"",MIN($S10,$W10)) | Y10: =IF($X10="","",$X10*$G10) | Z10: =IF($T10="","",$H10-IF($P10="",0,$P10)-IF($Y10="",0,$Y10)) | AA10: =IF($Y10="","",$Y10) | AB10: =IF($T10="","",MAX(0,N($S10)-N($X10))) | AC10: {=IF(OR($D10="",$AB10="",N($AB10)<=0),"",IFERROR(MATCH(1,INDEX(('2_Review & Audit'!$F$6:$F$505=$A10)*('2_Review & Audit'!$I$6:$I$505>=$E10-30)*('2_Review & Audit'!$I$6:$I$505<=$E10+30)*('2_Review & Audit'!$R$6:$R$505>0)*(ROW('2_Review & Audit'!$R$6:$R$505)>$T10),0),0)+5,""))} | AD10: {=IF($AC10="","",INDEX('2_Review & Audit'!$H:$H,$AC10))} | AE10: {=IF($AC10="","",INDEX('2_Review & Audit'!$I:$I,$AC10))} | AF10: {=IF($AC10="","",MAX(0,INDEX('2_Review & Audit'!$J:$J,$AC10)-SUMIFS($AG$7:AG9,$AC$7:AC9,$AC10)))} | AG10: =IF(OR($AC10="",$AF10="",$AB10=""),"",MIN($AB10,$AF10)) | AH10: =IF($AG10="","",$AG10*$G10) | AI10: =IF($AC10="","",$H10-IF($P10="",0,$P10)-IF($Y10="",0,$Y10)-IF($AH10="",0,$AH10)) | AJ10: =IF($AH10="","",$AH10) | AK10: =IF($AC10="","",MAX(0,N($AB10)-N($AG10))) | AL10: {=IF(OR($D10="",$AK10="",N($AK10)<=0),"",IFERROR(MATCH(1,INDEX(('2_Review & Audit'!$F$6:$F$505=$A10)*('2_Review & Audit'!$I$6:$I$505>=$E10-30)*('2_Review & Audit'!$I$6:$I$505<=$E10+30)*('2_Review & Audit'!$R$6:$R$505>0)*(ROW('2_Review & Audit'!$R$6:$R$505)>$AC10),0),0)+5,""))} | AM10: =IF($AL10="","",INDEX('2_Review & Audit'!$H:$H,$AL10)) | AN10: =IF($AL10="","",INDEX('2_Review & Audit'!$I:$I,$AL10)) | AO10: =IF($AL10="","",MAX(0,INDEX('2_Review & Audit'!$H:$H,$AL10)-SUMIFS($AP$7:AP9,$AL$7:AL9,$AL10))) | AP10: =IF(OR($D10="",$AK10="",$AO10=""),"",MIN($AK10,$AO10)) | AQ10: =IF($AP10="","",$AP10*$G10) | AR10: =IF($AL10="","",$H10-IF($P10="",0,$P10)-IF($Y10="",0,$Y10)-IF($AH10="",0,$AH10)-IF($AQ10="",0,$AQ10)) | AS10: =IF($AQ10="","",$AQ10) | AT10: =IF($AL10="","",IF(ABS(N($AK10)-N($AP10))<0.000001,0,MAX(0,N($AK10)-N($AP10))))
A11: =IFERROR(INDEX('2_Review & Audit'!$F$6:$F$505,MATCH(ROW()-5,'2_Review & Audit'!$AC$6:$AC$505,0)),"") -> IXUS | B11: =IF($A11="","",INDEX('2_Review & Audit'!$C$6:$C$505,MATCH(ROW()-5,'2_Review & Audit'!$AC$6:$AC$505,0))) -> International | C11: =IF($A11="","",INDEX('2_Review & Audit'!$D$6:$D$505,MATCH(ROW()-5,'2_Review & Audit'!$AC$6:$AC$505,0))) -> ETF | D11: =IF($A11="","",INDEX('2_Review & Audit'!$H$6:$H$505,MATCH(ROW()-5,'2_Review & Audit'!$AC$6:$AC$505,0))) -> IXUS-20260317-0D997-93D56 | E11: =IF($A11="","",INDEX('2_Review & Audit'!$M$6:$M$505,MATCH(ROW()-5,'2_Review & Audit'!$AC$6:$AC$505,0))) -> 46101 | F11: =IF($A11="","",IF(INDEX('2_Review & Audit'!$N$6:$N$505,MATCH(ROW()-5,'2_Review & Audit'!$AC$6:$AC$505,0))="",INDEX('2_Review & Audit'!$J$6:$J$505,MATCH(ROW()-5,'2_Review & Audit'!$AC$6:$AC$505,0))-INDEX('2_Review & Audit'!$R$6:$R$505,MATCH(ROW()-5,'2_Review & Audit'!$AC$6:$AC$505,0)),INDEX('2_Review & Audit'!$N$6:$N$505,MATCH(ROW()-5,'2_Review & Audit'!$AC$6:$AC$505,0)))) -> 0.997 | G11: =IF(OR($A11="",$F11=0),"",ABS(INDEX('2_Review & Audit'!$Q$6:$Q$505,MATCH(ROW()-5,'2_Review & Audit'!$AC$6:$AC$505,0))/$F11)) -> 10.01 | H11: =IF($A11="","",ABS(INDEX('2_Review & Audit'!$Q$6:$Q$505,MATCH(ROW()-5,'2_Review & Audit'!$AC$6:$AC$505,0)))) -> 9.97997 | I11: =IF($A11="","",INDEX('2_Review & Audit'!$Y$6:$Y$505,MATCH(ROW()-5,'2_Review & Audit'!$AC$6:$AC$505,0))) -> Short-Term | J11: =IF($A11="","",IFERROR(MATCH(ROW()-5,'2_Review & Audit'!$AC$6:$AC$505,0)+5,"")) -> 29 | K11: {=IF($A11="","",IF($AU11<>"",IFERROR(MATCH($AU11,'2_Review & Audit'!$H$6:$H$505,0)+5,""),IFERROR(MATCH(1,INDEX(('2_Review & Audit'!$F$6:$F$505=$A11)*('2_Review & Audit'!$I$6:$I$505>=$E11-30)*('2_Review & Audit'!$I$6:$I$505<=$E11+30)*('2_Review & Audit'!$R$6:$R$505>0),0),0)+5,"")))} | L11: {=IF($K11="","",INDEX('2_Review & Audit'!$H:$H,$K11))} | M11: {=IF($K11="","",INDEX('2_Review & Audit'!$I:$I,$K11))} | N11: {=IF($K11="","",MAX(0,INDEX('2_Review & Audit'!$R:$R,$K11)-SUMIFS($O$7:O10,$K$7:K10,$K11)))} | O11: =IF(OR($K11="",$N11="",$F11=""),"",MIN($F11,$N11)) | P11: =IF($O11="","",$O11*$G11) | Q11: =IF($M11="","",$H11-IF($P11="",0,$P11)-IF($Y11="",0,$Y11)-IF($AH11="",0,$AH11)-IF($AQ11="",0,$AQ11)) | R11: =IF($M11="","",IF($P11="",0,$P11)) | S11: =IF($M11="","",MAX(0,N($F11)-N($O11))) | T11: {=IF(OR($D11="",$S11="",N($S11)<=0),"",IFERROR(MATCH(1,INDEX(('2_Review & Audit'!$F$6:$F$505=$A11)*('2_Review & Audit'!$I$6:$I$505>=$E11-30)*('2_Review & Audit'!$I$6:$I$505<=$E11+30)*('2_Review & Audit'!$R$6:$R$505>0)*(ROW('2_Review & Audit'!$R$6:$R$505)>$K11),0),0)+5,""))} | U11: {=IF($T11="","",INDEX('2_Review & Audit'!$H:$H,$T11))} | V11: {=IF($T11="","",INDEX('2_Review & Audit'!$I:$I,$T11))} | W11: {=IF($T11="","",MAX(0,INDEX('2_Review & Audit'!$J:$J,$T11)-SUMIFS($X$7:X10,$T$7:T10,$T11)))} | X11: =IF(OR($T11="",$W11="",$S11=""),"",MIN($S11,$W11)) | Y11: =IF($X11="","",$X11*$G11) | Z11: =IF($T11="","",$H11-IF($P11="",0,$P11)-IF($Y11="",0,$Y11)) | AA11: =IF($Y11="","",$Y11) | AB11: =IF($T11="","",MAX(0,N($S11)-N($X11))) | AC11: {=IF(OR($D11="",$AB11="",N($AB11)<=0),"",IFERROR(MATCH(1,INDEX(('2_Review & Audit'!$F$6:$F$505=$A11)*('2_Review & Audit'!$I$6:$I$505>=$E11-30)*('2_Review & Audit'!$I$6:$I$505<=$E11+30)*('2_Review & Audit'!$R$6:$R$505>0)*(ROW('2_Review & Audit'!$R$6:$R$505)>$T11),0),0)+5,""))} | AD11: {=IF($AC11="","",INDEX('2_Review & Audit'!$H:$H,$AC11))} | AE11: {=IF($AC11="","",INDEX('2_Review & Audit'!$I:$I,$AC11))} | AF11: {=IF($AC11="","",MAX(0,INDEX('2_Review & Audit'!$J:$J,$AC11)-SUMIFS($AG$7:AG10,$AC$7:AC10,$AC11)))} | AG11: =IF(OR($AC11="",$AF11="",$AB11=""),"",MIN($AB11,$AF11)) | AH11: =IF($AG11="","",$AG11*$G11) | AI11: =IF($AC11="","",$H11-IF($P11="",0,$P11)-IF($Y11="",0,$Y11)-IF($AH11="",0,$AH11)) | AJ11: =IF($AH11="","",$AH11) | AK11: =IF($AC11="","",MAX(0,N($AB11)-N($AG11))) | AL11: {=IF(OR($D11="",$AK11="",N($AK11)<=0),"",IFERROR(MATCH(1,INDEX(('2_Review & Audit'!$F$6:$F$505=$A11)*('2_Review & Audit'!$I$6:$I$505>=$E11-30)*('2_Review & Audit'!$I$6:$I$505<=$E11+30)*('2_Review & Audit'!$R$6:$R$505>0)*(ROW('2_Review & Audit'!$R$6:$R$505)>$AC11),0),0)+5,""))} | AM11: =IF($AL11="","",INDEX('2_Review & Audit'!$H:$H,$AL11)) | AN11: =IF($AL11="","",INDEX('2_Review & Audit'!$I:$I,$AL11)) | AO11: =IF($AL11="","",MAX(0,INDEX('2_Review & Audit'!$H:$H,$AL11)-SUMIFS($AP$7:AP10,$AL$7:AL10,$AL11))) | AP11: =IF(OR($D11="",$AK11="",$AO11=""),"",MIN($AK11,$AO11)) | AQ11: =IF($AP11="","",$AP11*$G11) | AR11: =IF($AL11="","",$H11-IF($P11="",0,$P11)-IF($Y11="",0,$Y11)-IF($AH11="",0,$AH11)-IF($AQ11="",0,$AQ11)) | AS11: =IF($AQ11="","",$AQ11) | AT11: =IF($AL11="","",IF(ABS(N($AK11)-N($AP11))<0.000001,0,MAX(0,N($AK11)-N($AP11))))
A12: =IFERROR(INDEX('2_Review & Audit'!$F$6:$F$505,MATCH(ROW()-5,'2_Review & Audit'!$AC$6:$AC$505,0)),"") | B12: =IF($A12="","",INDEX('2_Review & Audit'!$C$6:$C$505,MATCH(ROW()-5,'2_Review & Audit'!$AC$6:$AC$505,0))) | C12: =IF($A12="","",INDEX('2_Review & Audit'!$D$6:$D$505,MATCH(ROW()-5,'2_Review & Audit'!$AC$6:$AC$505,0))) | D12: =IF($A12="","",INDEX('2_Review & Audit'!$H$6:$H$505,MATCH(ROW()-5,'2_Review & Audit'!$AC$6:$AC$505,0))) | E12: =IF($A12="","",INDEX('2_Review & Audit'!$M$6:$M$505,MATCH(ROW()-5,'2_Review & Audit'!$AC$6:$AC$505,0))) | F12: =IF($A12="","",IF(INDEX('2_Review & Audit'!$N$6:$N$505,MATCH(ROW()-5,'2_Review & Audit'!$AC$6:$AC$505,0))="",INDEX('2_Review & Audit'!$J$6:$J$505,MATCH(ROW()-5,'2_Review & Audit'!$AC$6:$AC$505,0))-INDEX('2_Review & Audit'!$R$6:$R$505,MATCH(ROW()-5,'2_Review & Audit'!$AC$6:$AC$505,0)),INDEX('2_Review & Audit'!$N$6:$N$505,MATCH(ROW()-5,'2_Review & Audit'!$AC$6:$AC$505,0)))) | G12: =IF(OR($A12="",$F12=0),"",ABS(INDEX('2_Review & Audit'!$Q$6:$Q$505,MATCH(ROW()-5,'2_Review & Audit'!$AC$6:$AC$505,0))/$F12)) | H12: =IF($A12="","",ABS(INDEX('2_Review & Audit'!$Q$6:$Q$505,MATCH(ROW()-5,'2_Review & Audit'!$AC$6:$AC$505,0)))) | I12: =IF($A12="","",INDEX('2_Review & Audit'!$Y$6:$Y$505,MATCH(ROW()-5,'2_Review & Audit'!$AC$6:$AC$505,0))) | J12: =IF($A12="","",IFERROR(MATCH(ROW()-5,'2_Review & Audit'!$AC$6:$AC$505,0)+5,"")) | K12: {=IF($A12="","",IF($AU12<>"",IFERROR(MATCH($AU12,'2_Review & Audit'!$H$6:$H$505,0)+5,""),IFERROR(MATCH(1,INDEX(('2_Review & Audit'!$F$6:$F$505=$A12)*('2_Review & Audit'!$I$6:$I$505>=$E12-30)*('2_Review & Audit'!$I$6:$I$505<=$E12+30)*('2_Review & Audit'!$R$6:$R$505>0),0),0)+5,"")))} | L12: {=IF($K12="","",INDEX('2_Review & Audit'!$H:$H,$K12))} | M12: {=IF($K12="","",INDEX('2_Review & Audit'!$I:$I,$K12))} | N12: {=IF($K12="","",MAX(0,INDEX('2_Review & Audit'!$R:$R,$K12)-SUMIFS($O$7:O11,$K$7:K11,$K12)))} | O12: =IF(OR($K12="",$N12="",$F12=""),"",MIN($F12,$N12)) | P12: =IF($O12="","",$O12*$G12) | Q12: =IF($M12="","",$H12-IF($P12="",0,$P12)-IF($Y12="",0,$Y12)-IF($AH12="",0,$AH12)-IF($AQ12="",0,$AQ12)) | R12: =IF($M12="","",IF($P12="",0,$P12)) | S12: =IF($M12="","",MAX(0,N($F12)-N($O12))) | T12: {=IF(OR($D12="",$S12="",N($S12)<=0),"",IFERROR(MATCH(1,INDEX(('2_Review & Audit'!$F$6:$F$505=$A12)*('2_Review & Audit'!$I$6:$I$505>=$E12-30)*('2_Review & Audit'!$I$6:$I$505<=$E12+30)*('2_Review & Audit'!$R$6:$R$505>0)*(ROW('2_Review & Audit'!$R$6:$R$505)>$K12),0),0)+5,""))} | U12: {=IF($T12="","",INDEX('2_Review & Audit'!$H:$H,$T12))} | V12: {=IF($T12="","",INDEX('2_Review & Audit'!$I:$I,$T12))} | W12: {=IF($T12="","",MAX(0,INDEX('2_Review & Audit'!$J:$J,$T12)-SUMIFS($X$7:X11,$T$7:T11,$T12)))} | X12: =IF(OR($T12="",$W12="",$S12=""),"",MIN($S12,$W12)) | Y12: =IF($X12="","",$X12*$G12) | Z12: =IF($T12="","",$H12-IF($P12="",0,$P12)-IF($Y12="",0,$Y12)) | AA12: =IF($Y12="","",$Y12) | AB12: =IF($T12="","",MAX(0,N($S12)-N($X12))) | AC12: {=IF(OR($D12="",$AB12="",N($AB12)<=0),"",IFERROR(MATCH(1,INDEX(('2_Review & Audit'!$F$6:$F$505=$A12)*('2_Review & Audit'!$I$6:$I$505>=$E12-30)*('2_Review & Audit'!$I$6:$I$505<=$E12+30)*('2_Review & Audit'!$R$6:$R$505>0)*(ROW('2_Review & Audit'!$R$6:$R$505)>$T12),0),0)+5,""))} | AD12: {=IF($AC12="","",INDEX('2_Review & Audit'!$H:$H,$AC12))} | AE12: {=IF($AC12="","",INDEX('2_Review & Audit'!$I:$I,$AC12))} | AF12: {=IF($AC12="","",MAX(0,INDEX('2_Review & Audit'!$J:$J,$AC12)-SUMIFS($AG$7:AG11,$AC$7:AC11,$AC12)))} | AG12: =IF(OR($AC12="",$AF12="",$AB12=""),"",MIN($AB12,$AF12)) | AH12: =IF($AG12="","",$AG12*$G12) | AI12: =IF($AC12="","",$H12-IF($P12="",0,$P12)-IF($Y12="",0,$Y12)-IF($AH12="",0,$AH12)) | AJ12: =IF($AH12="","",$AH12) | AK12: =IF($AC12="","",MAX(0,N($AB12)-N($AG12))) | AL12: {=IF(OR($D12="",$AK12="",N($AK12)<=0),"",IFERROR(MATCH(1,INDEX(('2_Review & Audit'!$F$6:$F$505=$A12)*('2_Review & Audit'!$I$6:$I$505>=$E12-30)*('2_Review & Audit'!$I$6:$I$505<=$E12+30)*('2_Review & Audit'!$R$6:$R$505>0)*(ROW('2_Review & Audit'!$R$6:$R$505)>$AC12),0),0)+5,""))} | AM12: =IF($AL12="","",INDEX('2_Review & Audit'!$H:$H,$AL12)) | AN12: =IF($AL12="","",INDEX('2_Review & Audit'!$I:$I,$AL12)) | AO12: =IF($AL12="","",MAX(0,INDEX('2_Review & Audit'!$H:$H,$AL12)-SUMIFS($AP$7:AP11,$AL$7:AL11,$AL12))) | AP12: =IF(OR($D12="",$AK12="",$AO12=""),"",MIN($AK12,$AO12)) | AQ12: =IF($AP12="","",$AP12*$G12) | AR12: =IF($AL12="","",$H12-IF($P12="",0,$P12)-IF($Y12="",0,$Y12)-IF($AH12="",0,$AH12)-IF($AQ12="",0,$AQ12)) | AS12: =IF($AQ12="","",$AQ12) | AT12: =IF($AL12="","",IF(ABS(N($AK12)-N($AP12))<0.000001,0,MAX(0,N($AK12)-N($AP12))))
A13: =IFERROR(INDEX('2_Review & Audit'!$F$6:$F$505,MATCH(ROW()-5,'2_Review & Audit'!$AC$6:$AC$505,0)),"") | B13: =IF($A13="","",INDEX('2_Review & Audit'!$C$6:$C$505,MATCH(ROW()-5,'2_Review & Audit'!$AC$6:$AC$505,0))) | C13: =IF($A13="","",INDEX('2_Review & Audit'!$D$6:$D$505,MATCH(ROW()-5,'2_Review & Audit'!$AC$6:$AC$505,0))) | D13: =IF($A13="","",INDEX('2_Review & Audit'!$H$6:$H$505,MATCH(ROW()-5,'2_Review & Audit'!$AC$6:$AC$505,0))) | E13: =IF($A13="","",INDEX('2_Review & Audit'!$M$6:$M$505,MATCH(ROW()-5,'2_Review & Audit'!$AC$6:$AC$505,0))) | F13: =IF($A13="","",IF(INDEX('2_Review & Audit'!$N$6:$N$505,MATCH(ROW()-5,'2_Review & Audit'!$AC$6:$AC$505,0))="",INDEX('2_Review & Audit'!$J$6:$J$505,MATCH(ROW()-5,'2_Review & Audit'!$AC$6:$AC$505,0))-INDEX('2_Review & Audit'!$R$6:$R$505,MATCH(ROW()-5,'2_Review & Audit'!$AC$6:$AC$505,0)),INDEX('2_Review & Audit'!$N$6:$N$505,MATCH(ROW()-5,'2_Review & Audit'!$AC$6:$AC$505,0)))) | G13: =IF(OR($A13="",$F13=0),"",ABS(INDEX('2_Review & Audit'!$Q$6:$Q$505,MATCH(ROW()-5,'2_Review & Audit'!$AC$6:$AC$505,0))/$F13)) | H13: =IF($A13="","",ABS(INDEX('2_Review & Audit'!$Q$6:$Q$505,MATCH(ROW()-5,'2_Review & Audit'!$AC$6:$AC$505,0)))) | I13: =IF($A13="","",INDEX('2_Review & Audit'!$Y$6:$Y$505,MATCH(ROW()-5,'2_Review & Audit'!$AC$6:$AC$505,0))) | J13: =IF($A13="","",IFERROR(MATCH(ROW()-5,'2_Review & Audit'!$AC$6:$AC$505,0)+5,"")) | K13: {=IF($A13="","",IF($AU13<>"",IFERROR(MATCH($AU13,'2_Review & Audit'!$H$6:$H$505,0)+5,""),IFERROR(MATCH(1,INDEX(('2_Review & Audit'!$F$6:$F$505=$A13)*('2_Review & Audit'!$I$6:$I$505>=$E13-30)*('2_Review & Audit'!$I$6:$I$505<=$E13+30)*('2_Review & Audit'!$R$6:$R$505>0),0),0)+5,"")))} | L13: {=IF($K13="","",INDEX('2_Review & Audit'!$H:$H,$K13))} | M13: {=IF($K13="","",INDEX('2_Review & Audit'!$I:$I,$K13))} | N13: {=IF($K13="","",MAX(0,INDEX('2_Review & Audit'!$R:$R,$K13)-SUMIFS($O$7:O12,$K$7:K12,$K13)))} | O13: =IF(OR($K13="",$N13="",$F13=""),"",MIN($F13,$N13)) | P13: =IF($O13="","",$O13*$G13) | Q13: =IF($M13="","",$H13-IF($P13="",0,$P13)-IF($Y13="",0,$Y13)-IF($AH13="",0,$AH13)-IF($AQ13="",0,$AQ13)) | R13: =IF($M13="","",IF($P13="",0,$P13)) | S13: =IF($M13="","",MAX(0,N($F13)-N($O13))) | T13: {=IF(OR($D13="",$S13="",N($S13)<=0),"",IFERROR(MATCH(1,INDEX(('2_Review & Audit'!$F$6:$F$505=$A13)*('2_Review & Audit'!$I$6:$I$505>=$E13-30)*('2_Review & Audit'!$I$6:$I$505<=$E13+30)*('2_Review & Audit'!$R$6:$R$505>0)*(ROW('2_Review & Audit'!$R$6:$R$505)>$K13),0),0)+5,""))} | U13: {=IF($T13="","",INDEX('2_Review & Audit'!$H:$H,$T13))} | V13: {=IF($T13="","",INDEX('2_Review & Audit'!$I:$I,$T13))} | W13: {=IF($T13="","",MAX(0,INDEX('2_Review & Audit'!$J:$J,$T13)-SUMIFS($X$7:X12,$T$7:T12,$T13)))} | X13: =IF(OR($T13="",$W13="",$S13=""),"",MIN($S13,$W13)) | Y13: =IF($X13="","",$X13*$G13) | Z13: =IF($T13="","",$H13-IF($P13="",0,$P13)-IF($Y13="",0,$Y13)) | AA13: =IF($Y13="","",$Y13) | AB13: =IF($T13="","",MAX(0,N($S13)-N($X13))) | AC13: {=IF(OR($D13="",$AB13="",N($AB13)<=0),"",IFERROR(MATCH(1,INDEX(('2_Review & Audit'!$F$6:$F$505=$A13)*('2_Review & Audit'!$I$6:$I$505>=$E13-30)*('2_Review & Audit'!$I$6:$I$505<=$E13+30)*('2_Review & Audit'!$R$6:$R$505>0)*(ROW('2_Review & Audit'!$R$6:$R$505)>$T13),0),0)+5,""))} | AD13: {=IF($AC13="","",INDEX('2_Review & Audit'!$H:$H,$AC13))} | AE13: {=IF($AC13="","",INDEX('2_Review & Audit'!$I:$I,$AC13))} | AF13: {=IF($AC13="","",MAX(0,INDEX('2_Review & Audit'!$J:$J,$AC13)-SUMIFS($AG$7:AG12,$AC$7:AC12,$AC13)))} | AG13: =IF(OR($AC13="",$AF13="",$AB13=""),"",MIN($AB13,$AF13)) | AH13: =IF($AG13="","",$AG13*$G13) | AI13: =IF($AC13="","",$H13-IF($P13="",0,$P13)-IF($Y13="",0,$Y13)-IF($AH13="",0,$AH13)) | AJ13: =IF($AH13="","",$AH13) | AK13: =IF($AC13="","",MAX(0,N($AB13)-N($AG13))) | AL13: {=IF(OR($D13="",$AK13="",N($AK13)<=0),"",IFERROR(MATCH(1,INDEX(('2_Review & Audit'!$F$6:$F$505=$A13)*('2_Review & Audit'!$I$6:$I$505>=$E13-30)*('2_Review & Audit'!$I$6:$I$505<=$E13+30)*('2_Review & Audit'!$R$6:$R$505>0)*(ROW('2_Review & Audit'!$R$6:$R$505)>$AC13),0),0)+5,""))} | AM13: =IF($AL13="","",INDEX('2_Review & Audit'!$H:$H,$AL13)) | AN13: =IF($AL13="","",INDEX('2_Review & Audit'!$I:$I,$AL13)) | AO13: =IF($AL13="","",MAX(0,INDEX('2_Review & Audit'!$H:$H,$AL13)-SUMIFS($AP$7:AP12,$AL$7:AL12,$AL13))) | AP13: =IF(OR($D13="",$AK13="",$AO13=""),"",MIN($AK13,$AO13)) | AQ13: =IF($AP13="","",$AP13*$G13) | AR13: =IF($AL13="","",$H13-IF($P13="",0,$P13)-IF($Y13="",0,$Y13)-IF($AH13="",0,$AH13)-IF($AQ13="",0,$AQ13)) | AS13: =IF($AQ13="","",$AQ13) | AT13: =IF($AL13="","",IF(ABS(N($AK13)-N($AP13))<0.000001,0,MAX(0,N($AK13)-N($AP13))))
A14: =IFERROR(INDEX('2_Review & Audit'!$F$6:$F$505,MATCH(ROW()-5,'2_Review & Audit'!$AC$6:$AC$505,0)),"") | B14: =IF($A14="","",INDEX('2_Review & Audit'!$C$6:$C$505,MATCH(ROW()-5,'2_Review & Audit'!$AC$6:$AC$505,0))) | C14: =IF($A14="","",INDEX('2_Review & Audit'!$D$6:$D$505,MATCH(ROW()-5,'2_Review & Audit'!$AC$6:$AC$505,0))) | D14: =IF($A14="","",INDEX('2_Review & Audit'!$H$6:$H$505,MATCH(ROW()-5,'2_Review & Audit'!$AC$6:$AC$505,0))) | E14: =IF($A14="","",INDEX('2_Review & Audit'!$M$6:$M$505,MATCH(ROW()-5,'2_Review & Audit'!$AC$6:$AC$505,0))) | F14: =IF($A14="","",IF(INDEX('2_Review & Audit'!$N$6:$N$505,MATCH(ROW()-5,'2_Review & Audit'!$AC$6:$AC$505,0))="",INDEX('2_Review & Audit'!$J$6:$J$505,MATCH(ROW()-5,'2_Review & Audit'!$AC$6:$AC$505,0))-INDEX('2_Review & Audit'!$R$6:$R$505,MATCH(ROW()-5,'2_Review & Audit'!$AC$6:$AC$505,0)),INDEX('2_Review & Audit'!$N$6:$N$505,MATCH(ROW()-5,'2_Review & Audit'!$AC$6:$AC$505,0)))) | G14: =IF(OR($A14="",$F14=0),"",ABS(INDEX('2_Review & Audit'!$Q$6:$Q$505,MATCH(ROW()-5,'2_Review & Audit'!$AC$6:$AC$505,0))/$F14)) | H14: =IF($A14="","",ABS(INDEX('2_Review & Audit'!$Q$6:$Q$505,MATCH(ROW()-5,'2_Review & Audit'!$AC$6:$AC$505,0)))) | I14: =IF($A14="","",INDEX('2_Review & Audit'!$Y$6:$Y$505,MATCH(ROW()-5,'2_Review & Audit'!$AC$6:$AC$505,0))) | J14: =IF($A14="","",IFERROR(MATCH(ROW()-5,'2_Review & Audit'!$AC$6:$AC$505,0)+5,"")) | K14: {=IF($A14="","",IF($AU14<>"",IFERROR(MATCH($AU14,'2_Review & Audit'!$H$6:$H$505,0)+5,""),IFERROR(MATCH(1,INDEX(('2_Review & Audit'!$F$6:$F$505=$A14)*('2_Review & Audit'!$I$6:$I$505>=$E14-30)*('2_Review & Audit'!$I$6:$I$505<=$E14+30)*('2_Review & Audit'!$R$6:$R$505>0),0),0)+5,"")))} | L14: {=IF($K14="","",INDEX('2_Review & Audit'!$H:$H,$K14))} | M14: {=IF($K14="","",INDEX('2_Review & Audit'!$I:$I,$K14))} | N14: {=IF($K14="","",MAX(0,INDEX('2_Review & Audit'!$R:$R,$K14)-SUMIFS($O$7:O13,$K$7:K13,$K14)))} | O14: =IF(OR($K14="",$N14="",$F14=""),"",MIN($F14,$N14)) | P14: =IF($O14="","",$O14*$G14) | Q14: =IF($M14="","",$H14-IF($P14="",0,$P14)-IF($Y14="",0,$Y14)-IF($AH14="",0,$AH14)-IF($AQ14="",0,$AQ14)) | R14: =IF($M14="","",IF($P14="",0,$P14)) | S14: =IF($M14="","",MAX(0,N($F14)-N($O14))) | T14: {=IF(OR($D14="",$S14="",N($S14)<=0),"",IFERROR(MATCH(1,INDEX(('2_Review & Audit'!$F$6:$F$505=$A14)*('2_Review & Audit'!$I$6:$I$505>=$E14-30)*('2_Review & Audit'!$I$6:$I$505<=$E14+30)*('2_Review & Audit'!$R$6:$R$505>0)*(ROW('2_Review & Audit'!$R$6:$R$505)>$K14),0),0)+5,""))} | U14: {=IF($T14="","",INDEX('2_Review & Audit'!$H:$H,$T14))} | V14: {=IF($T14="","",INDEX('2_Review & Audit'!$I:$I,$T14))} | W14: {=IF($T14="","",MAX(0,INDEX('2_Review & Audit'!$J:$J,$T14)-SUMIFS($X$7:X13,$T$7:T13,$T14)))} | X14: =IF(OR($T14="",$W14="",$S14=""),"",MIN($S14,$W14)) | Y14: =IF($X14="","",$X14*$G14) | Z14: =IF($T14="","",$H14-IF($P14="",0,$P14)-IF($Y14="",0,$Y14)) | AA14: =IF($Y14="","",$Y14) | AB14: =IF($T14="","",MAX(0,N($S14)-N($X14))) | AC14: {=IF(OR($D14="",$AB14="",N($AB14)<=0),"",IFERROR(MATCH(1,INDEX(('2_Review & Audit'!$F$6:$F$505=$A14)*('2_Review & Audit'!$I$6:$I$505>=$E14-30)*('2_Review & Audit'!$I$6:$I$505<=$E14+30)*('2_Review & Audit'!$R$6:$R$505>0)*(ROW('2_Review & Audit'!$R$6:$R$505)>$T14),0),0)+5,""))} | AD14: {=IF($AC14="","",INDEX('2_Review & Audit'!$H:$H,$AC14))} | AE14: {=IF($AC14="","",INDEX('2_Review & Audit'!$I:$I,$AC14))} | AF14: {=IF($AC14="","",MAX(0,INDEX('2_Review & Audit'!$J:$J,$AC14)-SUMIFS($AG$7:AG13,$AC$7:AC13,$AC14)))} | AG14: =IF(OR($AC14="",$AF14="",$AB14=""),"",MIN($AB14,$AF14)) | AH14: =IF($AG14="","",$AG14*$G14) | AI14: =IF($AC14="","",$H14-IF($P14="",0,$P14)-IF($Y14="",0,$Y14)-IF($AH14="",0,$AH14)) | AJ14: =IF($AH14="","",$AH14) | AK14: =IF($AC14="","",MAX(0,N($AB14)-N($AG14))) | AL14: {=IF(OR($D14="",$AK14="",N($AK14)<=0),"",IFERROR(MATCH(1,INDEX(('2_Review & Audit'!$F$6:$F$505=$A14)*('2_Review & Audit'!$I$6:$I$505>=$E14-30)*('2_Review & Audit'!$I$6:$I$505<=$E14+30)*('2_Review & Audit'!$R$6:$R$505>0)*(ROW('2_Review & Audit'!$R$6:$R$505)>$AC14),0),0)+5,""))} | AM14: =IF($AL14="","",INDEX('2_Review & Audit'!$H:$H,$AL14)) | AN14: =IF($AL14="","",INDEX('2_Review & Audit'!$I:$I,$AL14)) | AO14: =IF($AL14="","",MAX(0,INDEX('2_Review & Audit'!$H:$H,$AL14)-SUMIFS($AP$7:AP13,$AL$7:AL13,$AL14))) | AP14: =IF(OR($D14="",$AK14="",$AO14=""),"",MIN($AK14,$AO14)) | AQ14: =IF($AP14="","",$AP14*$G14) | AR14: =IF($AL14="","",$H14-IF($P14="",0,$P14)-IF($Y14="",0,$Y14)-IF($AH14="",0,$AH14)-IF($AQ14="",0,$AQ14)) | AS14: =IF($AQ14="","",$AQ14) | AT14: =IF($AL14="","",IF(ABS(N($AK14)-N($AP14))<0.000001,0,MAX(0,N($AK14)-N($AP14))))
A15: =IFERROR(INDEX('2_Review & Audit'!$F$6:$F$505,MATCH(ROW()-5,'2_Review & Audit'!$AC$6:$AC$505,0)),"") | B15: =IF($A15="","",INDEX('2_Review & Audit'!$C$6:$C$505,MATCH(ROW()-5,'2_Review & Audit'!$AC$6:$AC$505,0))) | C15: =IF($A15="","",INDEX('2_Review & Audit'!$D$6:$D$505,MATCH(ROW()-5,'2_Review & Audit'!$AC$6:$AC$505,0))) | D15: =IF($A15="","",INDEX('2_Review & Audit'!$H$6:$H$505,MATCH(ROW()-5,'2_Review & Audit'!$AC$6:$AC$505,0))) | E15: =IF($A15="","",INDEX('2_Review & Audit'!$M$6:$M$505,MATCH(ROW()-5,'2_Review & Audit'!$AC$6:$AC$505,0))) | F15: =IF($A15="","",IF(INDEX('2_Review & Audit'!$N$6:$N$505,MATCH(ROW()-5,'2_Review & Audit'!$AC$6:$AC$505,0))="",INDEX('2_Review & Audit'!$J$6:$J$505,MATCH(ROW()-5,'2_Review & Audit'!$AC$6:$AC$505,0))-INDEX('2_Review & Audit'!$R$6:$R$505,MATCH(ROW()-5,'2_Review & Audit'!$AC$6:$AC$505,0)),INDEX('2_Review & Audit'!$N$6:$N$505,MATCH(ROW()-5,'2_Review & Audit'!$AC$6:$AC$505,0)))) | G15: =IF(OR($A15="",$F15=0),"",ABS(INDEX('2_Review & Audit'!$Q$6:$Q$505,MATCH(ROW()-5,'2_Review & Audit'!$AC$6:$AC$505,0))/$F15)) | H15: =IF($A15="","",ABS(INDEX('2_Review & Audit'!$Q$6:$Q$505,MATCH(ROW()-5,'2_Review & Audit'!$AC$6:$AC$505,0)))) | I15: =IF($A15="","",INDEX('2_Review & Audit'!$Y$6:$Y$505,MATCH(ROW()-5,'2_Review & Audit'!$AC$6:$AC$505,0))) | J15: =IF($A15="","",IFERROR(MATCH(ROW()-5,'2_Review & Audit'!$AC$6:$AC$505,0)+5,"")) | K15: {=IF($A15="","",IF($AU15<>"",IFERROR(MATCH($AU15,'2_Review & Audit'!$H$6:$H$505,0)+5,""),IFERROR(MATCH(1,INDEX(('2_Review & Audit'!$F$6:$F$505=$A15)*('2_Review & Audit'!$I$6:$I$505>=$E15-30)*('2_Review & Audit'!$I$6:$I$505<=$E15+30)*('2_Review & Audit'!$R$6:$R$505>0),0),0)+5,"")))} | L15: {=IF($K15="","",INDEX('2_Review & Audit'!$H:$H,$K15))} | M15: {=IF($K15="","",INDEX('2_Review & Audit'!$I:$I,$K15))} | N15: {=IF($K15="","",MAX(0,INDEX('2_Review & Audit'!$R:$R,$K15)-SUMIFS($O$7:O14,$K$7:K14,$K15)))} | O15: =IF(OR($K15="",$N15="",$F15=""),"",MIN($F15,$N15)) | P15: =IF($O15="","",$O15*$G15) | Q15: =IF($M15="","",$H15-IF($P15="",0,$P15)-IF($Y15="",0,$Y15)-IF($AH15="",0,$AH15)-IF($AQ15="",0,$AQ15)) | R15: =IF($M15="","",IF($P15="",0,$P15)) | S15: =IF($M15="","",MAX(0,N($F15)-N($O15))) | T15: {=IF(OR($D15="",$S15="",N($S15)<=0),"",IFERROR(MATCH(1,INDEX(('2_Review & Audit'!$F$6:$F$505=$A15)*('2_Review & Audit'!$I$6:$I$505>=$E15-30)*('2_Review & Audit'!$I$6:$I$505<=$E15+30)*('2_Review & Audit'!$R$6:$R$505>0)*(ROW('2_Review & Audit'!$R$6:$R$505)>$K15),0),0)+5,""))} | U15: {=IF($T15="","",INDEX('2_Review & Audit'!$H:$H,$T15))} | V15: {=IF($T15="","",INDEX('2_Review & Audit'!$I:$I,$T15))} | W15: {=IF($T15="","",MAX(0,INDEX('2_Review & Audit'!$J:$J,$T15)-SUMIFS($X$7:X14,$T$7:T14,$T15)))} | X15: =IF(OR($T15="",$W15="",$S15=""),"",MIN($S15,$W15)) | Y15: =IF($X15="","",$X15*$G15) | Z15: =IF($T15="","",$H15-IF($P15="",0,$P15)-IF($Y15="",0,$Y15)) | AA15: =IF($Y15="","",$Y15) | AB15: =IF($T15="","",MAX(0,N($S15)-N($X15))) | AC15: {=IF(OR($D15="",$AB15="",N($AB15)<=0),"",IFERROR(MATCH(1,INDEX(('2_Review & Audit'!$F$6:$F$505=$A15)*('2_Review & Audit'!$I$6:$I$505>=$E15-30)*('2_Review & Audit'!$I$6:$I$505<=$E15+30)*('2_Review & Audit'!$R$6:$R$505>0)*(ROW('2_Review & Audit'!$R$6:$R$505)>$T15),0),0)+5,""))} | AD15: {=IF($AC15="","",INDEX('2_Review & Audit'!$H:$H,$AC15))} | AE15: {=IF($AC15="","",INDEX('2_Review & Audit'!$I:$I,$AC15))} | AF15: {=IF($AC15="","",MAX(0,INDEX('2_Review & Audit'!$J:$J,$AC15)-SUMIFS($AG$7:AG14,$AC$7:AC14,$AC15)))} | AG15: =IF(OR($AC15="",$AF15="",$AB15=""),"",MIN($AB15,$AF15)) | AH15: =IF($AG15="","",$AG15*$G15) | AI15: =IF($AC15="","",$H15-IF($P15="",0,$P15)-IF($Y15="",0,$Y15)-IF($AH15="",0,$AH15)) | AJ15: =IF($AH15="","",$AH15) | AK15: =IF($AC15="","",MAX(0,N($AB15)-N($AG15))) | AL15: {=IF(OR($D15="",$AK15="",N($AK15)<=0),"",IFERROR(MATCH(1,INDEX(('2_Review & Audit'!$F$6:$F$505=$A15)*('2_Review & Audit'!$I$6:$I$505>=$E15-30)*('2_Review & Audit'!$I$6:$I$505<=$E15+30)*('2_Review & Audit'!$R$6:$R$505>0)*(ROW('2_Review & Audit'!$R$6:$R$505)>$AC15),0),0)+5,""))} | AM15: =IF($AL15="","",INDEX('2_Review & Audit'!$H:$H,$AL15)) | AN15: =IF($AL15="","",INDEX('2_Review & Audit'!$I:$I,$AL15)) | AO15: =IF($AL15="","",MAX(0,INDEX('2_Review & Audit'!$H:$H,$AL15)-SUMIFS($AP$7:AP14,$AL$7:AL14,$AL15))) | AP15: =IF(OR($D15="",$AK15="",$AO15=""),"",MIN($AK15,$AO15)) | AQ15: =IF($AP15="","",$AP15*$G15) | AR15: =IF($AL15="","",$H15-IF($P15="",0,$P15)-IF($Y15="",0,$Y15)-IF($AH15="",0,$AH15)-IF($AQ15="",0,$AQ15)) | AS15: =IF($AQ15="","",$AQ15) | AT15: =IF($AL15="","",IF(ABS(N($AK15)-N($AP15))<0.000001,0,MAX(0,N($AK15)-N($AP15))))
